Workbook
Name CostOfEquity: WACC!$C$16
Name DCF_ValuePerShare: DCF!$E$83
Name EV_DCF: DCF!$E$73
Name ImpliedMargin: Reverse_DCF!$C$6
Name ModelStatus: Checks!$D$3
Name PeerValuePerShare: Comps!$H$33
Name Recommendation: DCF!$E$114
Name RevenueMode: Inputs!$C$72
Name Scenario: Inputs!$C$53
Name SharePrice: Inputs!$C$27
Name TargetPrice: DCF!$E$109
Name TerminalGrowth: Drivers!$H$91
Name WACC_used: WACC!$C$34

Sheet Cover
D7: =Inputs!$C$6 -> Example Company ASA
D8: DCF Valuation Model
D10: =Inputs!$C$7&" | "&Inputs!$C$8&" | "&Inputs!$C$9&" | figures in "&Inputs!$C$11 -> EXMPL | Oslo Børs | Consumer services | figures in NOKm
D12: =DCF!$E$114&" – target price NOK "&TEXT(DCF!$E$109,"0")&" ("&TEXT(DCF!$E$110,"+0%;-0%")&" upside) | scenario: "&Inputs!$C$53 -> BUY – target price NOK 146 (+20% upside) | scenario: Base
D13: ="Model status: "&Checks!$D$3 -> Model status: ALL CHECKS OK
D14: All company data in this file is FICTIONAL example data – replace the blue inputs with your case data.
D15: =Inputs!$C$12 -> [Case team name]
D17: Model map (click a sheet name to open it) | H17: Colour legend
D18: Guide | E18: How to use | F18: Step-by-step guide, method notes and mapping of Pareto case data | H18: 1,234 | I18: Hard-coded input (blue)
D20: INPUTS | E20: Everything you type lives here. Blue figures are hard-coded inputs; yellow cells are forecast assumptions. | H20: 1,234 | I20: Forecast assumption / switch (blue on yellow)
D21: Inputs | E21: General inputs | F21: Company info, timeline, market data, net debt bridge and valuation settings | H21: 1,234 | I21: Formula (black)
D22: Hist | E22: As reported | F22: Seven years of reported income statement, balance sheet, cash flow and KPIs | H22: 1,234 | I22: Direct link to another sheet (green)
D23: Drivers | E23: Assumptions cockpit | F23: Forecast drivers per year, Bear/Base/Bull adjustments, terminal assumptions, cost structure and capital allocation | H23: 1,234 | I23: Key line / key output (light blue)
D25: CALCULATIONS | E25: The calculation engine. No inputs except known one-off items. | H25: 0.0 | I25: Integrity check – should be zero (grey italic)
D26: Model | E26: Operating model | F26: Revenue build (locations or volume x price), earnings build, investments, free cash flow and financing
D28: OUTPUT | E28: Link-only presentation of the results – what you would show in a report. | H28: Sign convention: income positive, costs negative.
D29: Output | E29: Financial statements | F29: Income statement, balance sheet (capital employed) and cash flow with integrity checks | H29: Units: NOKm unless stated; per share in NOK.
D30: Analysis | E30: Financial analysis | F30: Growth, margins, ROIC vs. WACC, leverage, per-share data and valuation multiples | H30: Historicals have grey year headers, forecasts navy.
D32: VALUATION | E32: From cost of capital to target price, cross-checked with peers. | H32: Explanations sit in the Notes column on each sheet.
D33: WACC | E33: Cost of capital | F33: CAPM with peer-based beta, cost of debt and target capital structure
D34: DCF | E34: DCF valuation | F34: FCFF, stub period and mid-year discounting, terminal value, equity bridge and target price
D35: Sensitivity | E35: Sensitivity & scenarios | F35: WACC vs. growth, WACC vs. exit multiple, growth vs. margin and Bear/Base/Bull
D36: Comps | E36: Trading multiples | F36: Peer group statistics and implied value per share
D37: Football | E37: Football field | F37: Valuation summary across all methods, with chart
D39: MARKET VIEW | E39: What the share price implies, where we differ from consensus – and what would prove us wrong.
D40: Reverse_DCF | E40: Reverse DCF | F40: Market-implied EBIT margin, growth, WACC and terminal growth at today's share price
D41: Consensus | E41: Consensus vs. our estimates | F41: Consensus inputs, our estimates vs. consensus and our variant perception
D42: Thesis | E42: Thesis tracker | F42: Scenario stories, signposts and kill criteria with a live status
D44: SUMMARY | E44: One-page overview, numbers for the pitch deck and the model health check.
D45: Dashboard | E45: Dashboard | F45: Recommendation, key financials and charts on one page
D46: Deck_Feed | E46: Deck feed | F46: Numbers and text lines ready to paste into the pitch deck
D47: Checks | E47: Integrity checks | F47: All checks must be OK before the model is submitted
D50: Version 3.0 – September 2026 · data set: Example Company ASA. Recalculate fully (Ctrl+Alt+F9) after pasting new data; press F9 to refresh data tables.

Sheet Guide
B1: Guide
B3: How to use the model – 8 steps
B4: 1 | C4: Inputs: company name, ticker, first historical year, valuation date, share price, shares, and net debt from the latest quarterly report.
B5: 2 | C5: Hist: paste seven years of reported figures. Costs are negative numbers. Map Pareto's 'Model' sheet lines using the table below.
B6: 3 | C6: Check the Hist balance check and cash flow check rows (should be zero) before moving on.
B7: 4 | C7: Choose the revenue build on Inputs (1 = segments, 2 = locations). Drivers (section A): price/mix growth per segment, then either volume growth (segment mode) or like-for-like growth, net new locations and capex per new location (location mode); the variable cost ratios, cost inflation, maintenance capex, NWC and tax per year. Rows the active build does not use are greyed out.
B8: 5 | C8: Drivers (section B/D/E/F): Bear/Bull adjustments and probabilities, terminal assumptions (g, RONIC, exit multiple), the fixed and central share of costs, capital allocation (target leverage, buybacks) and the ramp-up curve for new locations.
B9: 6 | C9: WACC: update risk-free rate, equity risk premium and peer betas. Comps: paste the peer table from the case material.
B10: 7 | C10: Review Output (the balance sheet and cash flow checks must be zero), Analysis, Dashboard, Sensitivity and Football. Resolve every ERROR on Checks and be ready to explain each WARNING.
B11: 8 | C11: Set the scenario back to Base, then copy numbers from Deck_Feed into the pitch deck.
B13: How the workbook is organised
B14: • | C14: Inputs >>> (Inputs, Hist, Drivers) is the only place you type. Calculations >>> (Model) is the engine. Output >>> (Output, Analysis) presents the results link-only. Valuation >>> (WACC, DCF, Sensitivity, Comps, Football) values the company. Summary >>> (Dashboard, Deck_Feed, Checks) wraps it up.
B15: • | C15: Blue = hard-coded input, blue on yellow = forecast assumption or switch, black = formula, green = link to another sheet, light blue row = key line, grey italic = check.
B17: Method notes
B18: • | C18: FCFF is on a pre-IFRS 16 basis: lease payments are treated as operating costs (EBITDAaL). Lease liabilities are therefore NOT deducted in the equity bridge. This avoids the classic mismatch of IFRS 16 EBITDA margins in history vs. pre-IFRS 16 margins in the forecast.
B19: • | C19: Stub period: only the remaining share of the first forecast year is valued; cash flows are discounted from the valuation date (mid-year convention optional).
B20: • | C20: Terminal value uses the value-driver formula: FCFF = NOPAT x (1 – g / RONIC). This forces reinvestment consistent with growth. With RONIC = WACC, growth adds no value.
B21: • | C21: Growth is paid for: capex = maintenance capex + growth capex. Location mode: openings x capex per new location; segment mode: incremental revenue / sales-to-capital. The DCF sanity checks compare the return on new capital in the explicit period with the higher of today's ROIC and the terminal RONIC – a forecast that grows almost for free is flagged.
B22: • | C22: Location engine (revenue build 2): volume = mature-equivalent locations x volume per mature location. New locations ramp up over three years (Drivers F); volume per location grows with like-for-like growth. Fixed costs grow with inflation and the number of locations (except the central share) and rent per location grows with inflation – so openings dilute margins at first and add to them as they mature.
B23: • | C23: Operating leverage is a result, not an input: personnel and other opex are split into a fixed part (grows with cost inflation and capacity) and a variable part (% of revenue). Margin expansion therefore follows from the growth you assume.
B24: • | C24: Capital structure: the WACC uses either a target D/(D+E) or the average modelled from the forecast balance sheet. With the buyback switch on, cash above the target leverage is returned so the forecast structure stays close to the WACC assumption; a gap above 10pp is flagged.
B25: • | C25: Target price = blended fair value (DCF and peers) rolled forward 12 months at the cost of equity, less the expected dividend. Rating: BUY only if the expected total return exceeds the cost of equity by the threshold on Inputs – a fairly priced share returns Ke, not zero.
B26: • | C26: The football field shows values today (fair value marker). The 12-month target price is drawn separately because it is rolled forward at the cost of equity and is not comparable with the ranges.
B27: • | C27: Reverse_DCF solves the DCF for today's share price: the EBIT margin (exact closed form – the DCF is linear in a uniform margin shift), growth (interpolated in Sensitivity table 5, a data table), WACC and terminal growth (bisection on the closed-form DCF). Use it to say what the market prices in – and where you differ.
B28: • | C28: Consensus: type the latest consensus (reported IFRS 16 basis) and your variant perception – topic, our view, consensus view, evidence and the catalyst that proves it. Thesis: scenario stories and kill criteria with a live status on the latest actuals.
B29: • | C29: Sensitivity tables 1-2 are live formulas. Tables 3-4 are Excel data tables – if they look stale, press F9 (File > Options > Formulas > Automatic).
B30: • | C30: Interest in the forecast is calculated on opening net debt, so the model has no circular references.
B32: Mapping Pareto case data ('Model' sheet) to Hist
C33: Revenues / Membership fees / Other | D33: Revenue – segment A/B/C (use A only if there is no split)
C34: COGS | D34: Cost of goods sold (negative)
C35: Salaries and personnel costs | D35: Personnel expenses (negative)
C36: Other expenses / Operating expenses | D36: Other operating expenses (negative)
C37: Depreciation & amortization | D37: D&A – owned assets + Depreciation – right-of-use assets (split using the lease note)
C38: Impairments | D38: Impairments and special items
C39: Net interest / Financial income + expenses | D39: Net financial items excl. leases + Interest on lease liabilities
C40: Tax expense | D40: Income tax (negative)
C41: Non-controlling interest | D41: Minority interests (negative)
C42: Installments + interests on lease liabilities / Rent payments | D42: Lease payments, total (negative)
C43: Balance sheet lines | D43: Same names on Hist – put anything else in 'Other' lines so totals match
C44: Members / FTEs / Clubs / Stores | D44: Volume KPIs and Locations per segment
... C46: Peer table (EV/Sales, EV/EBITDA, EV/EBIT, P/E for three years) | D46: Comps rows 6-13

Sheet Inputs >>>
D8: =Inputs!$C$6 -> Example Company ASA
D9: Financial Model
D12: Inputs
D14: Everything you type lives here. Blue figures are hard-coded inputs; yellow cells are forecast assumptions.
D17: Inputs | E17: General inputs | F17: Company info, timeline, market data, net debt bridge and valuation settings
D18: Hist | E18: As reported | F18: Seven years of reported income statement, balance sheet, cash flow and KPIs
D19: Drivers | E19: Assumptions cockpit | F19: Forecast drivers per year, Bear/Base/Bull adjustments, terminal assumptions, cost structure and capital allocation
D22: ← Back to cover

Sheet Inputs
B1: Inputs & settings
B2: Blue cells on a yellow background are inputs. Start here.
B4: 1. Company information | H4: Lists
B6: Company name | C6: Example Company ASA | E6: Used in all headers | H6: Bear
B7: Ticker | C7: EXMPL | H7: Base
B8: Exchange | C8: Oslo Børs | H8: Bull
B9: Sector | C9: Consumer services
B10: Reporting currency | C10: NOK
B11: Reporting unit | C11: NOKm | E11: All financial figures are in this unit
B12: Case team / analyst | C12: [Case team name]
B13: Model date | C13: 46281
B15: 2. Timeline
B17: First historical year | C17: 2019 | E17: Seven historical years: first year + 6
B18: Last actual year | C18: =$C$17+6 -> 2025
B19: First forecast year | C19: =$C$18+1 -> 2026
B20: Last explicit forecast year | C20: =$C$19+7 -> 2033 | E20: Eight explicit forecast years, then terminal value
B21: Valuation date | C21: 46281 | E21: Normally the share price date
B22: Fiscal year end, first forecast year | C22: =DATE($C$19,12,31) -> 46387 | E22: Assumes December year end
B23: Share of first forecast year remaining | C23: =MAX(0,MIN(1,($C$22-$C$21)/365)) -> 0.29041096 | E23: Only this share of the first year's FCFF is valued (stub period)
B25: 3. Market data
B27: Share price | C27: 122 | D27: NOK | E27: Source: Oslo Børs / Bloomberg – update
B28: Share price date | C28: 46281
B29: Shares outstanding | C29: 85 | D29: m | E29: Excl. treasury shares
B30: Dilutive instruments (options, RSUs) | C30: 0.6 | D30: m | E30: Treasury-stock method or face value
B31: Diluted shares | C31: =$C$29+$C$30 -> 85.6 | D31: m
B32: Market capitalisation | C32: =$C$27*$C$29 -> 10370 | D32: NOKm
B33: 52-week high | C33: 134.6 | D33: NOK
B34: 52-week low | C34: 101.2 | D34: NOK
B35: Consensus target price (optional) | C35: 135 | D35: NOK | E35: Bloomberg consensus, if provided in the case material
B37: 4. Net debt and EV bridge (latest reported balance sheet)
B39: Balance sheet date | C39: 46203 | E39: Latest quarterly report
B40: Interest-bearing debt | C40: 1420 | D40: NOKm | E40: Excl. lease liabilities
B41: Cash and cash equivalents | C41: 395 | D41: NOKm
B42: Net interest-bearing debt excl. leases | C42: =$C$40-$C$41 -> 1025 | D42: NOKm
B43: Lease liabilities (IFRS 16) | C43: 1805 | D43: NOKm | E43: Not deducted in the DCF: FCFF is after lease payments (pre-IFRS 16)
B44: Minority interests | C44: 70 | D44: NOKm | E44: Book value, or market value if available
B45: Associates and financial investments | C45: 40 | D45: NOKm | E45: Non-operating assets not captured by FCFF
B46: Pension deficit and other debt-like items | C46: 20 | D46: NOKm
B47: Other adjustments (+ adds to equity value) | C47: 0 | D47: NOKm
B48: Enterprise value at current price, excl. leases | C48: =$C$32+$C$42+$C$44-$C$45+$C$46-$C$47 -> 11445 | D48: NOKm
B49: Enterprise value at current price, incl. leases | C49: =$C$48+$C$43 -> 13250 | D49: NOKm
B51: 5. Valuation settings
B53: Active scenario | C53: Base | E53: Drop-down: Bear / Base / Bull
B54: Scenario index (1 = Bear, 2 = Base, 3 = Bull) | C54: =IF(N(Sensitivity!$D$4)>0,Sensitivity!$D$4,MATCH($C$53,$H$6:$H$8,0)) -> 2 | E54: Data tables on the Sensitivity sheet override this temporarily
B55: Mid-year discounting (1 = on, 0 = off) | C55: 1 | E55: Cash flows assumed to arrive evenly through the year
B56: Terminal value weight – Gordon growth | C56: 1 | E56: Recommended: 100% Gordon, exit multiple as a cross-check
B57: Terminal value weight – exit multiple | C57: =1-$C$56 -> 0
B58: Terminal FCFF (1 = value driver / RONIC, 2 = last FCFF x (1+g)) | C58: 1 | E58: Value driver: FCFF = NOPAT x (1 - g / RONIC) – avoids too little reinvestment
B59: Target price weight – DCF | C59: 0.7
B60: Target price weight – peer multiples | C60: =1-$C$59 -> 0.3
B61: Roll forward to 12-month target price (1 = yes) | C61: 1 | E61: TP = fair value x (1 + cost of equity) - dividend next 12m
B62: Round target price to nearest | C62: 1 | D62: NOK
B63: BUY if expected total return exceeds the cost of equity by at least | C63: 0.05 | E63: A fairly priced share is expected to return its cost of equity – only the excess justifies a BUY
B64: SELL if expected total return falls short of the cost of equity by at least | C64: -0.05 | E64: Entered as a negative number. HOLD in between
B65: Max ratio: explicit-period return on new capital / the higher of today's ROIC and the terminal RONIC | C65: 2.5 | E65: Sanity check on the DCF sheet: growth must be paid for with capex and NWC. Price increases on existing locations need no capital
B66: Max volume per mature location above the historical peak (location mode) | C66: 0.15 | E66: Utilisation check: like-for-like growth cannot fill locations far beyond anything seen historically
B67: Peer multiples include lease liabilities in EV (1 = yes) | C67: 1 | E67: 1 = IFRS 16 basis (typical for Bloomberg consensus). Controls company metrics and EV bridge
B68: Forecast year used for peer valuation (1 or 2) | C68: 2 | E68: 1 = first forecast year, 2 = second forecast year
B70: 6. Revenue build and labels
B72: Revenue build (1 = segments: volume growth x price/mix, 2 = locations: like-for-like + new locations) | C72: 2 | E72: Location mode ties revenue, fixed costs, rent and growth capex to the number of locations (Drivers A, E and F)
B73: Segment A name | C73: Norway
B74: Segment B name | C74: Sweden
B75: Segment C name | C75: Denmark & Finland
B76: Volume KPI (unit) | C76: Customers ('000) | E76: E.g. members, FTEs, stores, tonnes
B77: Normalised tax rate (historical NOPAT) | C77: 0.22 | E77: Norwegian corporate tax rate

Sheet Hist
B1: Historical financials | K1: =Inputs!$C$6&" | Scenario: "&Inputs!$C$53 -> Example Company ASA | Scenario: Base
B2: Paste reported figures into the blue cells (costs as negative numbers). Subtotals and ratios are calculated.
E3: =Inputs!$C$17+0 -> 2019 | F3: =Inputs!$C$17+1 -> 2020 | G3: =Inputs!$C$17+2 -> 2021 | H3: =Inputs!$C$17+3 -> 2022 | I3: =Inputs!$C$17+4 -> 2023 | J3: =Inputs!$C$17+5 -> 2024 | K3: =Inputs!$C$17+6 -> 2025
E4: Historicals
B5: ="("&Inputs!$C$11&")" -> (NOKm) | E5: =E3&"A" -> 2019A | F5: =F3&"A" -> 2020A | G5: =G3&"A" -> 2021A | H5: =H3&"A" -> 2022A | I5: =I3&"A" -> 2023A | J5: =J3&"A" -> 2024A | K5: =K3&"A" -> 2025A
B7: Income statement
B9: ="Revenue – "&Inputs!$C$73 -> Revenue – Norway | C9: NOKm | E9: 1950 | F9: 1790 | G9: 1880 | H9: 2150 | I9: 2340 | J9: 2505 | K9: 2690
B10: ="Revenue – "&Inputs!$C$74 -> Revenue – Sweden | C10: NOKm | E10: 1240 | F10: 1130 | G10: 1190 | H10: 1400 | I10: 1545 | J10: 1665 | K10: 1785
B11: ="Revenue – "&Inputs!$C$75 -> Revenue – Denmark & Finland | C11: NOKm | E11: 600 | F11: 548 | G11: 598 | H11: 712 | I11: 802 | J11: 875 | K11: 958
B12: Total revenue | C12: NOKm | E12: =SUM(E9:E11) -> 3790 | F12: =SUM(F9:F11) -> 3468 | G12: =SUM(G9:G11) -> 3668 | H12: =SUM(H9:H11) -> 4262 | I12: =SUM(I9:I11) -> 4687 | J12: =SUM(J9:J11) -> 5045 | K12: =SUM(K9:K11) -> 5433
B13: Cost of goods sold | C13: NOKm | E13: -1383.3 | F13: -1310.9 | G13: -1364.5 | H13: -1623.8 | I13: -1762.3 | J13: -1866.7 | K13: -1988.5
B14: Gross profit | C14: NOKm | E14: =E12+E13 -> 2406.7 | F14: =F12+F13 -> 2157.1 | G14: =G12+G13 -> 2303.5 | H14: =H12+H13 -> 2638.2 | I14: =I12+I13 -> 2924.7 | J14: =J12+J13 -> 3178.3 | K14: =K12+K13 -> 3444.5
B15: Personnel expenses | C15: NOKm | E15: -871.7 | F15: -853.1 | G15: -873 | H15: -976 | I15: -1049.9 | J15: -1114.9 | K15: -1184.4
B16: Other operating expenses | C16: NOKm | E16: -485.1 | F16: -468.2 | G16: -480.5 | H16: -537 | I16: -576.5 | J16: -610.4 | K16: -646.5
B17: EBITDA (reported, IFRS 16) | C17: NOKm | E17: =E14+E15+E16 -> 1049.9 | F17: =F14+F15+F16 -> 835.8 | G17: =G14+G15+G16 -> 950 | H17: =H14+H15+H16 -> 1125.2 | I17: =I14+I15+I16 -> 1298.3 | J17: =J14+J15+J16 -> 1453 | K17: =K14+K15+K16 -> 1613.6
B18: D&A – owned assets | C18: NOKm | E18: -174.3 | F18: -176.9 | G18: -179.7 | H18: -196.1 | I18: -210.9 | J18: -227 | K18: -239.1
B19: Depreciation – right-of-use assets | C19: NOKm | E19: -254.7 | F19: -258 | G19: -261.2 | H19: -279.6 | I19: -300 | J19: -318.9 | K19: -339
B20: Impairments and special items | C20: NOKm | E20: 0 | F20: -45 | G20: 0 | H20: 0 | I20: -20 | J20: 0 | K20: 0
B21: EBIT (reported) | C21: NOKm | E21: =E17+E18+E19+E20 -> 620.9 | F21: =F17+F18+F19+F20 -> 355.9 | G21: =G17+G18+G19+G20 -> 509.1 | H21: =H17+H18+H19+H20 -> 649.5 | I21: =I17+I18+I19+I20 -> 767.4 | J21: =J17+J18+J19+J20 -> 907.1 | K21: =K17+K18+K19+K20 -> 1035.5
B22: Net financial items excl. leases | C22: NOKm | E22: -60.3 | F22: -49.2 | G22: -44.2 | H22: -55 | I22: -84 | J22: -82.1 | K22: -80.4
B23: Interest on lease liabilities | C23: NOKm | E23: -63.7 | F23: -64.5 | G23: -65.3 | H23: -69.9 | I23: -75 | J23: -79.7 | K23: -84.8
B24: Profit before tax | C24: NOKm | E24: =E21+E22+E23 -> 496.9 | F24: =F21+F22+F23 -> 242.2 | G24: =G21+G22+G23 -> 399.6 | H24: =H21+H22+H23 -> 524.6 | I24: =I21+I22+I23 -> 608.4 | J24: =J21+J22+J23 -> 745.3 | K24: =K21+K22+K23 -> 870.3
B25: Income tax | C25: NOKm | E25: -114.3 | F25: -61.3 | G25: -87.9 | H25: -115.4 | I25: -133.8 | J25: -164 | K25: -191.5
B26: Net profit | C26: NOKm | E26: =E24+E25 -> 382.6 | F26: =F24+F25 -> 180.9 | G26: =G24+G25 -> 311.7 | H26: =H24+H25 -> 409.2 | I26: =I24+I25 -> 474.6 | J26: =J24+J25 -> 581.3 | K26: =K24+K25 -> 678.8
B27: Minority interests | C27: NOKm | E27: -3.8 | F27: -1.8 | G27: -3.1 | H27: -4.1 | I27: -4.7 | J27: -5.8 | K27: -6.8
B28: Net profit to shareholders | C28: NOKm | E28: =E26+E27 -> 378.8 | F28: =F26+F27 -> 179.1 | G28: =G26+G27 -> 308.6 | H28: =H26+H27 -> 405.1 | I28: =I26+I27 -> 469.9 | J28: =J26+J27 -> 575.5 | K28: =K26+K27 -> 672
B30: IFRS 16 adjustment and adjusted earnings
B32: Lease payments, total (from cash flow statement) | C32: NOKm | E32: -318.4 | F32: -322.5 | G32: -326.5 | H32: -349.5 | I32: -375 | J32: -398.6 | K32: -423.8 | V32: Principal + interest. Enter as a negative number
B33: EBITDAaL – EBITDA after leases (pre-IFRS 16) | C33: NOKm | E33: =E17+E32 -> 731.5 | F33: =F17+F32 -> 513.3 | G33: =G17+G32 -> 623.5 | H33: =H17+H32 -> 775.7 | I33: =I17+I32 -> 923.3 | J33: =J17+J32 -> 1054.4 | K33: =K17+K32 -> 1189.8
B34: EBIT adj. (pre-IFRS 16, excl. special items) | C34: NOKm | E34: =E33+E18 -> 557.2 | F34: =F33+F18 -> 336.4 | G34: =G33+G18 -> 443.8 | H34: =H33+H18 -> 579.6 | I34: =I33+I18 -> 712.4 | J34: =J33+J18 -> 827.4 | K34: =K33+K18 -> 950.7
B36: Balance sheet
B38: Goodwill | C38: NOKm | E38: 1800 | F38: 1800 | G38: 1800 | H38: 2400 | I38: 2400 | J38: 2730 | K38: 2730
B39: Other intangible assets | C39: NOKm | E39: 230 | F39: 230 | G39: 230 | H39: 370 | I39: 370 | J39: 460 | K39: 460
B40: Property, plant and equipment | C40: NOKm | E40: 842.8 | F40: 790.7 | G40: 772.4 | H40: 875 | I40: 917.2 | J40: 977.5 | K40: 1010.1
B41: Right-of-use assets | C41: NOKm | E41: 1267.3 | F41: 1284.5 | G41: 1301.3 | H41: 1397.9 | I41: 1505 | J41: 1604.1 | K41: 1710
B42: Other non-current assets | C42: NOKm | E42: 55 | F42: 55 | G42: 55 | H42: 55 | I42: 55 | J42: 55 | K42: 55
B43: Inventories | C43: NOKm | E43: 151.6 | F43: 138.7 | G43: 146.7 | H43: 170.5 | I43: 187.5 | J43: 201.8 | K43: 217.3
B44: Trade receivables | C44: NOKm | E44: 132.7 | F44: 121.4 | G44: 128.4 | H44: 149.2 | I44: 164 | J44: 176.6 | K44: 190.2
B45: Other current assets | C45: NOKm | E45: 75.8 | F45: 69.4 | G45: 73.4 | H45: 85.2 | I45: 93.7 | J45: 100.9 | K45: 108.7
B46: Cash and cash equivalents | C46: NOKm | E46: 451.5 | F46: 787.4 | G46: 1092.5 | H46: 451.2 | I46: 521.4 | J46: 243 | K46: 461.4
B47: Total assets | C47: NOKm | E47: =SUM(E38:E46) -> 5006.7 | F47: =SUM(F38:F46) -> 5277.1 | G47: =SUM(G38:G46) -> 5599.7 | H47: =SUM(H38:H46) -> 5954 | I47: =SUM(I38:I46) -> 6213.8 | J47: =SUM(J38:J46) -> 6548.9 | K47: =SUM(K38:K46) -> 6942.7
B48: Equity to shareholders | C48: NOKm | E48: 1270.1 | F48: 1449.2 | G48: 1757.8 | H48: 1950.4 | I48: 2122.8 | J48: 2341.3 | K48: 2605.3
B49: Minority interests | C49: NOKm | E49: 31.8 | F49: 33.6 | G49: 36.7 | H49: 40.8 | I49: 45.5 | J49: 51.3 | K49: 58.1
B50: Total equity | C50: NOKm | E50: =E48+E49 -> 1301.9 | F50: =F48+F49 -> 1482.8 | G50: =G48+G49 -> 1794.5 | H50: =H48+H49 -> 1991.2 | I50: =I48+I49 -> 2168.3 | J50: =J48+J49 -> 2392.6 | K50: =K48+K49 -> 2663.4
B51: Interest-bearing debt – non-current | C51: NOKm | E51: 1480 | F51: 1600 | G51: 1600 | H51: 1550 | I51: 1450 | J51: 1400 | K51: 1350
B52: Interest-bearing debt – current | C52: NOKm | E52: 120 | F52: 150 | G52: 100 | H52: 100 | I52: 100 | J52: 100 | K52: 100
B53: Lease liabilities – non-current | C53: NOKm | E53: 1069.8 | F53: 1083.6 | G53: 1097 | H53: 1174.3 | I53: 1260 | J53: 1339.3 | K53: 1424
B54: Lease liabilities – current | C54: NOKm | E54: 267.5 | F54: 270.9 | G54: 274.3 | H54: 293.6 | I54: 315 | J54: 334.8 | K54: 356
B55: Deferred tax and other non-current liabilities | C55: NOKm | E55: 180 | F55: 180 | G55: 180 | H55: 180 | I55: 180 | J55: 180 | K55: 180
B56: Trade payables | C56: NOKm | E56: 265.3 | F56: 242.8 | G56: 256.8 | H56: 298.3 | I56: 328.1 | J56: 353.2 | K56: 380.3
B57: Other current liabilities (incl. deferred revenue) | C57: NOKm | E57: 322.2 | F57: 267 | G57: 297.1 | H57: 366.6 | I57: 412.4 | J57: 449 | K57: 489
B58: Total equity and liabilities | C58: NOKm | E58: =E50+SUM(E51:E57) -> 5006.7 | F58: =F50+SUM(F51:F57) -> 5277.1 | G58: =G50+SUM(G51:G57) -> 5599.7 | H58: =H50+SUM(H51:H57) -> 5954 | I58: =I50+SUM(I51:I57) -> 6213.8 | J58: =J50+SUM(J51:J57) -> 6548.9 | K58: =K50+SUM(K51:K57) -> 6942.7
B59: Balance check (should be zero) | C59: NOKm | E59: =ROUND(E47-E58,1) -> 0 | F59: =ROUND(F47-F58,1) -> 0 | G59: =ROUND(G47-G58,1) -> 0 | H59: =ROUND(H47-H58,1) -> 0 | I59: =ROUND(I47-I58,1) -> 0 | J59: =ROUND(J47-J58,1) -> 0 | K59: =ROUND(K47-K58,1) -> 0
B61: Cash flow statement (condensed)
B63: Cash flow from operations (excl. lease payments) | C63: NOKm | E63: 891 | F63: 633.2 | G63: 843 | H63: 1009.4 | I63: 1095.8 | J63: 1234.5 | K63: 1371.9
B64: Capital expenditure | C64: NOKm | E64: -197.1 | F64: -124.8 | G64: -161.4 | H64: -238.7 | I64: -253.1 | J64: -257.3 | K64: -271.7
B65: Acquisitions and disposals | C65: NOKm | E65: 0 | F65: 0 | G65: 0 | H65: -800 | I65: 0 | J65: -450 | K65: 0
B66: Lease payments | C66: NOKm | E66: =E32 -> -318.4 | F66: =F32 -> -322.5 | G66: =G32 -> -326.5 | H66: =H32 -> -349.5 | I66: =I32 -> -375 | J66: =J32 -> -398.6 | K66: =K32 -> -423.8
B67: Dividends paid | C67: NOKm | E67: -204 | F67: 0 | G67: 0 | H67: -212.5 | I67: -297.5 | J67: -357 | K67: -408
B68: Net change in debt and other financing | C68: NOKm | E68: -20 | F68: 150 | G68: -50 | H68: -50 | I68: -100 | J68: -50 | K68: -50
B69: Net change in cash | C69: NOKm | E69: =SUM(E63:E68) -> 151.5 | F69: =SUM(F63:F68) -> 335.9 | G69: =SUM(G63:G68) -> 305.1 | H69: =SUM(H63:H68) -> -641.3 | I69: =SUM(I63:I68) -> 70.2 | J69: =SUM(J63:J68) -> -278.4 | K69: =SUM(K63:K68) -> 218.4
B70: Cash flow vs. balance sheet (should be zero) | C70: NOKm | F70: =ROUND(F69-(F46-E46),1) -> 0 | G70: =ROUND(G69-(G46-F46),1) -> 0 | H70: =ROUND(H69-(H46-G46),1) -> 0 | I70: =ROUND(I69-(I46-H46),1) -> 0 | J70: =ROUND(J69-(J46-I46),1) -> 0 | K70: =ROUND(K69-(K46-J46),1) -> 0
B72: KPIs and per-share data
B74: ="Volume – "&Inputs!$C$73&" ("&Inputs!$C$76&")" -> Volume – Norway (Customers ('000)) | C74: # | E74: 300 | F74: 281 | G74: 289 | H74: 316 | I74: 329 | J74: 337 | K74: 347
B75: ="Volume – "&Inputs!$C$74&" ("&Inputs!$C$76&")" -> Volume – Sweden (Customers ('000)) | C75: # | E75: 228 | F75: 212 | G75: 219 | H75: 247 | I75: 259 | J75: 267 | K75: 274
B76: ="Volume – "&Inputs!$C$75&" ("&Inputs!$C$76&")" -> Volume – Denmark & Finland (Customers ('000)) | C76: # | E76: 118 | F76: 110 | G76: 117 | H76: 132 | I76: 143 | J76: 150 | K76: 158
B77: ="Locations – "&Inputs!$C$73 -> Locations – Norway | C77: # | E77: 82 | F77: 83 | G77: 85 | H77: 88 | I77: 89 | J77: 91 | K77: 94
B78: ="Locations – "&Inputs!$C$74 -> Locations – Sweden | C78: # | E78: 68 | F78: 69 | G78: 70 | H78: 73 | I78: 75 | J78: 76 | K78: 77
B79: ="Locations – "&Inputs!$C$75 -> Locations – Denmark & Finland | C79: # | E79: 32 | F79: 32 | G79: 33 | H79: 40 | I79: 42 | J79: 44 | K79: 46
B80: Number of locations | C80: # | E80: =E77+E78+E79 -> 182 | F80: =F77+F78+F79 -> 184 | G80: =G77+G78+G79 -> 188 | H80: =H77+H78+H79 -> 201 | I80: =I77+I78+I79 -> 206 | J80: =J77+J78+J79 -> 211 | K80: =K77+K78+K79 -> 217
B81: Full-time employees (FTEs) | C81: # | E81: 3150 | F81: 2980 | G81: 3050 | H81: 3420 | I81: 3560 | J81: 3640 | K81: 3730
B82: Shares outstanding, year-end | C82: m | E82: 85 | F82: 85 | G82: 85 | H82: 85 | I82: 85 | J82: 85 | K82: 85
B83: Dividend per share (for the fiscal year) | C83: NOK | E83: 0 | F83: 0 | G83: 2.5 | H83: 3.5 | I83: 4.2 | J83: 4.8 | K83: 5.4
B84: Share price, year-end | C84: NOK | E84: 78 | F84: 64 | G84: 82 | H84: 88 | I84: 95 | J84: 104 | K84: 112
B86: Key ratios (calculated – used as reference for the forecast)
B88: Revenue growth | C88: % | F88: =F12/E12-1 -> -0.084960422 | G88: =G12/F12-1 -> 0.057670127 | H88: =H12/G12-1 -> 0.16194111 | I88: =I12/H12-1 -> 0.099718442 | J88: =J12/I12-1 -> 0.076381481 | K88: =K12/J12-1 -> 0.07690783
B89: =" Revenue growth – "&Inputs!$C$73 -> Revenue growth – Norway | C89: % | F89: =F9/E9-1 -> -0.082051282 | G89: =G9/F9-1 -> 0.05027933 | H89: =H9/G9-1 -> 0.14361702 | I89: =I9/H9-1 -> 0.088372093 | J89: =J9/I9-1 -> 0.070512821 | K89: =K9/J9-1 -> 0.073852295
B90: =" Revenue growth – "&Inputs!$C$74 -> Revenue growth – Sweden | C90: % | F90: =F10/E10-1 -> -0.088709677 | G90: =G10/F10-1 -> 0.053097345 | H90: =H10/G10-1 -> 0.17647059 | I90: =I10/H10-1 -> 0.10357143 | J90: =J10/I10-1 -> 0.077669903 | K90: =K10/J10-1 -> 0.072072072
B91: =" Revenue growth – "&Inputs!$C$75 -> Revenue growth – Denmark & Finland | C91: % | F91: =F11/E11-1 -> -0.086666667 | G91: =G11/F11-1 -> 0.091240876 | H91: =H11/G11-1 -> 0.19063545 | I91: =I11/H11-1 -> 0.12640449 | J91: =J11/I11-1 -> 0.091022444 | K91: =K11/J11-1 -> 0.094857143
B92: =" Volume growth – "&Inputs!$C$73 -> Volume growth – Norway | C92: % | F92: =F74/E74-1 -> -0.063333333 | G92: =G74/F74-1 -> 0.028469751 | H92: =H74/G74-1 -> 0.093425606 | I92: =I74/H74-1 -> 0.041139241 | J92: =J74/I74-1 -> 0.024316109 | K92: =K74/J74-1 -> 0.029673591
B93: =" Volume growth – "&Inputs!$C$74 -> Volume growth – Sweden | C93: % | F93: =F75/E75-1 -> -0.070175439 | G93: =G75/F75-1 -> 0.033018868 | H93: =H75/G75-1 -> 0.12785388 | I93: =I75/H75-1 -> 0.048582996 | J93: =J75/I75-1 -> 0.030888031 | K93: =K75/J75-1 -> 0.026217228
B94: =" Volume growth – "&Inputs!$C$75 -> Volume growth – Denmark & Finland | C94: % | F94: =F76/E76-1 -> -0.06779661 | G94: =G76/F76-1 -> 0.063636364 | H94: =H76/G76-1 -> 0.12820513 | I94: =I76/H76-1 -> 0.083333333 | J94: =J76/I76-1 -> 0.048951049 | K94: =K76/J76-1 -> 0.053333333
B95: =" Price/mix growth – "&Inputs!$C$73 -> Price/mix growth – Norway | C95: % | F95: =(1+F89)/(1+F92)-1 -> -0.019983575 | G95: =(1+G89)/(1+G92)-1 -> 0.021205853 | H95: =(1+H89)/(1+H92)-1 -> 0.045902909 | I95: =(1+I89)/(1+I92)-1 -> 0.045366509 | J95: =(1+J89)/(1+J92)-1 -> 0.045100053 | K95: =(1+K89)/(1+K92)-1 -> 0.042905543
B96: =" Price/mix growth – "&Inputs!$C$74 -> Price/mix growth – Sweden | C96: % | F96: =(1+F90)/(1+F93)-1 -> -0.019933049 | G96: =(1+G90)/(1+G93)-1 -> 0.019436699 | H96: =(1+H90)/(1+H93)-1 -> 0.043105501 | I96: =(1+I90)/(1+I93)-1 -> 0.052440706 | J96: =(1+J90)/(1+J93)-1 -> 0.045380168 | K96: =(1+K90)/(1+K93)-1 -> 0.04468337
B97: =" Price/mix growth – "&Inputs!$C$75 -> Price/mix growth – Denmark & Finland | C97: % | F97: =(1+F91)/(1+F94)-1 -> -0.020242424 | G97: =(1+G91)/(1+G94)-1 -> 0.02595296 | H97: =(1+H91)/(1+H94)-1 -> 0.055335968 | I97: =(1+I91)/(1+I94)-1 -> 0.039757995 | J97: =(1+J91)/(1+J94)-1 -> 0.040108063 | K97: =(1+K91)/(1+K94)-1 -> 0.039421338
B98: =" Revenue per unit – "&Inputs!$C$73 -> Revenue per unit – Norway | C98: NOK '000 | E98: =IF(E74=0,0,E9/E74) -> 6.5 | F98: =IF(F74=0,0,F9/F74) -> 6.3701068 | G98: =IF(G74=0,0,G9/G74) -> 6.5051903 | H98: =IF(H74=0,0,H9/H74) -> 6.8037975 | I98: =IF(I74=0,0,I9/I74) -> 7.112462 | J98: =IF(J74=0,0,J9/J74) -> 7.4332344 | K98: =IF(K74=0,0,K9/K74) -> 7.7521614
B99: =" Revenue per unit – "&Inputs!$C$74 -> Revenue per unit – Sweden | C99: NOK '000 | E99: =IF(E75=0,0,E10/E75) -> 5.4385965 | F99: =IF(F75=0,0,F10/F75) -> 5.3301887 | G99: =IF(G75=0,0,G10/G75) -> 5.43379 | H99: =IF(H75=0,0,H10/H75) -> 5.6680162 | I99: =IF(I75=0,0,I10/I75) -> 5.965251 | J99: =IF(J75=0,0,J10/J75) -> 6.2359551 | K99: =IF(K75=0,0,K10/K75) -> 6.5145985
B100: =" Revenue per unit – "&Inputs!$C$75 -> Revenue per unit – Denmark & Finland | C100: NOK '000 | E100: =IF(E76=0,0,E11/E76) -> 5.0847458 | F100: =IF(F76=0,0,F11/F76) -> 4.9818182 | G100: =IF(G76=0,0,G11/G76) -> 5.1111111 | H100: =IF(H76=0,0,H11/H76) -> 5.3939394 | I100: =IF(I76=0,0,I11/I76) -> 5.6083916 | J100: =IF(J76=0,0,J11/J76) -> 5.8333333 | K100: =IF(K76=0,0,K11/K76) -> 6.0632911
B101: =" Net new locations – "&Inputs!$C$73 -> Net new locations – Norway | C101: # | F101: =F77-E77 -> 1 | G101: =G77-F77 -> 2 | H101: =H77-G77 -> 3 | I101: =I77-H77 -> 1 | J101: =J77-I77 -> 2 | K101: =K77-J77 -> 3
B102: =" Net new locations – "&Inputs!$C$74 -> Net new locations – Sweden | C102: # | F102: =F78-E78 -> 1 | G102: =G78-F78 -> 1 | H102: =H78-G78 -> 3 | I102: =I78-H78 -> 2 | J102: =J78-I78 -> 1 | K102: =K78-J78 -> 1
B103: =" Net new locations – "&Inputs!$C$75 -> Net new locations – Denmark & Finland | C103: # | F103: =F79-E79 -> 0 | G103: =G79-F79 -> 1 | H103: =H79-G79 -> 7 | I103: =I79-H79 -> 2 | J103: =J79-I79 -> 2 | K103: =K79-J79 -> 2
B104: =" Volume per location – "&Inputs!$C$73 -> Volume per location – Norway | C104: # | E104: =IF(E77=0,0,E74/E77) -> 3.6585366 | F104: =IF(F77=0,0,F74/F77) -> 3.3855422 | G104: =IF(G77=0,0,G74/G77) -> 3.4 | H104: =IF(H77=0,0,H74/H77) -> 3.5909091 | I104: =IF(I77=0,0,I74/I77) -> 3.6966292 | J104: =IF(J77=0,0,J74/J77) -> 3.7032967 | K104: =IF(K77=0,0,K74/K77) -> 3.6914894
B105: =" Volume per location – "&Inputs!$C$74 -> Volume per location – Sweden | C105: # | E105: =IF(E78=0,0,E75/E78) -> 3.3529412 | F105: =IF(F78=0,0,F75/F78) -> 3.0724638 | G105: =IF(G78=0,0,G75/G78) -> 3.1285714 | H105: =IF(H78=0,0,H75/H78) -> 3.3835616 | I105: =IF(I78=0,0,I75/I78) -> 3.4533333 | J105: =IF(J78=0,0,J75/J78) -> 3.5131579 | K105: =IF(K78=0,0,K75/K78) -> 3.5584416
B106: =" Volume per location – "&Inputs!$C$75 -> Volume per location – Denmark & Finland | C106: # | E106: =IF(E79=0,0,E76/E79) -> 3.6875 | F106: =IF(F79=0,0,F76/F79) -> 3.4375 | G106: =IF(G79=0,0,G76/G79) -> 3.5454545 | H106: =IF(H79=0,0,H76/H79) -> 3.3 | I106: =IF(I79=0,0,I76/I79) -> 3.4047619 | J106: =IF(J79=0,0,J76/J79) -> 3.4090909 | K106: =IF(K79=0,0,K76/K79) -> 3.4347826
B107: =" Like-for-like growth in volume per location – "&Inputs!$C$73 -> Like-for-like growth in volume per location – Norway | C107: % | F107: =IF(E104=0,0,F104/E104-1) -> -0.074618474 | G107: =IF(F104=0,0,G104/F104-1) -> 0.0042704626 | H107: =IF(G104=0,0,H104/G104-1) -> 0.056149733 | I107: =IF(H104=0,0,I104/H104-1) -> 0.029441047 | J107: =IF(I104=0,0,J104/I104-1) -> 0.0018036675 | K107: =IF(J104=0,0,K104/J104-1) -> -0.0031883326
B108: =" Like-for-like growth in volume per location – "&Inputs!$C$74 -> Like-for-like growth in volume per location – Sweden | C108: % | F108: =IF(E105=0,0,F105/E105-1) -> -0.083651157 | G108: =IF(F105=0,0,G105/F105-1) -> 0.018261456 | H108: =IF(G105=0,0,H105/G105-1) -> 0.081503722 | I108: =IF(H105=0,0,I105/H105-1) -> 0.020620783 | J108: =IF(I105=0,0,J105/I105-1) -> 0.017323715 | K108: =IF(J105=0,0,K105/J105-1) -> 0.012889732
B109: =" Like-for-like growth in volume per location – "&Inputs!$C$75 -> Like-for-like growth in volume per location – Denmark & Finland | C109: % | F109: =IF(E106=0,0,F106/E106-1) -> -0.06779661 | G109: =IF(F106=0,0,G106/F106-1) -> 0.031404959 | H109: =IF(G106=0,0,H106/G106-1) -> -0.069230769 | I109: =IF(H106=0,0,I106/H106-1) -> 0.031746032 | J109: =IF(I106=0,0,J106/I106-1) -> 0.0012714558 | K109: =IF(J106=0,0,K106/J106-1) -> 0.0075362319
B110: Gross margin | C110: % | E110: =E14/E12 -> 0.63501319 | F110: =F14/F12 -> 0.62200115 | G110: =G14/G12 -> 0.62799891 | H110: =H14/H12 -> 0.61900516 | I110: =I14/I12 -> 0.62400256 | J110: =J14/J12 -> 0.62999009 | K110: =K14/K12 -> 0.63399595
B111: COGS in % of revenue | C111: % | E111: =-E13/E12 -> 0.36498681 | F111: =-F13/F12 -> 0.37799885 | G111: =-G13/G12 -> 0.37200109 | H111: =-H13/H12 -> 0.38099484 | I111: =-I13/I12 -> 0.37599744 | J111: =-J13/J12 -> 0.37000991 | K111: =-K13/K12 -> 0.36600405
B112: Personnel expenses in % of revenue | C112: % | E112: =-E15/E12 -> 0.23 | F112: =-F15/F12 -> 0.24599193 | G112: =-G15/G12 -> 0.23800436 | H112: =-H15/H12 -> 0.22900047 | I112: =-I15/I12 -> 0.22400256 | J112: =-J15/J12 -> 0.22099108 | K112: =-K15/K12 -> 0.2180011
...

Sheet Drivers
B1: Forecast drivers & scenarios | T1: =Inputs!$C$6&" | Scenario: "&Inputs!$C$53 -> Example Company ASA | Scenario: Base
B2: Base case per year (A), scenario adjustments (B), terminal value (D), cost structure and capital allocation (E), ramp-up of new locations (F). The model reads C–F.
E3: =Inputs!$C$17+0 -> 2019 | F3: =Inputs!$C$17+1 -> 2020 | G3: =Inputs!$C$17+2 -> 2021 | H3: =Inputs!$C$17+3 -> 2022 | I3: =Inputs!$C$17+4 -> 2023 | J3: =Inputs!$C$17+5 -> 2024 | K3: =Inputs!$C$17+6 -> 2025 | L3: =Inputs!$C$19+0 -> 2026 | M3: =Inputs!$C$19+1 -> 2027 | N3: =Inputs!$C$19+2 -> 2028 | O3: =Inputs!$C$19+3 -> 2029 | P3: =Inputs!$C$19+4 -> 2030 | Q3: =Inputs!$C$19+5 -> 2031 | R3: =Inputs!$C$19+6 -> 2032 | S3: =Inputs!$C$19+7 -> 2033
E4: Historicals | L4: Explicit forecast
B5: ="("&Inputs!$C$11&")" -> (NOKm) | E5: =E3&"A" -> 2019A | F5: =F3&"A" -> 2020A | G5: =G3&"A" -> 2021A | H5: =H3&"A" -> 2022A | I5: =I3&"A" -> 2023A | J5: =J3&"A" -> 2024A | K5: =K3&"A" -> 2025A | L5: =L3&"E" -> 2026E | M5: =M3&"E" -> 2027E | N5: =N3&"E" -> 2028E | O5: =O3&"E" -> 2029E | P5: =P3&"E" -> 2030E | Q5: =Q3&"E" -> 2031E | R5: =R3&"E" -> 2032E | S5: =S3&"E" -> 2033E | T5: Hist. avg (3y) | V5: Notes
B7: Active scenario | E7: =Inputs!$C$53 -> Base | G7: ="Revenue build: "&IF(Inputs!$C$72=2,"locations (like-for-like + new locations)","segments (volume x price/mix)")&" – greyed-out rows are not used (switch on Inputs)" -> Revenue build: locations (like-for-like + new locations) – greyed-out rows are not used (switch on Inputs)
B8: Scenario index (1 = Bear, 2 = Base, 3 = Bull) | E8: =Inputs!$C$54 -> 2
B10: A. Base case drivers – enter forecast assumptions in the blue cells (history shown for reference)
B12: ="Volume growth – "&Inputs!$C$73&" (segment mode)" -> Volume growth – Norway (segment mode) | C12: % | F12: =Hist!F92 -> -0.063333333 | G12: =Hist!G92 -> 0.028469751 | H12: =Hist!H92 -> 0.093425606 | I12: =Hist!I92 -> 0.041139241 | J12: =Hist!J92 -> 0.024316109 | K12: =Hist!K92 -> 0.029673591 | L12: 0.026 | M12: 0.024 | N12: 0.022 | O12: 0.02 | P12: 0.018 | Q12: 0.016 | R12: 0.014 | S12: 0.012 | T12: =IFERROR(AVERAGE(I12:K12),"") -> 0.031709647 | V12: Segment mode only (greyed out in location mode): total volume growth per segment
B13: ="Price/mix growth – "&Inputs!$C$73&"" -> Price/mix growth – Norway | C13: % | F13: =Hist!F95 -> -0.019983575 | G13: =Hist!G95 -> 0.021205853 | H13: =Hist!H95 -> 0.045902909 | I13: =Hist!I95 -> 0.045366509 | J13: =Hist!J95 -> 0.045100053 | K13: =Hist!K95 -> 0.042905543 | L13: 0.034 | M13: 0.03 | N13: 0.028 | O13: 0.026 | P13: 0.025 | Q13: 0.024 | R13: 0.023 | S13: 0.022 | T13: =IFERROR(AVERAGE(I13:K13),"") -> 0.044457368
B14: ="Volume growth – "&Inputs!$C$74&" (segment mode)" -> Volume growth – Sweden (segment mode) | C14: % | F14: =Hist!F93 -> -0.070175439 | G14: =Hist!G93 -> 0.033018868 | H14: =Hist!H93 -> 0.12785388 | I14: =Hist!I93 -> 0.048582996 | J14: =Hist!J93 -> 0.030888031 | K14: =Hist!K93 -> 0.026217228 | L14: 0.03 | M14: 0.028 | N14: 0.026 | O14: 0.023 | P14: 0.02 | Q14: 0.018 | R14: 0.015 | S14: 0.013 | T14: =IFERROR(AVERAGE(I14:K14),"") -> 0.035229418
B15: ="Price/mix growth – "&Inputs!$C$74&"" -> Price/mix growth – Sweden | C15: % | F15: =Hist!F96 -> -0.019933049 | G15: =Hist!G96 -> 0.019436699 | H15: =Hist!H96 -> 0.043105501 | I15: =Hist!I96 -> 0.052440706 | J15: =Hist!J96 -> 0.045380168 | K15: =Hist!K96 -> 0.04468337 | L15: 0.032 | M15: 0.03 | N15: 0.028 | O15: 0.026 | P15: 0.025 | Q15: 0.024 | R15: 0.023 | S15: 0.022 | T15: =IFERROR(AVERAGE(I15:K15),"") -> 0.047501415
B16: ="Volume growth – "&Inputs!$C$75&" (segment mode)" -> Volume growth – Denmark & Finland (segment mode) | C16: % | F16: =Hist!F94 -> -0.06779661 | G16: =Hist!G94 -> 0.063636364 | H16: =Hist!H94 -> 0.12820513 | I16: =Hist!I94 -> 0.083333333 | J16: =Hist!J94 -> 0.048951049 | K16: =Hist!K94 -> 0.053333333 | L16: 0.055 | M16: 0.05 | N16: 0.045 | O16: 0.04 | P16: 0.035 | Q16: 0.03 | R16: 0.025 | S16: 0.02 | T16: =IFERROR(AVERAGE(I16:K16),"") -> 0.061872572
B17: ="Price/mix growth – "&Inputs!$C$75&"" -> Price/mix growth – Denmark & Finland | C17: % | F17: =Hist!F97 -> -0.020242424 | G17: =Hist!G97 -> 0.02595296 | H17: =Hist!H97 -> 0.055335968 | I17: =Hist!I97 -> 0.039757995 | J17: =Hist!J97 -> 0.040108063 | K17: =Hist!K97 -> 0.039421338 | L17: 0.03 | M17: 0.028 | N17: 0.027 | O17: 0.026 | P17: 0.025 | Q17: 0.024 | R17: 0.023 | S17: 0.022 | T17: =IFERROR(AVERAGE(I17:K17),"") -> 0.039762465
B18: ="Like-for-like growth per location – "&Inputs!$C$73&" (location mode)" -> Like-for-like growth per location – Norway (location mode) | C18: % | F18: =Hist!F107 -> -0.074618474 | G18: =Hist!G107 -> 0.0042704626 | H18: =Hist!H107 -> 0.056149733 | I18: =Hist!I107 -> 0.029441047 | J18: =Hist!J107 -> 0.0018036675 | K18: =Hist!K107 -> -0.0031883326 | L18: 0.008 | M18: 0.007 | N18: 0.006 | O18: 0.005 | P18: 0.004 | Q18: 0.003 | R18: 0.003 | S18: 0.003 | T18: =IFERROR(AVERAGE(I18:K18),"") -> 0.0093521272 | V18: Location mode: growth in volume per MATURE location. History: growth in volume per location
B19: ="Like-for-like growth per location – "&Inputs!$C$74&" (location mode)" -> Like-for-like growth per location – Sweden (location mode) | C19: % | F19: =Hist!F108 -> -0.083651157 | G19: =Hist!G108 -> 0.018261456 | H19: =Hist!H108 -> 0.081503722 | I19: =Hist!I108 -> 0.020620783 | J19: =Hist!J108 -> 0.017323715 | K19: =Hist!K108 -> 0.012889732 | L19: 0.01 | M19: 0.009 | N19: 0.008 | O19: 0.007 | P19: 0.006 | Q19: 0.005 | R19: 0.004 | S19: 0.003 | T19: =IFERROR(AVERAGE(I19:K19),"") -> 0.016944743
B20: ="Like-for-like growth per location – "&Inputs!$C$75&" (location mode)" -> Like-for-like growth per location – Denmark & Finland (location mode) | C20: % | F20: =Hist!F109 -> -0.06779661 | G20: =Hist!G109 -> 0.031404959 | H20: =Hist!H109 -> -0.069230769 | I20: =Hist!I109 -> 0.031746032 | J20: =Hist!J109 -> 0.0012714558 | K20: =Hist!K109 -> 0.0075362319 | L20: 0.015 | M20: 0.014 | N20: 0.012 | O20: 0.01 | P20: 0.009 | Q20: 0.008 | R20: 0.006 | S20: 0.005 | T20: =IFERROR(AVERAGE(I20:K20),"") -> 0.013517906
B21: ="Net new locations – "&Inputs!$C$73&" (location mode)" -> Net new locations – Norway (location mode) | C21: # | F21: =Hist!F101 -> 1 | G21: =Hist!G101 -> 2 | H21: =Hist!H101 -> 3 | I21: =Hist!I101 -> 1 | J21: =Hist!J101 -> 2 | K21: =Hist!K101 -> 3 | L21: 2 | M21: 2 | N21: 2 | O21: 2 | P21: 2 | Q21: 1 | R21: 1 | S21: 1 | T21: =IFERROR(AVERAGE(I21:K21),"") -> 2 | V21: Location mode: openings minus closures. New locations ramp up over three years (section F)
B22: ="Net new locations – "&Inputs!$C$74&" (location mode)" -> Net new locations – Sweden (location mode) | C22: # | F22: =Hist!F102 -> 1 | G22: =Hist!G102 -> 1 | H22: =Hist!H102 -> 3 | I22: =Hist!I102 -> 2 | J22: =Hist!J102 -> 1 | K22: =Hist!K102 -> 1 | L22: 2 | M22: 2 | N22: 2 | O22: 2 | P22: 1 | Q22: 1 | R22: 1 | S22: 1 | T22: =IFERROR(AVERAGE(I22:K22),"") -> 1.3333333
B23: ="Net new locations – "&Inputs!$C$75&" (location mode)" -> Net new locations – Denmark & Finland (location mode) | C23: # | F23: =Hist!F103 -> 0 | G23: =Hist!G103 -> 1 | H23: =Hist!H103 -> 7 | I23: =Hist!I103 -> 2 | J23: =Hist!J103 -> 2 | K23: =Hist!K103 -> 2 | L23: 3 | M23: 3 | N23: 3 | O23: 2 | P23: 2 | Q23: 2 | R23: 1 | S23: 1 | T23: =IFERROR(AVERAGE(I23:K23),"") -> 2
B24: COGS in % of revenue | C24: % | E24: =Hist!E111 -> 0.36498681 | F24: =Hist!F111 -> 0.37799885 | G24: =Hist!G111 -> 0.37200109 | H24: =Hist!H111 -> 0.38099484 | I24: =Hist!I111 -> 0.37599744 | J24: =Hist!J111 -> 0.37000991 | K24: =Hist!K111 -> 0.36600405 | L24: 0.366 | M24: 0.366 | N24: 0.366 | O24: 0.366 | P24: 0.366 | Q24: 0.366 | R24: 0.366 | S24: 0.366 | T24: =IFERROR(AVERAGE(I24:K24),"") -> 0.37067047
B25: Personnel expenses – variable part, in % of revenue | C25: % | E25: =Hist!E112 -> 0.23 | F25: =Hist!F112 -> 0.24599193 | G25: =Hist!G112 -> 0.23800436 | H25: =Hist!H112 -> 0.22900047 | I25: =Hist!I112 -> 0.22400256 | J25: =Hist!J112 -> 0.22099108 | K25: =Hist!K112 -> 0.2180011 | L25: 0.0872 | M25: 0.0872 | N25: 0.0872 | O25: 0.0872 | P25: 0.0872 | Q25: 0.0872 | R25: 0.0872 | S25: 0.0872 | T25: =IFERROR(AVERAGE(I25:K25),"") -> 0.22099825 | V25: History shows the TOTAL ratio. Only this part scales with revenue – the fixed part (section E) grows with inflation and locations
B26: Other opex – variable part, in % of revenue | C26: % | E26: =Hist!E113 -> 0.12799472 | F26: =Hist!F113 -> 0.13500577 | G26: =Hist!G113 -> 0.13099782 | H26: =Hist!H113 -> 0.12599718 | I26: =Hist!I113 -> 0.12299979 | J26: =Hist!J113 -> 0.12099108 | K26: =Hist!K113 -> 0.11899503 | L26: 0.0595 | M26: 0.0595 | N26: 0.0595 | O26: 0.0595 | P26: 0.0595 | Q26: 0.0595 | R26: 0.0595 | S26: 0.0595 | T26: =IFERROR(AVERAGE(I26:K26),"") -> 0.1209953 | V26: History shows the TOTAL ratio – see personnel expenses
B27: Cost inflation on the fixed cost base and rent | C27: % | L27: 0.03 | M27: 0.027 | N27: 0.025 | O27: 0.025 | P27: 0.025 | Q27: 0.025 | R27: 0.025 | S27: 0.025 | T27: =IFERROR(AVERAGE(I27:K27),"") | V27: Wage and price inflation on the fixed cost base – and on rent per location in location mode
B28: Real growth in the fixed cost base (segment mode) | C28: % | L28: 0.015 | M28: 0.015 | N28: 0.015 | O28: 0.015 | P28: 0.015 | Q28: 0.015 | R28: 0.015 | S28: 0.015 | T28: =IFERROR(AVERAGE(I28:K28),"") | V28: Segment mode only. In location mode the fixed cost base grows with the number of locations (section C)
B29: Lease payments in % of revenue (IFRS 16, segment mode) | C29: % | E29: =Hist!E115 -> 0.084010554 | F29: =Hist!F115 -> 0.09299308 | G29: =Hist!G115 -> 0.089013086 | H29: =Hist!H115 -> 0.082003754 | I29: =Hist!I115 -> 0.080008534 | J29: =Hist!J115 -> 0.07900892 | K29: =Hist!K115 -> 0.078004786 | L29: 0.078 | M29: 0.078 | N29: 0.077 | O29: 0.077 | P29: 0.077 | Q29: 0.077 | R29: 0.077 | S29: 0.077 | T29: =IFERROR(AVERAGE(I29:K29),"") -> 0.079007413 | V29: Segment mode only. In location mode rent per location grows with cost inflation (Model)
B30: D&A (owned assets) in % of revenue | C30: % | E30: =Hist!E117 -> 0.045989446 | F30: =Hist!F117 -> 0.051009227 | G30: =Hist!G117 -> 0.048991276 | H30: =Hist!H117 -> 0.046011262 | I30: =Hist!I117 -> 0.0449968 | J30: =Hist!J117 -> 0.044995045 | K30: =Hist!K117 -> 0.044008835 | L30: 0.044 | M30: 0.044 | N30: 0.044 | O30: 0.044 | P30: 0.044 | Q30: 0.044 | R30: 0.044 | S30: 0.044 | T30: =IFERROR(AVERAGE(I30:K30),"") -> 0.044666893
B31: Maintenance capex in % of revenue | C31: % | E31: =Hist!E117 -> 0.045989446 | F31: =Hist!F117 -> 0.051009227 | G31: =Hist!G117 -> 0.048991276 | H31: =Hist!H117 -> 0.046011262 | I31: =Hist!I117 -> 0.0449968 | J31: =Hist!J117 -> 0.044995045 | K31: =Hist!K117 -> 0.044008835 | L31: 0.05 | M31: 0.05 | N31: 0.05 | O31: 0.05 | P31: 0.05 | Q31: 0.05 | R31: 0.05 | S31: 0.05 | T31: =IFERROR(AVERAGE(I31:K31),"") -> 0.044666893 | V31: History shows D&A in % of revenue. Maintenance and refurbishment ≈ the historical capex/D&A ratio (~1.14x)
B32: Sales-to-capital for growth capex (segment mode) | C32: x | F32: =Hist!F121 -> n.m. | G32: =Hist!G121 -> n.m. | H32: =Hist!H121 -> 13.943662 | I32: =Hist!I121 -> 10.07109 | J32: =Hist!J121 -> 11.815182 | K32: =Hist!K121 -> 11.90184 | L32: 2 | M32: 2 | N32: 2 | O32: 2 | P32: 2 | Q32: 2 | R32: 2 | S32: 2 | T32: =IFERROR(AVERAGE(I32:K32),"") -> 11.262704 | V32: Segment mode only. History: incremental revenue / (capex – D&A), flattered by acquired revenue. Lower = more capital-intensive
B33: Capex per new location, NOKm (location mode) | C33: NOKm | L33: 22 | M33: 22.6 | N33: 23.1 | O33: 23.7 | P33: 24.3 | Q33: 24.9 | R33: 25.5 | S33: 26.1 | T33: =IFERROR(AVERAGE(I33:K33),"") | V33: Location mode: fit-out, equipment and pre-opening costs per new location
B34: NWC in % of revenue | C34: % | E34: =Hist!E124 -> -0.06 | F34: =Hist!F124 -> -0.051989619 | G34: =Hist!G124 -> -0.055997819 | H34: =Hist!H124 -> -0.061004223 | I34: =Hist!I124 -> -0.063004054 | J34: =Hist!J124 -> -0.064003964 | K34: =Hist!K124 -> -0.064991717 | L34: -0.065 | M34: -0.065 | N34: -0.065 | O34: -0.065 | P34: -0.065 | Q34: -0.065 | R34: -0.065 | S34: -0.065 | T34: =IFERROR(AVERAGE(I34:K34),"") -> -0.063999912
B35: Tax rate | C35: % | E35: =Hist!E122 -> 0.23002616 | F35: =Hist!F122 -> 0.25309661 | G35: =Hist!G122 -> 0.21996997 | H35: =Hist!H122 -> 0.21997713 | I35: =Hist!I122 -> 0.2199211 | J35: =Hist!J122 -> 0.22004562 | K35: =Hist!K122 -> 0.22003907 | L35: 0.22 | M35: 0.22 | N35: 0.22 | O35: 0.22 | P35: 0.22 | Q35: 0.22 | R35: 0.22 | S35: 0.22 | T35: =IFERROR(AVERAGE(I35:K35),"") -> 0.22000193
B36: Dividend payout ratio | C36: % | E36: =Hist!E131 -> 0 | F36: =Hist!F131 -> 0 | G36: =Hist!G131 -> 0.68859365 | H36: =Hist!H131 -> 0.73438657 | I36: =Hist!I131 -> 0.75973611 | J36: =Hist!J131 -> 0.70894874 | K36: =Hist!K131 -> 0.68303571 | L36: 0.65 | M36: 0.7 | N36: 0.75 | O36: 0.8 | P36: 0.85 | Q36: 0.9 | R36: 0.9 | S36: 0.9 | T36: =IFERROR(AVERAGE(I36:K36),"") -> 0.71724019
B37: Interest rate on net debt (pre-tax) | C37: % | F37: =Hist!F135 -> 0.042838485 | G37: =Hist!G135 -> 0.045917307 | H37: =Hist!H135 -> 0.090534979 | I37: =Hist!I135 -> 0.07007007 | J37: =Hist!J135 -> 0.079817227 | K37: =Hist!K135 -> 0.063961814 | L37: 0.055 | M37: 0.052 | N37: 0.05 | O37: 0.05 | P37: 0.05 | Q37: 0.05 | R37: 0.05 | S37: 0.05 | T37: =IFERROR(AVERAGE(I37:K37),"") -> 0.071283037
B38: Interest rate on net cash | C38: % | L38: 0.015 | M38: 0.015 | N38: 0.015 | O38: 0.015 | P38: 0.015 | Q38: 0.015 | R38: 0.015 | S38: 0.015 | T38: =IFERROR(AVERAGE(I38:K38),"")
B39: Interest share of lease payments | C39: % | E39: =Hist!E133 -> 0.20006281 | F39: =Hist!F133 -> 0.2 | G39: =Hist!G133 -> 0.2 | H39: =Hist!H133 -> 0.2 | I39: =Hist!I133 -> 0.2 | J39: =Hist!J133 -> 0.19994982 | K39: =Hist!K133 -> 0.20009438 | L39: 0.2 | M39: 0.2 | N39: 0.2 | O39: 0.2 | P39: 0.2 | Q39: 0.2 | R39: 0.2 | S39: 0.2 | T39: =IFERROR(AVERAGE(I39:K39),"") -> 0.20001474
B40: Minority share of net profit | C40: % | E40: =Hist!E134 -> 0.0099320439 | F40: =Hist!F134 -> 0.0099502488 | G40: =Hist!G134 -> 0.0099454604 | H40: =Hist!H134 -> 0.01001955 | I40: =Hist!I134 -> 0.0099030763 | J40: =Hist!J134 -> 0.0099776363 | K40: =Hist!K134 -> 0.010017678 | L40: 0.01 | M40: 0.01 | N40: 0.01 | O40: 0.01 | P40: 0.01 | Q40: 0.01 | R40: 0.01 | S40: 0.01 | T40: =IFERROR(AVERAGE(I40:K40),"") -> 0.0099661303
B42: B. Scenario adjustments – added to every forecast year of the base case
B43: Driver | E43: Bear | F43: Base | G43: Bull | H43: Active | J43: Comment
B44: Volume / like-for-like growth, all segments (pp p.a.) | E44: -0.015 | F44: 0 | G44: 0.01 | H44: =CHOOSE(Inputs!$C$54,E44,F44,G44) -> 0 | J44: Weaker customer intake / churn in Bear
B45: Price/mix growth, all segments (pp p.a.) | E45: -0.01 | F45: 0 | G45: 0.005 | H45: =CHOOSE(Inputs!$C$54,E45,F45,G45) -> 0 | J45: Pricing power tested by low-cost competition
B46: Net new locations per segment per year (count, location mode) | E46: -1 | F46: 0 | G46: 1 | H46: =CHOOSE(Inputs!$C$54,E46,F46,G46) -> 0 | J46: Slower / faster roll-out
B47: COGS in % of revenue (pp) | E47: 0.01 | F47: 0 | G47: -0.005 | H47: =CHOOSE(Inputs!$C$54,E47,F47,G47) -> 0 | J47: Input-cost inflation vs. procurement gains
B48: Personnel expenses, variable part (pp of revenue) | E48: 0.005 | F48: 0 | G48: -0.003 | H48: =CHOOSE(Inputs!$C$54,E48,F48,G48) -> 0 | J48: Wage inflation vs. productivity
B49: Other opex, variable part (pp of revenue) | E49: 0.005 | F49: 0 | G49: -0.002 | H49: =CHOOSE(Inputs!$C$54,E49,F49,G49) -> 0 | J49: Marketing / service cost pressure vs. scale
B50: Maintenance capex in % of revenue (pp) | E50: 0.003 | F50: 0 | G50: 0 | H50: =CHOOSE(Inputs!$C$54,E50,F50,G50) -> 0 | J50: Higher maintenance capex in Bear
B51: Terminal growth (pp) | E51: -0.005 | F51: 0 | G51: 0.0025 | H51: =CHOOSE(Inputs!$C$54,E51,F51,G51) -> 0 | J51: Long-term growth
B52: Exit multiple, EV/EBITDAaL (x) | E52: -1 | F52: 0 | G52: 1 | H52: =CHOOSE(Inputs!$C$54,E52,F52,G52) -> 0 | J52: Multiple de-/re-rating
B53: Scenario probability (for weighted value) | E53: 0.25 | F53: 0.5 | G53: 0.25 | H53: =SUM(E53:G53) -> 1 | J53: Must sum to 100% (sum shown in Active column)
B56: C. Live drivers used by the model (base case + active scenario adjustment + sensitivity adjustment)
B58: ="Volume growth – "&Inputs!$C$73&" (segment mode)" -> Volume growth – Norway (segment mode) | C58: % | L58: =L12+$H$44+N(Sensitivity!$D$5) -> 0.026 | M58: =M12+$H$44+N(Sensitivity!$D$5) -> 0.024 | N58: =N12+$H$44+N(Sensitivity!$D$5) -> 0.022 | O58: =O12+$H$44+N(Sensitivity!$D$5) -> 0.02 | P58: =P12+$H$44+N(Sensitivity!$D$5) -> 0.018 | Q58: =Q12+$H$44+N(Sensitivity!$D$5) -> 0.016 | R58: =R12+$H$44+N(Sensitivity!$D$5) -> 0.014 | S58: =S12+$H$44+N(Sensitivity!$D$5) -> 0.012
B59: ="Price/mix growth – "&Inputs!$C$73&"" -> Price/mix growth – Norway | C59: % | L59: =L13+$H$45 -> 0.034 | M59: =M13+$H$45 -> 0.03 | N59: =N13+$H$45 -> 0.028 | O59: =O13+$H$45 -> 0.026 | P59: =P13+$H$45 -> 0.025 | Q59: =Q13+$H$45 -> 0.024 | R59: =R13+$H$45 -> 0.023 | S59: =S13+$H$45 -> 0.022
B60: ="Volume growth – "&Inputs!$C$74&" (segment mode)" -> Volume growth – Sweden (segment mode) | C60: % | L60: =L14+$H$44+N(Sensitivity!$D$5) -> 0.03 | M60: =M14+$H$44+N(Sensitivity!$D$5) -> 0.028 | N60: =N14+$H$44+N(Sensitivity!$D$5) -> 0.026 | O60: =O14+$H$44+N(Sensitivity!$D$5) -> 0.023 | P60: =P14+$H$44+N(Sensitivity!$D$5) -> 0.02 | Q60: =Q14+$H$44+N(Sensitivity!$D$5) -> 0.018 | R60: =R14+$H$44+N(Sensitivity!$D$5) -> 0.015 | S60: =S14+$H$44+N(Sensitivity!$D$5) -> 0.013
B61: ="Price/mix growth – "&Inputs!$C$74&"" -> Price/mix growth – Sweden | C61: % | L61: =L15+$H$45 -> 0.032 | M61: =M15+$H$45 -> 0.03 | N61: =N15+$H$45 -> 0.028 | O61: =O15+$H$45 -> 0.026 | P61: =P15+$H$45 -> 0.025 | Q61: =Q15+$H$45 -> 0.024 | R61: =R15+$H$45 -> 0.023 | S61: =S15+$H$45 -> 0.022
B62: ="Volume growth – "&Inputs!$C$75&" (segment mode)" -> Volume growth – Denmark & Finland (segment mode) | C62: % | L62: =L16+$H$44+N(Sensitivity!$D$5) -> 0.055 | M62: =M16+$H$44+N(Sensitivity!$D$5) -> 0.05 | N62: =N16+$H$44+N(Sensitivity!$D$5) -> 0.045 | O62: =O16+$H$44+N(Sensitivity!$D$5) -> 0.04 | P62: =P16+$H$44+N(Sensitivity!$D$5) -> 0.035 | Q62: =Q16+$H$44+N(Sensitivity!$D$5) -> 0.03 | R62: =R16+$H$44+N(Sensitivity!$D$5) -> 0.025 | S62: =S16+$H$44+N(Sensitivity!$D$5) -> 0.02
B63: ="Price/mix growth – "&Inputs!$C$75&"" -> Price/mix growth – Denmark & Finland | C63: % | L63: =L17+$H$45 -> 0.03 | M63: =M17+$H$45 -> 0.028 | N63: =N17+$H$45 -> 0.027 | O63: =O17+$H$45 -> 0.026 | P63: =P17+$H$45 -> 0.025 | Q63: =Q17+$H$45 -> 0.024 | R63: =R17+$H$45 -> 0.023 | S63: =S17+$H$45 -> 0.022
B64: ="Like-for-like growth per location – "&Inputs!$C$73&" (location mode)" -> Like-for-like growth per location – Norway (location mode) | C64: % | L64: =L18+$H$44+N(Sensitivity!$D$5) -> 0.008 | M64: =M18+$H$44+N(Sensitivity!$D$5) -> 0.007 | N64: =N18+$H$44+N(Sensitivity!$D$5) -> 0.006 | O64: =O18+$H$44+N(Sensitivity!$D$5) -> 0.005 | P64: =P18+$H$44+N(Sensitivity!$D$5) -> 0.004 | Q64: =Q18+$H$44+N(Sensitivity!$D$5) -> 0.003 | R64: =R18+$H$44+N(Sensitivity!$D$5) -> 0.003 | S64: =S18+$H$44+N(Sensitivity!$D$5) -> 0.003
B65: ="Like-for-like growth per location – "&Inputs!$C$74&" (location mode)" -> Like-for-like growth per location – Sweden (location mode) | C65: % | L65: =L19+$H$44+N(Sensitivity!$D$5) -> 0.01 | M65: =M19+$H$44+N(Sensitivity!$D$5) -> 0.009 | N65: =N19+$H$44+N(Sensitivity!$D$5) -> 0.008 | O65: =O19+$H$44+N(Sensitivity!$D$5) -> 0.007 | P65: =P19+$H$44+N(Sensitivity!$D$5) -> 0.006 | Q65: =Q19+$H$44+N(Sensitivity!$D$5) -> 0.005 | R65: =R19+$H$44+N(Sensitivity!$D$5) -> 0.004 | S65: =S19+$H$44+N(Sensitivity!$D$5) -> 0.003
B66: ="Like-for-like growth per location – "&Inputs!$C$75&" (location mode)" -> Like-for-like growth per location – Denmark & Finland (location mode) | C66: % | L66: =L20+$H$44+N(Sensitivity!$D$5) -> 0.015 | M66: =M20+$H$44+N(Sensitivity!$D$5) -> 0.014 | N66: =N20+$H$44+N(Sensitivity!$D$5) -> 0.012 | O66: =O20+$H$44+N(Sensitivity!$D$5) -> 0.01 | P66: =P20+$H$44+N(Sensitivity!$D$5) -> 0.009 | Q66: =Q20+$H$44+N(Sensitivity!$D$5) -> 0.008 | R66: =R20+$H$44+N(Sensitivity!$D$5) -> 0.006 | S66: =S20+$H$44+N(Sensitivity!$D$5) -> 0.005
B67: ="Net new locations – "&Inputs!$C$73&" (location mode)" -> Net new locations – Norway (location mode) | C67: # | L67: =L21+$H$46 -> 2 | M67: =M21+$H$46 -> 2 | N67: =N21+$H$46 -> 2 | O67: =O21+$H$46 -> 2 | P67: =P21+$H$46 -> 2 | Q67: =Q21+$H$46 -> 1 | R67: =R21+$H$46 -> 1 | S67: =S21+$H$46 -> 1
B68: ="Net new locations – "&Inputs!$C$74&" (location mode)" -> Net new locations – Sweden (location mode) | C68: # | L68: =L22+$H$46 -> 2 | M68: =M22+$H$46 -> 2 | N68: =N22+$H$46 -> 2 | O68: =O22+$H$46 -> 2 | P68: =P22+$H$46 -> 1 | Q68: =Q22+$H$46 -> 1 | R68: =R22+$H$46 -> 1 | S68: =S22+$H$46 -> 1
B69: ="Net new locations – "&Inputs!$C$75&" (location mode)" -> Net new locations – Denmark & Finland (location mode) | C69: # | L69: =L23+$H$46 -> 3 | M69: =M23+$H$46 -> 3 | N69: =N23+$H$46 -> 3 | O69: =O23+$H$46 -> 2 | P69: =P23+$H$46 -> 2 | Q69: =Q23+$H$46 -> 2 | R69: =R23+$H$46 -> 1 | S69: =S23+$H$46 -> 1
B70: COGS in % of revenue | C70: % | L70: =L24+$H$47 -> 0.366 | M70: =M24+$H$47 -> 0.366 | N70: =N24+$H$47 -> 0.366 | O70: =O24+$H$47 -> 0.366 | P70: =P24+$H$47 -> 0.366 | Q70: =Q24+$H$47 -> 0.366 | R70: =R24+$H$47 -> 0.366 | S70: =S24+$H$47 -> 0.366
B71: Personnel expenses – variable part, in % of revenue | C71: % | L71: =L25+$H$48 -> 0.0872 | M71: =M25+$H$48 -> 0.0872 | N71: =N25+$H$48 -> 0.0872 | O71: =O25+$H$48 -> 0.0872 | P71: =P25+$H$48 -> 0.0872 | Q71: =Q25+$H$48 -> 0.0872 | R71: =R25+$H$48 -> 0.0872 | S71: =S25+$H$48 -> 0.0872
B72: Other opex – variable part, in % of revenue | C72: % | L72: =L26+$H$49-N(Sensitivity!$D$6) -> 0.0595 | M72: =M26+$H$49-N(Sensitivity!$D$6) -> 0.0595 | N72: =N26+$H$49-N(Sensitivity!$D$6) -> 0.0595 | O72: =O26+$H$49-N(Sensitivity!$D$6) -> 0.0595 | P72: =P26+$H$49-N(Sensitivity!$D$6) -> 0.0595 | Q72: =Q26+$H$49-N(Sensitivity!$D$6) -> 0.0595 | R72: =R26+$H$49-N(Sensitivity!$D$6) -> 0.0595 | S72: =S26+$H$49-N(Sensitivity!$D$6) -> 0.0595
B73: Cost inflation on the fixed cost base and rent | C73: % | L73: =L27 -> 0.03 | M73: =M27 -> 0.027 | N73: =N27 -> 0.025 | O73: =O27 -> 0.025 | P73: =P27 -> 0.025 | Q73: =Q27 -> 0.025 | R73: =R27 -> 0.025 | S73: =S27 -> 0.025
B74: Real growth in the fixed cost base (location mode: from the locations) | C74: % | L74: =IF(Inputs!$C$72=2,(1-$H$102)*Model!L55,L28) -> 0.022780374 | M74: =IF(Inputs!$C$72=2,(1-$H$102)*Model!M55,M28) -> 0.023809524 | N74: =IF(Inputs!$C$72=2,(1-$H$102)*Model!N55,N28) -> 0.023076923 | O74: =IF(Inputs!$C$72=2,(1-$H$102)*Model!O55,O28) -> 0.020788913 | P74: =IF(Inputs!$C$72=2,(1-$H$102)*Model!P55,P28) -> 0.017116183 | Q74: =IF(Inputs!$C$72=2,(1-$H$102)*Model!Q55,Q28) -> 0.013691684 | R74: =IF(Inputs!$C$72=2,(1-$H$102)*Model!R55,R28) -> 0.010458167 | S74: =IF(Inputs!$C$72=2,(1-$H$102)*Model!S55,S28) -> 0.0088408644
B75: Lease payments in % of revenue (IFRS 16, segment mode) | C75: % | L75: =L29 -> 0.078 | M75: =M29 -> 0.078 | N75: =N29 -> 0.077 | O75: =O29 -> 0.077 | P75: =P29 -> 0.077 | Q75: =Q29 -> 0.077 | R75: =R29 -> 0.077 | S75: =S29 -> 0.077
B76: D&A (owned assets) in % of revenue | C76: % | L76: =L30 -> 0.044 | M76: =M30 -> 0.044 | N76: =N30 -> 0.044 | O76: =O30 -> 0.044 | P76: =P30 -> 0.044 | Q76: =Q30 -> 0.044 | R76: =R30 -> 0.044 | S76: =S30 -> 0.044
B77: Maintenance capex in % of revenue | C77: % | L77: =L31+$H$50 -> 0.05 | M77: =M31+$H$50 -> 0.05 | N77: =N31+$H$50 -> 0.05 | O77: =O31+$H$50 -> 0.05 | P77: =P31+$H$50 -> 0.05 | Q77: =Q31+$H$50 -> 0.05 | R77: =R31+$H$50 -> 0.05 | S77: =S31+$H$50 -> 0.05
B78: Sales-to-capital for growth capex (segment mode) | C78: x | L78: =L32 -> 2 | M78: =M32 -> 2 | N78: =N32 -> 2 | O78: =O32 -> 2 | P78: =P32 -> 2 | Q78: =Q32 -> 2 | R78: =R32 -> 2 | S78: =S32 -> 2
B79: Capex per new location, NOKm (location mode) | C79: NOKm | L79: =L33 -> 22 | M79: =M33 -> 22.6 | N79: =N33 -> 23.1 | O79: =O33 -> 23.7 | P79: =P33 -> 24.3 | Q79: =Q33 -> 24.9 | R79: =R33 -> 25.5 | S79: =S33 -> 26.1
B80: NWC in % of revenue | C80: % | L80: =L34 -> -0.065 | M80: =M34 -> -0.065 | N80: =N34 -> -0.065 | O80: =O34 -> -0.065 | P80: =P34 -> -0.065 | Q80: =Q34 -> -0.065 | R80: =R34 -> -0.065 | S80: =S34 -> -0.065
B81: Tax rate | C81: % | L81: =L35 -> 0.22 | M81: =M35 -> 0.22 | N81: =N35 -> 0.22 | O81: =O35 -> 0.22 | P81: =P35 -> 0.22 | Q81: =Q35 -> 0.22 | R81: =R35 -> 0.22 | S81: =S35 -> 0.22
B82: Dividend payout ratio | C82: % | L82: =L36 -> 0.65 | M82: =M36 -> 0.7 | N82: =N36 -> 0.75 | O82: =O36 -> 0.8 | P82: =P36 -> 0.85 | Q82: =Q36 -> 0.9 | R82: =R36 -> 0.9 | S82: =S36 -> 0.9
B83: Interest rate on net debt (pre-tax) | C83: % | L83: =L37 -> 0.055 | M83: =M37 -> 0.052 | N83: =N37 -> 0.05 | O83: =O37 -> 0.05 | P83: =P37 -> 0.05 | Q83: =Q37 -> 0.05 | R83: =R37 -> 0.05 | S83: =S37 -> 0.05
B84: Interest rate on net cash | C84: % | L84: =L38 -> 0.015 | M84: =M38 -> 0.015 | N84: =N38 -> 0.015 | O84: =O38 -> 0.015 | P84: =P38 -> 0.015 | Q84: =Q38 -> 0.015 | R84: =R38 -> 0.015 | S84: =S38 -> 0.015
B85: Interest share of lease payments | C85: % | L85: =L39 -> 0.2 | M85: =M39 -> 0.2 | N85: =N39 -> 0.2 | O85: =O39 -> 0.2 | P85: =P39 -> 0.2 | Q85: =Q39 -> 0.2 | R85: =R39 -> 0.2 | S85: =S39 -> 0.2
B86: Minority share of net profit | C86: % | L86: =L40 -> 0.01 | M86: =M40 -> 0.01 | N86: =N40 -> 0.01 | O86: =O40 -> 0.01 | P86: =P40 -> 0.01 | Q86: =Q40 -> 0.01 | R86: =R40 -> 0.01 | S86: =S40 -> 0.01
B89: D. Terminal value assumptions
B90: Assumption | E90: Input | H90: Active | J90: Comment
B91: Terminal growth rate (nominal) | E91: 0.02 | H91: =E91+$H$51 -> 0.02 | J91: Long-run nominal growth; should not exceed long-term GDP growth (~2-3%)
B92: Terminal EBIT adj. margin – override (blank = last forecast year) | H92: =IF(E92="",Model!$S$86,E92) -> 0.19059585 | J92: Leave blank to use the final forecast year's margin (already scenario-adjusted)
B93: Return on new invested capital (RONIC) | E93: 0.12 | H93: =E93 -> 0.12 | J93: Set close to WACC for companies without a lasting competitive advantage
B94: Long-term tax rate | E94: 0.22 | H94: =E94 -> 0.22
B95: Exit multiple, EV / EBITDAaL (pre-IFRS 16) | E95: 8.5 | H95: =E95+$H$52 -> 8.5 | J95: Cross-check only unless given weight on the Inputs sheet
B98: E. Cost structure and capital allocation
B99: Assumption | E99: Input | H99: Active | J99: Comment
B100: Fixed share of personnel expenses (last actual year) | E100: 0.6 | H100: =E100 -> 0.6 | J100: Staffing per location is largely fixed. The fixed part grows with cost inflation and capacity (section C), not with revenue
B101: Fixed share of other opex (last actual year) | E101: 0.5 | H101: =E101 -> 0.5 | J101: IT, admin and premises-related costs are fixed; marketing and variable services scale with revenue
B102: Central share of fixed costs (inflation only, location mode) | E102: 0.25 | H102: =E102 -> 0.25 | J102: Head office, IT and brand costs do not grow with the number of locations – the source of operating leverage from openings
B103: Target leverage for buybacks (NIBD / EBITDAaL) | E103: 0.75 | H103: =E103 -> 0.75 | J103: Cash above this leverage is returned to shareholders when the switch below is on
B104: Return excess cash via share buybacks (1 = yes, 0 = let cash build up) | E104: 1 | H104: =E104 -> 1 | J104: Keeps the forecast capital structure close to the WACC assumption and lifts EPS; 0 = cash piles up at the cash rate
B105: Assumed annual share price growth for buybacks | E105: 0.08 | H105: =E105 -> 0.08 | J105: Buyback price = current share price grown at this rate (deliberately not linked to the cost of equity – avoids a circular reference)
B108: F. Location engine – ramp-up of new locations (location mode)
B109: Assumption | E109: Input | H109: Active | J109: Comment
B110: Opening year: volume in % of a mature location | E110: 0.35 | H110: =E110 -> 0.35 | J110: Opened during the year and still filling up – roughly half a year at ~70% of mature volume
B111: Second year: volume in % of a mature location | E111: 0.75 | H111: =E111 -> 0.75 | J111: Most new locations reach 70-80% of mature volume in their first full year
B112: Third year: volume in % of a mature location (100% from the fourth year) | E112: 0.95 | H112: =E112 -> 0.95 | J112: Check the curve against the company's own disclosures on club / store maturity

Sheet Calculations >>>
D8: =Inputs!$C$6 -> Example Company ASA
D9: Financial Model
D12: Calculations
D14: The calculation engine. No inputs except known one-off items.
D17: Model | E17: Operating model | F17: Revenue build (locations or volume x price), earnings build, investments, free cash flow and financing
D20: ← Back to cover

Sheet Model
B1: Operating Model – Calculations | T1: =Inputs!$C$6&" | Scenario: "&Inputs!$C$53 -> Example Company ASA | Scenario: Base
B2: Calculation engine: history is linked from Hist, forecasts are driven by the live drivers on Drivers. Results are presented on Output.
E3: =Inputs!$C$17+0 -> 2019 | F3: =Inputs!$C$17+1 -> 2020 | G3: =Inputs!$C$17+2 -> 2021 | H3: =Inputs!$C$17+3 -> 2022 | I3: =Inputs!$C$17+4 -> 2023 | J3: =Inputs!$C$17+5 -> 2024 | K3: =Inputs!$C$17+6 -> 2025 | L3: =Inputs!$C$19+0 -> 2026 | M3: =Inputs!$C$19+1 -> 2027 | N3: =Inputs!$C$19+2 -> 2028 | O3: =Inputs!$C$19+3 -> 2029 | P3: =Inputs!$C$19+4 -> 2030 | Q3: =Inputs!$C$19+5 -> 2031 | R3: =Inputs!$C$19+6 -> 2032 | S3: =Inputs!$C$19+7 -> 2033
E4: Historicals | L4: Explicit forecast
B5: ="("&Inputs!$C$11&")" -> (NOKm) | E5: =E3&"A" -> 2019A | F5: =F3&"A" -> 2020A | G5: =G3&"A" -> 2021A | H5: =H3&"A" -> 2022A | I5: =I3&"A" -> 2023A | J5: =J3&"A" -> 2024A | K5: =K3&"A" -> 2025A | L5: =L3&"E" -> 2026E | M5: =M3&"E" -> 2027E | N5: =N3&"E" -> 2028E | O5: =O3&"E" -> 2029E | P5: =P3&"E" -> 2030E | Q5: =Q3&"E" -> 2031E | R5: =R3&"E" -> 2032E | S5: =S3&"E" -> 2033E | V5: Notes
B7: 1. Revenue build – locations x volume per location x price/mix, per segment
B9: =Inputs!$C$73 -> Norway
B10: Locations (end of year) | C10: # | E10: =Hist!E77 -> 82 | F10: =Hist!F77 -> 83 | G10: =Hist!G77 -> 85 | H10: =Hist!H77 -> 88 | I10: =Hist!I77 -> 89 | J10: =Hist!J77 -> 91 | K10: =Hist!K77 -> 94 | L10: =K10+L11 -> 96 | M10: =L10+M11 -> 98 | N10: =M10+N11 -> 100 | O10: =N10+O11 -> 102 | P10: =O10+P11 -> 104 | Q10: =P10+Q11 -> 105 | R10: =Q10+R11 -> 106 | S10: =R10+S11 -> 107
B11: Net new locations | C11: # | F11: =F10-E10 -> 1 | G11: =G10-F10 -> 2 | H11: =H10-G10 -> 3 | I11: =I10-H10 -> 1 | J11: =J10-I10 -> 2 | K11: =K10-J10 -> 3 | L11: =Drivers!L67 -> 2 | M11: =Drivers!M67 -> 2 | N11: =Drivers!N67 -> 2 | O11: =Drivers!O67 -> 2 | P11: =Drivers!P67 -> 2 | Q11: =Drivers!Q67 -> 1 | R11: =Drivers!R67 -> 1 | S11: =Drivers!S67 -> 1
B12: Openings still ramping up (forecast openings only) | C12: # | E12: =0 -> 0 | F12: =0 -> 0 | G12: =0 -> 0 | H12: =0 -> 0 | I12: =0 -> 0 | J12: =0 -> 0 | K12: =0 -> 0 | L12: =MAX(0,L11) -> 2 | M12: =MAX(0,M11) -> 2 | N12: =MAX(0,N11) -> 2 | O12: =MAX(0,O11) -> 2 | P12: =MAX(0,P11) -> 2 | Q12: =MAX(0,Q11) -> 1 | R12: =MAX(0,R11) -> 1 | S12: =MAX(0,S11) -> 1
B13: Mature-equivalent locations | C13: # | E13: =E10 -> 82 | F13: =F10 -> 83 | G13: =G10 -> 85 | H13: =H10 -> 88 | I13: =I10 -> 89 | J13: =J10 -> 91 | K13: =K10 -> 94 | L13: =K13+MIN(0,L11)+L12*Drivers!$H$110+K12*(Drivers!$H$111-Drivers!$H$110)+J12*(Drivers!$H$112-Drivers!$H$111)+I12*(1-Drivers!$H$112) -> 94.7 | M13: =L13+MIN(0,M11)+M12*Drivers!$H$110+L12*(Drivers!$H$111-Drivers!$H$110)+K12*(Drivers!$H$112-Drivers!$H$111)+J12*(1-Drivers!$H$112) -> 96.2 | N13: =M13+MIN(0,N11)+N12*Drivers!$H$110+M12*(Drivers!$H$111-Drivers!$H$110)+L12*(Drivers!$H$112-Drivers!$H$111)+K12*(1-Drivers!$H$112) -> 98.1 | O13: =N13+MIN(0,O11)+O12*Drivers!$H$110+N12*(Drivers!$H$111-Drivers!$H$110)+M12*(Drivers!$H$112-Drivers!$H$111)+L12*(1-Drivers!$H$112) -> 100.1 | P13: =O13+MIN(0,P11)+P12*Drivers!$H$110+O12*(Drivers!$H$111-Drivers!$H$110)+N12*(Drivers!$H$112-Drivers!$H$111)+M12*(1-Drivers!$H$112) -> 102.1 | Q13: =P13+MIN(0,Q11)+Q12*Drivers!$H$110+P12*(Drivers!$H$111-Drivers!$H$110)+O12*(Drivers!$H$112-Drivers!$H$111)+N12*(1-Drivers!$H$112) -> 103.75 | R13: =Q13+MIN(0,R11)+R12*Drivers!$H$110+Q12*(Drivers!$H$111-Drivers!$H$110)+P12*(Drivers!$H$112-Drivers!$H$111)+O12*(1-Drivers!$H$112) -> 105 | S13: =R13+MIN(0,S11)+S12*Drivers!$H$110+R12*(Drivers!$H$111-Drivers!$H$110)+Q12*(Drivers!$H$112-Drivers!$H$111)+P12*(1-Drivers!$H$112) -> 106.05 | V13: Location mode: existing locations + new ones weighted by the ramp-up curve (Drivers F)
B14: ="Volume per mature location ("&Inputs!$C$76&")" -> Volume per mature location (Customers ('000)) | C14: # | E14: =IF(E10=0,0,E16/E10) -> 3.6585366 | F14: =IF(F10=0,0,F16/F10) -> 3.3855422 | G14: =IF(G10=0,0,G16/G10) -> 3.4 | H14: =IF(H10=0,0,H16/H10) -> 3.5909091 | I14: =IF(I10=0,0,I16/I10) -> 3.6966292 | J14: =IF(J10=0,0,J16/J10) -> 3.7032967 | K14: =IF(K10=0,0,K16/K10) -> 3.6914894 | L14: =K14*(1+Drivers!L64) -> 3.7210213 | M14: =L14*(1+Drivers!M64) -> 3.7470684 | N14: =M14*(1+Drivers!N64) -> 3.7695508 | O14: =N14*(1+Drivers!O64) -> 3.7883986 | P14: =O14*(1+Drivers!P64) -> 3.8035522 | Q14: =P14*(1+Drivers!Q64) -> 3.8149628 | R14: =Q14*(1+Drivers!R64) -> 3.8264077 | S14: =R14*(1+Drivers!S64) -> 3.837887 | V14: Grows with like-for-like growth (Drivers A)
B15: Like-for-like growth | C15: % | F15: =IF(E14=0,0,F14/E14-1) -> -0.074618474 | G15: =IF(F14=0,0,G14/F14-1) -> 0.0042704626 | H15: =IF(G14=0,0,H14/G14-1) -> 0.056149733 | I15: =IF(H14=0,0,I14/H14-1) -> 0.029441047 | J15: =IF(I14=0,0,J14/I14-1) -> 0.0018036675 | K15: =IF(J14=0,0,K14/J14-1) -> -0.0031883326 | L15: =IF(K14=0,0,L14/K14-1) -> 0.008 | M15: =IF(L14=0,0,M14/L14-1) -> 0.007 | ... S15: =IF(R14=0,0,S14/R14-1) -> 0.003
B16: ="Volume ("&Inputs!$C$76&")" -> Volume (Customers ('000)) | C16: # | E16: =Hist!E74 -> 300 | F16: =Hist!F74 -> 281 | G16: =Hist!G74 -> 289 | H16: =Hist!H74 -> 316 | I16: =Hist!I74 -> 329 | J16: =Hist!J74 -> 337 | K16: =Hist!K74 -> 347 | L16: =IF(Inputs!$C$72=2,L13*L14,K16*(1+Drivers!L58)) -> 352.38071 | M16: =IF(Inputs!$C$72=2,M13*M14,L16*(1+Drivers!M58)) -> 360.46798 | N16: =IF(Inputs!$C$72=2,N13*N14,M16*(1+Drivers!N58)) -> 369.79294 | O16: =IF(Inputs!$C$72=2,O13*O14,N16*(1+Drivers!O58)) -> 379.2187 | P16: =IF(Inputs!$C$72=2,P13*P14,O16*(1+Drivers!P58)) -> 388.34268 | Q16: =IF(Inputs!$C$72=2,Q13*Q14,P16*(1+Drivers!Q58)) -> 395.80239 | R16: =IF(Inputs!$C$72=2,R13*R14,Q16*(1+Drivers!R58)) -> 401.77281 | S16: =IF(Inputs!$C$72=2,S13*S14,R16*(1+Drivers!S58)) -> 407.00791 | V16: Location mode: mature-equivalent locations x volume per location. Segment mode: volume growth (Drivers A)
B17: Volume growth | C17: % | F17: =F16/E16-1 -> -0.063333333 | G17: =G16/F16-1 -> 0.028469751 | H17: =H16/G16-1 -> 0.093425606 | I17: =I16/H16-1 -> 0.041139241 | J17: =J16/I16-1 -> 0.024316109 | K17: =K16/J16-1 -> 0.029673591 | L17: =L16/K16-1 -> 0.015506383 | M17: =M16/L16-1 -> 0.02295037 | ... S17: =S16/R16-1 -> 0.01303
B18: Revenue per unit | C18: NOK '000 | E18: =IF(E16=0,0,E20/E16) -> 6.5 | F18: =IF(F16=0,0,F20/F16) -> 6.3701068 | G18: =IF(G16=0,0,G20/G16) -> 6.5051903 | H18: =IF(H16=0,0,H20/H16) -> 6.8037975 | I18: =IF(I16=0,0,I20/I16) -> 7.112462 | J18: =IF(J16=0,0,J20/J16) -> 7.4332344 | K18: =IF(K16=0,0,K20/K16) -> 7.7521614 | L18: =IF(L16=0,0,L20/L16) -> 8.0157349 | ... S18: =IF(S16=0,0,S20/S16) -> 9.5558956
B19: Price/mix growth | C19: % | F19: =(1+F21)/(1+F17)-1 -> -0.019983575 | G19: =(1+G21)/(1+G17)-1 -> 0.021205853 | H19: =(1+H21)/(1+H17)-1 -> 0.045902909 | I19: =(1+I21)/(1+I17)-1 -> 0.045366509 | J19: =(1+J21)/(1+J17)-1 -> 0.045100053 | K19: =(1+K21)/(1+K17)-1 -> 0.042905543 | L19: =(1+L21)/(1+L17)-1 -> 0.034 | M19: =(1+M21)/(1+M17)-1 -> 0.03 | ... S19: =(1+S21)/(1+S17)-1 -> 0.022
B20: Revenue | C20: NOKm | E20: =Hist!E9 -> 1950 | F20: =Hist!F9 -> 1790 | G20: =Hist!G9 -> 1880 | H20: =Hist!H9 -> 2150 | I20: =Hist!I9 -> 2340 | J20: =Hist!J9 -> 2505 | K20: =Hist!K9 -> 2690 | L20: =IF(K16=0,K20*(1+Drivers!L58),K20*L16/K16)*(1+Drivers!L59) -> 2824.5904 | M20: =IF(L16=0,L20*(1+Drivers!M58),L20*M16/L16)*(1+Drivers!M59) -> 2976.0983 | N20: =IF(M16=0,M20*(1+Drivers!N58),M20*N16/M16)*(1+Drivers!N59) -> 3138.5734 | O20: =IF(N16=0,N20*(1+Drivers!O58),N20*O16/N16)*(1+Drivers!O59) -> 3302.2564 | P20: =IF(O16=0,O20*(1+Drivers!P58),O20*P16/O16)*(1+Drivers!P59) -> 3466.2512 | Q20: =IF(P16=0,P20*(1+Drivers!Q58),P20*Q16/P16)*(1+Drivers!Q59) -> 3617.6228 | R20: =IF(Q16=0,Q20*(1+Drivers!R58),Q20*R16/Q16)*(1+Drivers!R59) -> 3756.6527 | S20: =IF(R16=0,R20*(1+Drivers!S58),R20*S16/R16)*(1+Drivers!S59) -> 3889.3251
B21: Revenue growth | C21: % | F21: =F20/E20-1 -> -0.082051282 | G21: =G20/F20-1 -> 0.05027933 | H21: =H20/G20-1 -> 0.14361702 | I21: =I20/H20-1 -> 0.088372093 | J21: =J20/I20-1 -> 0.070512821 | K21: =K20/J20-1 -> 0.073852295 | L21: =L20/K20-1 -> 0.0500336 | M21: =M20/L20-1 -> 0.053638881 | ... S21: =S20/R20-1 -> 0.03531666
B23: =Inputs!$C$74 -> Sweden
B24: Locations (end of year) | C24: # | E24: =Hist!E78 -> 68 | F24: =Hist!F78 -> 69 | G24: =Hist!G78 -> 70 | H24: =Hist!H78 -> 73 | I24: =Hist!I78 -> 75 | J24: =Hist!J78 -> 76 | K24: =Hist!K78 -> 77 | L24: =K24+L25 -> 79 | M24: =L24+M25 -> 81 | N24: =M24+N25 -> 83 | O24: =N24+O25 -> 85 | P24: =O24+P25 -> 86 | Q24: =P24+Q25 -> 87 | R24: =Q24+R25 -> 88 | S24: =R24+S25 -> 89
B25: Net new locations | C25: # | F25: =F24-E24 -> 1 | G25: =G24-F24 -> 1 | H25: =H24-G24 -> 3 | I25: =I24-H24 -> 2 | J25: =J24-I24 -> 1 | K25: =K24-J24 -> 1 | L25: =Drivers!L68 -> 2 | M25: =Drivers!M68 -> 2 | N25: =Drivers!N68 -> 2 | O25: =Drivers!O68 -> 2 | P25: =Drivers!P68 -> 1 | Q25: =Drivers!Q68 -> 1 | R25: =Drivers!R68 -> 1 | S25: =Drivers!S68 -> 1
B26: Openings still ramping up (forecast openings only) | C26: # | E26: =0 -> 0 | F26: =0 -> 0 | G26: =0 -> 0 | H26: =0 -> 0 | I26: =0 -> 0 | J26: =0 -> 0 | K26: =0 -> 0 | L26: =MAX(0,L25) -> 2 | M26: =MAX(0,M25) -> 2 | N26: =MAX(0,N25) -> 2 | O26: =MAX(0,O25) -> 2 | P26: =MAX(0,P25) -> 1 | Q26: =MAX(0,Q25) -> 1 | R26: =MAX(0,R25) -> 1 | S26: =MAX(0,S25) -> 1
B27: Mature-equivalent locations | C27: # | E27: =E24 -> 68 | F27: =F24 -> 69 | G27: =G24 -> 70 | H27: =H24 -> 73 | I27: =I24 -> 75 | J27: =J24 -> 76 | K27: =K24 -> 77 | L27: =K27+MIN(0,L25)+L26*Drivers!$H$110+K26*(Drivers!$H$111-Drivers!$H$110)+J26*(Drivers!$H$112-Drivers!$H$111)+I26*(1-Drivers!$H$112) -> 77.7 | M27: =L27+MIN(0,M25)+M26*Drivers!$H$110+L26*(Drivers!$H$111-Drivers!$H$110)+K26*(Drivers!$H$112-Drivers!$H$111)+J26*(1-Drivers!$H$112) -> 79.2 | N27: =M27+MIN(0,N25)+N26*Drivers!$H$110+M26*(Drivers!$H$111-Drivers!$H$110)+L26*(Drivers!$H$112-Drivers!$H$111)+K26*(1-Drivers!$H$112) -> 81.1 | O27: =N27+MIN(0,O25)+O26*Drivers!$H$110+N26*(Drivers!$H$111-Drivers!$H$110)+M26*(Drivers!$H$112-Drivers!$H$111)+L26*(1-Drivers!$H$112) -> 83.1 | P27: =O27+MIN(0,P25)+P26*Drivers!$H$110+O26*(Drivers!$H$111-Drivers!$H$110)+N26*(Drivers!$H$112-Drivers!$H$111)+M26*(1-Drivers!$H$112) -> 84.75 | Q27: =P27+MIN(0,Q25)+Q26*Drivers!$H$110+P26*(Drivers!$H$111-Drivers!$H$110)+O26*(Drivers!$H$112-Drivers!$H$111)+N26*(1-Drivers!$H$112) -> 86 | R27: =Q27+MIN(0,R25)+R26*Drivers!$H$110+Q26*(Drivers!$H$111-Drivers!$H$110)+P26*(Drivers!$H$112-Drivers!$H$111)+O26*(1-Drivers!$H$112) -> 87.05 | S27: =R27+MIN(0,S25)+S26*Drivers!$H$110+R26*(Drivers!$H$111-Drivers!$H$110)+Q26*(Drivers!$H$112-Drivers!$H$111)+P26*(1-Drivers!$H$112) -> 88.05
B28: ="Volume per mature location ("&Inputs!$C$76&")" -> Volume per mature location (Customers ('000)) | C28: # | E28: =IF(E24=0,0,E30/E24) -> 3.3529412 | F28: =IF(F24=0,0,F30/F24) -> 3.0724638 | G28: =IF(G24=0,0,G30/G24) -> 3.1285714 | H28: =IF(H24=0,0,H30/H24) -> 3.3835616 | I28: =IF(I24=0,0,I30/I24) -> 3.4533333 | J28: =IF(J24=0,0,J30/J24) -> 3.5131579 | K28: =IF(K24=0,0,K30/K24) -> 3.5584416 | L28: =K28*(1+Drivers!L65) -> 3.594026 | M28: =L28*(1+Drivers!M65) -> 3.6263722 | N28: =M28*(1+Drivers!N65) -> 3.6553832 | O28: =N28*(1+Drivers!O65) -> 3.6809709 | P28: =O28*(1+Drivers!P65) -> 3.7030567 | Q28: =P28*(1+Drivers!Q65) -> 3.721572 | R28: =Q28*(1+Drivers!R65) -> 3.7364583 | S28: =R28*(1+Drivers!S65) -> 3.7476676
B29: Like-for-like growth | C29: % | F29: =IF(E28=0,0,F28/E28-1) -> -0.083651157 | G29: =IF(F28=0,0,G28/F28-1) -> 0.018261456 | H29: =IF(G28=0,0,H28/G28-1) -> 0.081503722 | I29: =IF(H28=0,0,I28/H28-1) -> 0.020620783 | J29: =IF(I28=0,0,J28/I28-1) -> 0.017323715 | K29: =IF(J28=0,0,K28/J28-1) -> 0.012889732 | L29: =IF(K28=0,0,L28/K28-1) -> 0.01 | M29: =IF(L28=0,0,M28/L28-1) -> 0.009 | ... S29: =IF(R28=0,0,S28/R28-1) -> 0.003
B30: ="Volume ("&Inputs!$C$76&")" -> Volume (Customers ('000)) | C30: # | E30: =Hist!E75 -> 228 | F30: =Hist!F75 -> 212 | G30: =Hist!G75 -> 219 | H30: =Hist!H75 -> 247 | I30: =Hist!I75 -> 259 | J30: =Hist!J75 -> 267 | K30: =Hist!K75 -> 274 | L30: =IF(Inputs!$C$72=2,L27*L28,K30*(1+Drivers!L60)) -> 279.25582 | M30: =IF(Inputs!$C$72=2,M27*M28,L30*(1+Drivers!M60)) -> 287.20868 | N30: =IF(Inputs!$C$72=2,N27*N28,M30*(1+Drivers!N60)) -> 296.45158 | O30: =IF(Inputs!$C$72=2,O27*O28,N30*(1+Drivers!O60)) -> 305.88868 | P30: =IF(Inputs!$C$72=2,P27*P28,O30*(1+Drivers!P60)) -> 313.83405 | Q30: =IF(Inputs!$C$72=2,Q27*Q28,P30*(1+Drivers!Q60)) -> 320.05519 | R30: =IF(Inputs!$C$72=2,R27*R28,Q30*(1+Drivers!R60)) -> 325.25869 | S30: =IF(Inputs!$C$72=2,S27*S28,R30*(1+Drivers!S60)) -> 329.98214
B31: Volume growth | C31: % | F31: =F30/E30-1 -> -0.070175439 | G31: =G30/F30-1 -> 0.033018868 | H31: =H30/G30-1 -> 0.12785388 | I31: =I30/H30-1 -> 0.048582996 | J31: =J30/I30-1 -> 0.030888031 | K31: =K30/J30-1 -> 0.026217228 | L31: =L30/K30-1 -> 0.019181818 | M31: =M30/L30-1 -> 0.028478764 | ... S31: =S30/R30-1 -> 0.014522114
B32: Revenue per unit | C32: NOK '000 | E32: =IF(E30=0,0,E34/E30) -> 5.4385965 | F32: =IF(F30=0,0,F34/F30) -> 5.3301887 | G32: =IF(G30=0,0,G34/G30) -> 5.43379 | H32: =IF(H30=0,0,H34/H30) -> 5.6680162 | I32: =IF(I30=0,0,I34/I30) -> 5.965251 | J32: =IF(J30=0,0,J34/J30) -> 6.2359551 | K32: =IF(K30=0,0,K34/K30) -> 6.5145985 | L32: =IF(L30=0,0,L34/L30) -> 6.7230657 | ... S32: =IF(S30=0,0,S34/S30) -> 8.0148501
B33: Price/mix growth | C33: % | F33: =(1+F35)/(1+F31)-1 -> -0.019933049 | G33: =(1+G35)/(1+G31)-1 -> 0.019436699 | H33: =(1+H35)/(1+H31)-1 -> 0.043105501 | I33: =(1+I35)/(1+I31)-1 -> 0.052440706 | J33: =(1+J35)/(1+J31)-1 -> 0.045380168 | K33: =(1+K35)/(1+K31)-1 -> 0.04468337 | L33: =(1+L35)/(1+L31)-1 -> 0.032 | M33: =(1+M35)/(1+M31)-1 -> 0.03 | ... S33: =(1+S35)/(1+S31)-1 -> 0.022
B34: Revenue | C34: NOKm | E34: =Hist!E10 -> 1240 | F34: =Hist!F10 -> 1130 | G34: =Hist!G10 -> 1190 | H34: =Hist!H10 -> 1400 | I34: =Hist!I10 -> 1545 | J34: =Hist!J10 -> 1665 | K34: =Hist!K10 -> 1785 | L34: =IF(K30=0,K34*(1+Drivers!L60),K34*L30/K30)*(1+Drivers!L61) -> 1877.4552 | M34: =IF(L30=0,L34*(1+Drivers!M60),L34*M30/L30)*(1+Drivers!M61) -> 1988.8505 | N34: =IF(M30=0,M34*(1+Drivers!N60),M34*N30/M30)*(1+Drivers!N61) -> 2110.3353 | O34: =IF(N30=0,N34*(1+Drivers!O60),N34*O30/N30)*(1+Drivers!O61) -> 2234.1301 | P34: =IF(O30=0,O34*(1+Drivers!P60),O34*P30/O30)*(1+Drivers!P61) -> 2349.465 | Q34: =IF(P30=0,P34*(1+Drivers!Q60),P34*Q30/P30)*(1+Drivers!Q61) -> 2453.5434 | R34: =IF(Q30=0,Q34*(1+Drivers!R60),Q34*R30/Q30)*(1+Drivers!R61) -> 2550.7825 | S34: =IF(R30=0,R34*(1+Drivers!S60),R34*S30/R30)*(1+Drivers!S61) -> 2644.7574
B35: Revenue growth | C35: % | F35: =F34/E34-1 -> -0.088709677 | G35: =G34/F34-1 -> 0.053097345 | H35: =H34/G34-1 -> 0.17647059 | I35: =I34/H34-1 -> 0.10357143 | J35: =J34/I34-1 -> 0.077669903 | K35: =K34/J34-1 -> 0.072072072 | L35: =L34/K34-1 -> 0.051795636 | M35: =M34/L34-1 -> 0.059333127 | ... S35: =S34/R34-1 -> 0.0368416
B37: =Inputs!$C$75 -> Denmark & Finland
B38: Locations (end of year) | C38: # | E38: =Hist!E79 -> 32 | F38: =Hist!F79 -> 32 | G38: =Hist!G79 -> 33 | H38: =Hist!H79 -> 40 | I38: =Hist!I79 -> 42 | J38: =Hist!J79 -> 44 | K38: =Hist!K79 -> 46 | L38: =K38+L39 -> 49 | M38: =L38+M39 -> 52 | N38: =M38+N39 -> 55 | O38: =N38+O39 -> 57 | P38: =O38+P39 -> 59 | Q38: =P38+Q39 -> 61 | R38: =Q38+R39 -> 62 | S38: =R38+S39 -> 63
B39: Net new locations | C39: # | F39: =F38-E38 -> 0 | G39: =G38-F38 -> 1 | H39: =H38-G38 -> 7 | I39: =I38-H38 -> 2 | J39: =J38-I38 -> 2 | K39: =K38-J38 -> 2 | L39: =Drivers!L69 -> 3 | M39: =Drivers!M69 -> 3 | N39: =Drivers!N69 -> 3 | O39: =Drivers!O69 -> 2 | P39: =Drivers!P69 -> 2 | Q39: =Drivers!Q69 -> 2 | R39: =Drivers!R69 -> 1 | S39: =Drivers!S69 -> 1
B40: Openings still ramping up (forecast openings only) | C40: # | E40: =0 -> 0 | F40: =0 -> 0 | G40: =0 -> 0 | H40: =0 -> 0 | I40: =0 -> 0 | J40: =0 -> 0 | K40: =0 -> 0 | L40: =MAX(0,L39) -> 3 | M40: =MAX(0,M39) -> 3 | N40: =MAX(0,N39) -> 3 | O40: =MAX(0,O39) -> 2 | P40: =MAX(0,P39) -> 2 | Q40: =MAX(0,Q39) -> 2 | R40: =MAX(0,R39) -> 1 | S40: =MAX(0,S39) -> 1
B41: Mature-equivalent locations | C41: # | E41: =E38 -> 32 | F41: =F38 -> 32 | G41: =G38 -> 33 | H41: =H38 -> 40 | I41: =I38 -> 42 | J41: =J38 -> 44 | K41: =K38 -> 46 | L41: =K41+MIN(0,L39)+L40*Drivers!$H$110+K40*(Drivers!$H$111-Drivers!$H$110)+J40*(Drivers!$H$112-Drivers!$H$111)+I40*(1-Drivers!$H$112) -> 47.05 | M41: =L41+MIN(0,M39)+M40*Drivers!$H$110+L40*(Drivers!$H$111-Drivers!$H$110)+K40*(Drivers!$H$112-Drivers!$H$111)+J40*(1-Drivers!$H$112) -> 49.3 | N41: =M41+MIN(0,N39)+N40*Drivers!$H$110+M40*(Drivers!$H$111-Drivers!$H$110)+L40*(Drivers!$H$112-Drivers!$H$111)+K40*(1-Drivers!$H$112) -> 52.15 | O41: =N41+MIN(0,O39)+O40*Drivers!$H$110+N40*(Drivers!$H$111-Drivers!$H$110)+M40*(Drivers!$H$112-Drivers!$H$111)+L40*(1-Drivers!$H$112) -> 54.8 | P41: =O41+MIN(0,P39)+P40*Drivers!$H$110+O40*(Drivers!$H$111-Drivers!$H$110)+N40*(Drivers!$H$112-Drivers!$H$111)+M40*(1-Drivers!$H$112) -> 57.05 | Q41: =P41+MIN(0,Q39)+Q40*Drivers!$H$110+P40*(Drivers!$H$111-Drivers!$H$110)+O40*(Drivers!$H$112-Drivers!$H$111)+N40*(1-Drivers!$H$112) -> 59.1 | R41: =Q41+MIN(0,R39)+R40*Drivers!$H$110+Q40*(Drivers!$H$111-Drivers!$H$110)+P40*(Drivers!$H$112-Drivers!$H$111)+O40*(1-Drivers!$H$112) -> 60.75 | S41: =R41+MIN(0,S39)+S40*Drivers!$H$110+R40*(Drivers!$H$111-Drivers!$H$110)+Q40*(Drivers!$H$112-Drivers!$H$111)+P40*(1-Drivers!$H$112) -> 62
B42: ="Volume per mature location ("&Inputs!$C$76&")" -> Volume per mature location (Customers ('000)) | C42: # | E42: =IF(E38=0,0,E44/E38) -> 3.6875 | F42: =IF(F38=0,0,F44/F38) -> 3.4375 | G42: =IF(G38=0,0,G44/G38) -> 3.5454545 | H42: =IF(H38=0,0,H44/H38) -> 3.3 | I42: =IF(I38=0,0,I44/I38) -> 3.4047619 | J42: =IF(J38=0,0,J44/J38) -> 3.4090909 | K42: =IF(K38=0,0,K44/K38) -> 3.4347826 | L42: =K42*(1+Drivers!L66) -> 3.4863043 | M42: =L42*(1+Drivers!M66) -> 3.5351126 | N42: =M42*(1+Drivers!N66) -> 3.577534 | O42: =N42*(1+Drivers!O66) -> 3.6133093 | P42: =O42*(1+Drivers!P66) -> 3.6458291 | Q42: =P42*(1+Drivers!Q66) -> 3.6749957 | R42: =Q42*(1+Drivers!R66) -> 3.6970457 | S42: =R42*(1+Drivers!S66) -> 3.7155309
B43: Like-for-like growth | C43: % | F43: =IF(E42=0,0,F42/E42-1) -> -0.06779661 | G43: =IF(F42=0,0,G42/F42-1) -> 0.031404959 | H43: =IF(G42=0,0,H42/G42-1) -> -0.069230769 | I43: =IF(H42=0,0,I42/H42-1) -> 0.031746032 | J43: =IF(I42=0,0,J42/I42-1) -> 0.0012714558 | K43: =IF(J42=0,0,K42/J42-1) -> 0.0075362319 | L43: =IF(K42=0,0,L42/K42-1) -> 0.015 | M43: =IF(L42=0,0,M42/L42-1) -> 0.014 | ... S43: =IF(R42=0,0,S42/R42-1) -> 0.005
B44: ="Volume ("&Inputs!$C$76&")" -> Volume (Customers ('000)) | C44: # | E44: =Hist!E76 -> 118 | F44: =Hist!F76 -> 110 | G44: =Hist!G76 -> 117 | H44: =Hist!H76 -> 132 | I44: =Hist!I76 -> 143 | J44: =Hist!J76 -> 150 | K44: =Hist!K76 -> 158 | L44: =IF(Inputs!$C$72=2,L41*L42,K44*(1+Drivers!L62)) -> 164.03062 | M44: =IF(Inputs!$C$72=2,M41*M42,L44*(1+Drivers!M62)) -> 174.28105 | N44: =IF(Inputs!$C$72=2,N41*N42,M44*(1+Drivers!N62)) -> 186.5684 | O44: =IF(Inputs!$C$72=2,O41*O42,N44*(1+Drivers!O62)) -> 198.00935 | P44: =IF(Inputs!$C$72=2,P41*P42,O44*(1+Drivers!P62)) -> 207.99455 | Q44: =IF(Inputs!$C$72=2,Q41*Q42,P44*(1+Drivers!Q62)) -> 217.19225 | R44: =IF(Inputs!$C$72=2,R41*R42,Q44*(1+Drivers!R62)) -> 224.59553 | S44: =IF(Inputs!$C$72=2,S41*S42,R44*(1+Drivers!S62)) -> 230.36292
B45: Volume growth | C45: % | F45: =F44/E44-1 -> -0.06779661 | G45: =G44/F44-1 -> 0.063636364 | H45: =H44/G44-1 -> 0.12820513 | I45: =I44/H44-1 -> 0.083333333 | J45: =J44/I44-1 -> 0.048951049 | K45: =K44/J44-1 -> 0.053333333 | L45: =L44/K44-1 -> 0.038168478 | M45: =M44/L44-1 -> 0.062490967 | ... S45: =S44/R44-1 -> 0.025679012
B46: Revenue per unit | C46: NOK '000 | E46: =IF(E44=0,0,E48/E44) -> 5.0847458 | F46: =IF(F44=0,0,F48/F44) -> 4.9818182 | G46: =IF(G44=0,0,G48/G44) -> 5.1111111 | H46: =IF(H44=0,0,H48/H44) -> 5.3939394 | I46: =IF(I44=0,0,I48/I44) -> 5.6083916 | J46: =IF(J44=0,0,J48/J44) -> 5.8333333 | K46: =IF(K44=0,0,K48/K44) -> 6.0632911 | L46: =IF(L44=0,0,L48/L44) -> 6.2451899 | ... S46: =IF(S44=0,0,S48/S44) -> 7.4234693
B47: Price/mix growth | C47: % | F47: =(1+F49)/(1+F45)-1 -> -0.020242424 | G47: =(1+G49)/(1+G45)-1 -> 0.02595296 | H47: =(1+H49)/(1+H45)-1 -> 0.055335968 | I47: =(1+I49)/(1+I45)-1 -> 0.039757995 | J47: =(1+J49)/(1+J45)-1 -> 0.040108063 | K47: =(1+K49)/(1+K45)-1 -> 0.039421338 | L47: =(1+L49)/(1+L45)-1 -> 0.03 | M47: =(1+M49)/(1+M45)-1 -> 0.028 | ... S47: =(1+S49)/(1+S45)-1 -> 0.022
B48: Revenue | C48: NOKm | E48: =Hist!E11 -> 600 | F48: =Hist!F11 -> 548 | G48: =Hist!G11 -> 598 | H48: =Hist!H11 -> 712 | I48: =Hist!I11 -> 802 | J48: =Hist!J11 -> 875 | K48: =Hist!K11 -> 958 | L48: =IF(K44=0,K48*(1+Drivers!L62),K48*L44/K44)*(1+Drivers!L63) -> 1024.4024 | M48: =IF(L44=0,L48*(1+Drivers!M62),L48*M44/L44)*(1+Drivers!M63) -> 1118.894 | N48: =IF(M44=0,M48*(1+Drivers!N62),M48*N44/M44)*(1+Drivers!N63) -> 1230.1194 | O48: =IF(N44=0,N48*(1+Drivers!O62),N48*O44/N44)*(1+Drivers!O63) -> 1339.4986 | P48: =IF(O44=0,O48*(1+Drivers!P62),O48*P44/O44)*(1+Drivers!P63) -> 1442.2229 | Q48: =IF(P44=0,P48*(1+Drivers!Q62),P48*Q44/P44)*(1+Drivers!Q63) -> 1542.1432 | R48: =IF(Q44=0,Q48*(1+Drivers!R62),Q48*R44/Q44)*(1+Drivers!R63) -> 1631.3875 | S48: =IF(R44=0,R48*(1+Drivers!S62),R48*S44/R44)*(1+Drivers!S63) -> 1710.092
B49: Revenue growth | C49: % | F49: =F48/E48-1 -> -0.086666667 | G49: =G48/F48-1 -> 0.091240876 | H49: =H48/G48-1 -> 0.19063545 | I49: =I48/H48-1 -> 0.12640449 | J49: =J48/I48-1 -> 0.091022444 | K49: =K48/J48-1 -> 0.094857143 | L49: =L48/K48-1 -> 0.069313533 | M49: =M48/L48-1 -> 0.092240714 | ... S49: =S48/R48-1 -> 0.048243951
B51: Group – locations
B52: Locations (end of year) | C52: # | E52: =E10+E24+E38 -> 182 | F52: =F10+F24+F38 -> 184 | G52: =G10+G24+G38 -> 188 | H52: =H10+H24+H38 -> 201 | I52: =I10+I24+I38 -> 206 | J52: =J10+J24+J38 -> 211 | K52: =K10+K24+K38 -> 217 | L52: =L10+L24+L38 -> 224 | ... S52: =S10+S24+S38 -> 259
B53: Openings still ramping up | C53: # | E53: =0 -> 0 | F53: =0 -> 0 | G53: =0 -> 0 | H53: =0 -> 0 | I53: =0 -> 0 | J53: =0 -> 0 | K53: =0 -> 0 | L53: =L12+L26+L40 -> 7 | M53: =M12+M26+M40 -> 7 | N53: =N12+N26+N40 -> 7 | O53: =O12+O26+O40 -> 6 | P53: =P12+P26+P40 -> 5 | Q53: =Q12+Q26+Q40 -> 4 | R53: =R12+R26+R40 -> 3 | S53: =S12+S26+S40 -> 3
B54: Average number of locations | C54: # | F54: =AVERAGE(E52,F52) -> 183 | G54: =AVERAGE(F52,G52) -> 186 | H54: =AVERAGE(G52,H52) -> 194.5 | I54: =AVERAGE(H52,I52) -> 203.5 | J54: =AVERAGE(I52,J52) -> 208.5 | K54: =AVERAGE(J52,K52) -> 214 | L54: =AVERAGE(K52,L52) -> 220.5 | M54: =AVERAGE(L52,M52) -> 227.5 | ... S54: =AVERAGE(R52,S52) -> 257.5
B55: Growth in the average number of locations | C55: % | G55: =G54/F54-1 -> 0.016393443 | H55: =H54/G54-1 -> 0.045698925 | I55: =I54/H54-1 -> 0.046272494 | J55: =J54/I54-1 -> 0.024570025 | K55: =K54/J54-1 -> 0.026378897 | L55: =L54/K54-1 -> 0.030373832 | M55: =M54/L54-1 -> 0.031746032 | N55: =N54/M54-1 -> 0.030769231 | ... S55: =S54/R54-1 -> 0.011787819 | V55: Location mode: drives fixed costs (Drivers C) and rent per location (section 2)
B56: Revenue per average location | C56: NOKm | F56: =IF(F54=0,0,F58/F54) -> 18.95082 | G56: =IF(G54=0,0,G58/G54) -> 19.72043 | H56: =IF(H54=0,0,H58/H54) -> 21.912596 | I56: =IF(I54=0,0,I58/I54) -> 23.031941 | J56: =IF(J54=0,0,J58/J54) -> 24.196643 | K56: =IF(K54=0,0,K58/K54) -> 25.38785 | L56: =IF(L54=0,0,L58/L54) -> 25.970286 | M56: =IF(M54=0,0,M58/M54) -> 26.742166 | ... S56: =IF(S54=0,0,S58/S54) -> 32.016212
B58: Total revenue | C58: NOKm | E58: =E20+E34+E48 -> 3790 | F58: =F20+F34+F48 -> 3468 | G58: =G20+G34+G48 -> 3668 | H58: =H20+H34+H48 -> 4262 | I58: =I20+I34+I48 -> 4687 | J58: =J20+J34+J48 -> 5045 | K58: =K20+K34+K48 -> 5433 | L58: =L20+L34+L48 -> 5726.448 | ... S58: =S20+S34+S48 -> 8244.1745
B59: Revenue growth | C59: % | F59: =F58/E58-1 -> -0.084960422 | G59: =G58/F58-1 -> 0.057670127 | H59: =H58/G58-1 -> 0.16194111 | I59: =I58/H58-1 -> 0.099718442 | J59: =J58/I58-1 -> 0.076381481 | K59: =K58/J58-1 -> 0.07690783 | L59: =L58/K58-1 -> 0.05401214 | M59: =M58/L58-1 -> 0.062411248 | ... S59: =S58/R58-1 -> 0.038463123
B60: – of which volume | C60: % | F60: =(E20*F17+E34*F31+E48*F45)/E58 -> -0.066278499 | G60: =(F20*G17+F34*G31+F48*G45)/F58 -> 0.035508911 | H60: =(G20*H17+G34*H31+G48*H45)/G58 -> 0.11026525 | I60: =(H20*I17+H34*I31+H48*I45)/H58 -> 0.050633246 | J60: =(I20*J17+I34*J31+I48*J45)/I58 -> 0.030697769 | K60: =(J20*K17+J34*K31+J48*K45)/J58 -> 0.032636412 | L60: =(K20*L17+K34*L31+K48*L45)/K58 -> 0.020709943 | M60: =(L20*M17+L34*M31+L48*M45)/L58 -> 0.031836296 | ... S60: =(R20*S17+R34*S31+R48*S45)/R58 -> 0.016108731
B61: of which new locations (capacity) | C61: % | F61: =(IF(E10=0,0,E20*(F10/E10-1))+IF(E24=0,0,E34*(F24/E24-1))+IF(E38=0,0,E48*(F38/E38-1)))/E58 -> 0.011085958 | G61: =(IF(F10=0,0,F20*(G10/F10-1))+IF(F24=0,0,F34*(G24/F24-1))+IF(F38=0,0,F48*(G38/F38-1)))/F58 -> 0.022097561 | H61: =(IF(G10=0,0,G20*(H10/G10-1))+IF(G24=0,0,G34*(H24/G24-1))+IF(G38=0,0,G48*(H38/G38-1)))/G58 -> 0.066576179 | I61: =(IF(H10=0,0,H20*(I10/H10-1))+IF(H24=0,0,H34*(I24/H24-1))+IF(H38=0,0,H48*(I38/H38-1)))/H58 -> 0.023084933 | J61: =(IF(I10=0,0,I20*(J10/I10-1))+IF(I24=0,0,I34*(J24/I24-1))+IF(I38=0,0,I48*(J38/I38-1)))/I58 -> 0.02376248 | K61: =(IF(J10=0,0,J20*(K10/J10-1))+IF(J24=0,0,J34*(K24/J24-1))+IF(J38=0,0,J48*(K38/J38-1)))/J58 -> 0.028595251 | L61: =IF(Inputs!$C$72=2,(IF(K13=0,0,K20*(L13/K13-1))+IF(K27=0,0,K34*(L27/K27-1))+IF(K41=0,0,K48*(L41/K41-1)))/K58,0) -> 0.0106988 | M61: =IF(Inputs!$C$72=2,(IF(L13=0,0,L20*(M13/L13-1))+IF(L27=0,0,L34*(M27/L27-1))+IF(L41=0,0,L48*(M41/L41-1)))/L58,0) -> 0.022696934 | N61: =IF(Inputs!$C$72=2,(IF(M13=0,0,M20*(N13/M13-1))+IF(M27=0,0,M34*(N27/M27-1))+IF(M41=0,0,M48*(N41/M41-1)))/M58,0) -> 0.028135889 | O61: =IF(Inputs!$C$72=2,(IF(N13=0,0,N20*(O13/N13-1))+IF(N27=0,0,N34*(O27/N27-1))+IF(N41=0,0,N48*(O41/N41-1)))/N58,0) -> 0.027556368 | P61: =IF(Inputs!$C$72=2,(IF(O13=0,0,O20*(P13/O13-1))+IF(O27=0,0,O34*(P27/O27-1))+IF(O41=0,0,O48*(P41/O41-1)))/O58,0) -> 0.024045893 | Q61: =IF(Inputs!$C$72=2,(IF(P13=0,0,P20*(Q13/P13-1))+IF(P27=0,0,P34*(Q27/P27-1))+IF(P41=0,0,P48*(Q41/P41-1)))/P58,0) -> 0.019632795 | R61: =IF(Inputs!$C$72=2,(IF(Q13=0,0,Q20*(R13/Q13-1))+IF(Q27=0,0,Q34*(R27/Q27-1))+IF(Q41=0,0,Q48*(R41/Q41-1)))/Q58,0) -> 0.015314842 | S61: =IF(Inputs!$C$72=2,(IF(R13=0,0,R20*(S13/R13-1))+IF(R27=0,0,R34*(S27/R27-1))+IF(R41=0,0,R48*(S41/R41-1)))/R58,0) -> 0.01265133 | V61: History: growth in locations (incl. acquired). Forecast: growth in mature-equivalent locations (location mode)
B62: of which like-for-like volume | C62: % | F62: =F60-F61 -> -0.077364457 | G62: =G60-G61 -> 0.01341135 | H62: =H60-H61 -> 0.043689067 | I62: =I60-I61 -> 0.027548314 | J62: =J60-J61 -> 0.0069352889 | K62: =K60-K61 -> 0.0040411609 | L62: =L60-L61 -> 0.010011143 | M62: =M60-M61 -> 0.0091393618 | ... S62: =S60-S61 -> 0.0034574003
B63: – of which price/mix | C63: % | F63: =F59-F60 -> -0.018681923 | G63: =G59-G60 -> 0.022161216 | H63: =H59-H60 -> 0.051675866 | I63: =I59-I60 -> 0.049085196 | J63: =J59-J60 -> 0.045683711 | K63: =K59-K60 -> 0.044271418 | L63: =L59-L60 -> 0.033302198 | M63: =M59-M60 -> 0.030574952 | ... S63: =S59-S60 -> 0.022354392
B65: 2. Earnings build – from revenue to net profit
B67: Total revenue | C67: NOKm | E67: =E58 -> 3790 | F67: =F58 -> 3468 | G67: =G58 -> 3668 | H67: =H58 -> 4262 | I67: =I58 -> 4687 | J67: =J58 -> 5045 | K67: =K58 -> 5433 | L67: =L58 -> 5726.448 | ... S67: =S58 -> 8244.1745
B68: Cost of goods sold | C68: NOKm | E68: =Hist!E13 -> -1383.3 | F68: =Hist!F13 -> -1310.9 | G68: =Hist!G13 -> -1364.5 | H68: =Hist!H13 -> -1623.8 | I68: =Hist!I13 -> -1762.3 | J68: =Hist!J13 -> -1866.7 | K68: =Hist!K13 -> -1988.5 | L68: =-L67*Drivers!L70 -> -2095.88 | M68: =-M67*Drivers!M70 -> -2226.6864 | N68: =-N67*Drivers!N70 -> -2371.3243 | O68: =-O67*Drivers!O70 -> -2516.5739 | P68: =-P67*Drivers!P70 -> -2656.4057 | Q68: =-Q67*Drivers!Q70 -> -2786.4713 | R68: =-R67*Drivers!R70 -> -2905.6091 | S68: =-S67*Drivers!S70 -> -3017.3679
B69: Gross profit | C69: NOKm | E69: =E67+E68 -> 2406.7 | F69: =F67+F68 -> 2157.1 | G69: =G67+G68 -> 2303.5 | H69: =H67+H68 -> 2638.2 | I69: =I67+I68 -> 2924.7 | J69: =J67+J68 -> 3178.3 | K69: =K67+K68 -> 3444.5 | L69: =L67+L68 -> 3630.568 | ... S69: =S67+S68 -> 5226.8066
B70: Gross margin | C70: % | E70: =E69/E67 -> 0.63501319 | F70: =F69/F67 -> 0.62200115 | G70: =G69/G67 -> 0.62799891 | H70: =H69/H67 -> 0.61900516 | I70: =I69/I67 -> 0.62400256 | J70: =J69/J67 -> 0.62999009 | K70: =K69/K67 -> 0.63399595 | L70: =L69/L67 -> 0.634 | ... S70: =S69/S67 -> 0.634
B72: Personnel expenses – fixed part | C72: NOKm | E72: =E74*Drivers!$H$100 -> -523.02 | F72: =F74*Drivers!$H$100 -> -511.86 | G72: =G74*Drivers!$H$100 -> -523.8 | H72: =H74*Drivers!$H$100 -> -585.6 | I72: =I74*Drivers!$H$100 -> -629.94 | J72: =J74*Drivers!$H$100 -> -668.94 | K72: =K74*Drivers!$H$100 -> -710.64 | L72: =K72*(1+Drivers!L73)*(1+Drivers!L74) -> -748.6335 | M72: =L72*(1+Drivers!M73)*(1+Drivers!M74) -> -787.15248 | N72: =M72*(1+Drivers!N73)*(1+Drivers!N74) -> -825.45048 | O72: =N72*(1+Drivers!O73)*(1+Drivers!O74) -> -863.67596 | P72: =O72*(1+Drivers!P73)*(1+Drivers!P74) -> -900.42027 | Q72: =P72*(1+Drivers!Q73)*(1+Drivers!Q74) -> -935.56725 | R72: =Q72*(1+Drivers!R73)*(1+Drivers!R74) -> -968.98536 | S72: =R72*(1+Drivers!S73)*(1+Drivers!S74) -> -1001.9908 | V72: History: total x fixed share (Drivers E). Forecast: grows with cost inflation and capacity (Drivers C) – not with revenue
B73: Personnel expenses – variable part | C73: NOKm | E73: =E74-E72 -> -348.68 | F73: =F74-F72 -> -341.24 | G73: =G74-G72 -> -349.2 | H73: =H74-H72 -> -390.4 | I73: =I74-I72 -> -419.96 | J73: =J74-J72 -> -445.96 | K73: =K74-K72 -> -473.76 | L73: =-L67*Drivers!L71 -> -499.34626 | M73: =-M67*Drivers!M71 -> -530.51109 | N73: =-N67*Drivers!N71 -> -564.97126 | O73: =-O67*Drivers!O71 -> -599.57718 | P73: =-P67*Drivers!P71 -> -632.89229 | Q73: =-Q67*Drivers!Q71 -> -663.88058 | R73: =-R67*Drivers!R71 -> -692.26533 | S73: =-S67*Drivers!S71 -> -718.89202 | V73: Scales with revenue (Drivers A)
B74: Personnel expenses | C74: NOKm | E74: =Hist!E15 -> -871.7 | F74: =Hist!F15 -> -853.1 | G74: =Hist!G15 -> -873 | H74: =Hist!H15 -> -976 | I74: =Hist!I15 -> -1049.9 | J74: =Hist!J15 -> -1114.9 | K74: =Hist!K15 -> -1184.4 | L74: =L72+L73 -> -1247.9798 | M74: =M72+M73 -> -1317.6636 | N74: =N72+N73 -> -1390.4217 | O74: =O72+O73 -> -1463.2531 | P74: =P72+P73 -> -1533.3126 | Q74: =Q72+Q73 -> -1599.4478 | R74: =R72+R73 -> -1661.2507 | S74: =S72+S73 -> -1720.8828
B75: Other opex – fixed part | C75: NOKm | E75: =E77*Drivers!$H$101 -> -242.55 | F75: =F77*Drivers!$H$101 -> -234.1 | G75: =G77*Drivers!$H$101 -> -240.25 | H75: =H77*Drivers!$H$101 -> -268.5 | I75: =I77*Drivers!$H$101 -> -288.25 | J75: =J77*Drivers!$H$101 -> -305.2 | K75: =K77*Drivers!$H$101 -> -323.25 | L75: =K75*(1+Drivers!L73)*(1+Drivers!L74) -> -340.53217 | M75: =L75*(1+Drivers!M73)*(1+Drivers!M74) -> -358.05336 | N75: =M75*(1+Drivers!N73)*(1+Drivers!N74) -> -375.47403 | O75: =N75*(1+Drivers!O73)*(1+Drivers!O74) -> -392.86172 | P75: =O75*(1+Drivers!P73)*(1+Drivers!P74) -> -409.57567 | Q75: =P75*(1+Drivers!Q73)*(1+Drivers!Q74) -> -425.56303 | R75: =Q75*(1+Drivers!R73)*(1+Drivers!R74) -> -440.76398 | S75: =R75*(1+Drivers!S73)*(1+Drivers!S74) -> -455.77724
B76: Other opex – variable part | C76: NOKm | E76: =E77-E75 -> -242.55 | F76: =F77-F75 -> -234.1 | G76: =G77-G75 -> -240.25 | H76: =H77-H75 -> -268.5 | I76: =I77-I75 -> -288.25 | J76: =J77-J75 -> -305.2 | K76: =K77-K75 -> -323.25 | L76: =-L67*Drivers!L72 -> -340.72365 | M76: =-M67*Drivers!M72 -> -361.98864 | N76: =-N67*Drivers!N72 -> -385.50218 | O76: =-O67*Drivers!O72 -> -409.11516 | P76: =-P67*Drivers!P72 -> -431.84738 | Q76: =-Q67*Drivers!Q72 -> -452.99191 | R76: =-R67*Drivers!R72 -> -472.35994 | S76: =-S67*Drivers!S72 -> -490.52838
B77: Other operating expenses | C77: NOKm | E77: =Hist!E16 -> -485.1 | F77: =Hist!F16 -> -468.2 | G77: =Hist!G16 -> -480.5 | H77: =Hist!H16 -> -537 | I77: =Hist!I16 -> -576.5 | J77: =Hist!J16 -> -610.4 | K77: =Hist!K16 -> -646.5 | L77: =L75+L76 -> -681.25582 | M77: =M75+M76 -> -720.042 | N77: =N75+N76 -> -760.97621 | O77: =O75+O76 -> -801.97688 | P77: =P75+P76 -> -841.42304 | Q77: =Q75+Q76 -> -878.55495 | R77: =R75+R76 -> -913.12393 | S77: =S75+S76 -> -946.30562 | V77: Operating leverage is a result, not an input: fixed costs grow slower than revenue
B78: EBITDA (reported, IFRS 16) | C78: NOKm | E78: =E69+E74+E77 -> 1049.9 | F78: =F69+F74+F77 -> 835.8 | G78: =G69+G74+G77 -> 950 | H78: =H69+H74+H77 -> 1125.2 | I78: =I69+I74+I77 -> 1298.3 | J78: =J69+J74+J77 -> 1453 | K78: =K69+K74+K77 -> 1613.6 | L78: =L69+L74+L77 -> 1701.3324 | ... S78: =S69+S74+S77 -> 2559.6182
B79: EBITDA margin | C79: % | E79: =E78/E67 -> 0.27701847 | F79: =F78/F67 -> 0.24100346 | G79: =G78/G67 -> 0.25899673 | H79: =H78/H67 -> 0.26400751 | I79: =I78/I67 -> 0.27700021 | J79: =J78/J67 -> 0.28800793 | K79: =K78/K67 -> 0.29699982 | L79: =L78/L67 -> 0.29710083 | ... S79: =S78/S67 -> 0.31047598
B81: Lease payments (IFRS 16 adjustment) | C81: NOKm | E81: =Hist!E32 -> -318.4 | F81: =Hist!F32 -> -322.5 | G81: =Hist!G32 -> -326.5 | H81: =Hist!H32 -> -349.5 | I81: =Hist!I32 -> -375 | J81: =Hist!J32 -> -398.6 | K81: =Hist!K32 -> -423.8 | L81: =IF(Inputs!$C$72=2,K81*(1+Drivers!L73)*(1+L55),-L67*Drivers!L75) -> -449.7726 | M81: =IF(Inputs!$C$72=2,L81*(1+Drivers!M73)*(1+M55),-M67*Drivers!M75) -> -476.58048 | N81: =IF(Inputs!$C$72=2,M81*(1+Drivers!N73)*(1+N55),-N67*Drivers!N75) -> -503.5256 | O81: =IF(Inputs!$C$72=2,N81*(1+Drivers!O73)*(1+O55),-O67*Drivers!O75) -> -530.41967 | P81: =IF(Inputs!$C$72=2,O81*(1+Drivers!P73)*(1+P55),-P67*Drivers!P75) -> -556.0878 | Q81: =IF(Inputs!$C$72=2,P81*(1+Drivers!Q73)*(1+Q55),-Q67*Drivers!Q75) -> -580.39549 | R81: =IF(Inputs!$C$72=2,Q81*(1+Drivers!R73)*(1+R55),-R67*Drivers!R75) -> -603.20087 | S81: =IF(Inputs!$C$72=2,R81*(1+Drivers!S73)*(1+S55),-S67*Drivers!S75) -> -625.56908 | V81: Rent. Location mode: rent per location grows with cost inflation; segment mode: % of revenue. An operating cost in the DCF
B82: EBITDAaL (pre-IFRS 16) | C82: NOKm | E82: =E78+E81 -> 731.5 | F82: =F78+F81 -> 513.3 | G82: =G78+G81 -> 623.5 | H82: =H78+H81 -> 775.7 | I82: =I78+I81 -> 923.3 | J82: =J78+J81 -> 1054.4 | K82: =K78+K81 -> 1189.8 | L82: =L78+L81 -> 1251.5598 | ... S82: =S78+S81 -> 1934.0491
B83: EBITDAaL margin | C83: % | E83: =E82/E67 -> 0.19300792 | F83: =F82/F67 -> 0.14801038 | G83: =G82/G67 -> 0.16998364 | H83: =H82/H67 -> 0.18200375 | I83: =I82/I67 -> 0.19699168 | J83: =J82/J67 -> 0.20899901 | K83: =K82/K67 -> 0.21899503 | L83: =L82/L67 -> 0.21855779 | ... S83: =S82/S67 -> 0.23459585
B84: D&A – owned assets | C84: NOKm | E84: =Hist!E18 -> -174.3 | F84: =Hist!F18 -> -176.9 | G84: =Hist!G18 -> -179.7 | H84: =Hist!H18 -> -196.1 | I84: =Hist!I18 -> -210.9 | J84: =Hist!J18 -> -227 | K84: =Hist!K18 -> -239.1 | L84: =-L67*Drivers!L76 -> -251.96371 | M84: =-M67*Drivers!M76 -> -267.68908 | N84: =-N67*Drivers!N76 -> -285.07724 | O84: =-O67*Drivers!O76 -> -302.53894 | P84: =-P67*Drivers!P76 -> -319.34932 | Q84: =-Q67*Drivers!Q76 -> -334.98562 | R84: =-R67*Drivers!R76 -> -349.30819 | S84: =-S67*Drivers!S76 -> -362.74368
B85: EBIT adj. (pre-IFRS 16, excl. special items) | C85: NOKm | E85: =E82+E84 -> 557.2 | F85: =F82+F84 -> 336.4 | G85: =G82+G84 -> 443.8 | H85: =H82+H84 -> 579.6 | I85: =I82+I84 -> 712.4 | J85: =J82+J84 -> 827.4 | K85: =K82+K84 -> 950.7 | L85: =L82+L84 -> 999.5961 | ... S85: =S82+S84 -> 1571.3054 | V85: Basis for NOPAT and FCFF in the DCF
B86: EBIT adj. margin | C86: % | E86: =E85/E67 -> 0.14701847 | F86: =F85/F67 -> 0.097001153 | G86: =G85/G67 -> 0.12099237 | H86: =H85/H67 -> 0.13599249 | I86: =I85/I67 -> 0.15199488 | J86: =J85/J67 -> 0.16400396 | K86: =K85/K67 -> 0.1749862 | L86: =L85/L67 -> 0.17455779 | ... S86: =S85/S67 -> 0.19059585
B88: Reconciliation to reported EBIT (IFRS 16)
B89: Impairments and special items | C89: NOKm | E89: =Hist!E20 -> 0 | F89: =Hist!F20 -> -45 | G89: =Hist!G20 -> 0 | H89: =Hist!H20 -> 0 | I89: =Hist!I20 -> -20 | J89: =Hist!J20 -> 0 | K89: =Hist!K20 -> 0 | L89: 0 | M89: 0 | N89: 0 | O89: 0 | P89: 0 | Q89: 0 | R89: 0 | S89: 0 | V89: Forecast normally zero – enter known one-offs in the yellow cells
B90: Depreciation – right-of-use assets | C90: NOKm | E90: =Hist!E19 -> -254.7 | F90: =Hist!F19 -> -258 | G90: =Hist!G19 -> -261.2 | H90: =Hist!H19 -> -279.6 | I90: =Hist!I19 -> -300 | J90: =Hist!J19 -> -318.9 | K90: =Hist!K19 -> -339 | L90: =L81*(1-Drivers!L85) -> -359.81808 | M90: =M81*(1-Drivers!M85) -> -381.26438 | N90: =N81*(1-Drivers!N85) -> -402.82048 | O90: =O81*(1-Drivers!O85) -> -424.33574 | P90: =P81*(1-Drivers!P85) -> -444.87024 | Q90: =Q81*(1-Drivers!Q85) -> -464.31639 | R90: =R81*(1-Drivers!R85) -> -482.5607 | S90: =S81*(1-Drivers!S85) -> -500.45526
B91: EBIT (reported, IFRS 16) | C91: NOKm | E91: =E78+E84+E90+E89 -> 620.9 | F91: =F78+F84+F90+F89 -> 355.9 | G91: =G78+G84+G90+G89 -> 509.1 | H91: =H78+H84+H90+H89 -> 649.5 | I91: =I78+I84+I90+I89 -> 767.4 | J91: =J78+J84+J90+J89 -> 907.1 | K91: =K78+K84+K90+K89 -> 1035.5 | L91: =L78+L84+L90+L89 -> 1089.5506 | ... S91: =S78+S84+S90+S89 -> 1696.4192
B92: EBIT margin (reported) | C92: % | E92: =E91/E67 -> 0.16382586 | F92: =F91/F67 -> 0.10262399 | G92: =G91/G67 -> 0.13879498 | H92: =H91/H67 -> 0.15239324 | I92: =I91/I67 -> 0.16372946 | J92: =J91/J67 -> 0.17980178 | K92: =K91/K67 -> 0.19059452 | L92: =L91/L67 -> 0.1902664 | ... S92: =S91/S67 -> 0.20577187
B94: Net financial items excl. leases | C94: NOKm | E94: =Hist!E22 -> -60.3 | F94: =Hist!F22 -> -49.2 | G94: =Hist!G22 -> -44.2 | H94: =Hist!H22 -> -55 | I94: =Hist!I22 -> -84 | J94: =Hist!J22 -> -82.1 | K94: =Hist!K22 -> -80.4 | L94: =-K135*IF(K135>0,Drivers!L83,Drivers!L84) -> -54.373 | M94: =-L135*IF(L135>0,Drivers!M83,Drivers!M84) -> -48.810833 | N94: =-M135*IF(M135>0,Drivers!N83,Drivers!N84) -> -50.357634 | O94: =-N135*IF(N135>0,Drivers!O83,Drivers!O84) -> -54.479262 | P94: =-O135*IF(O135>0,Drivers!P83,Drivers!P84) -> -58.637304 | Q94: =-P135*IF(P135>0,Drivers!Q83,Drivers!Q84) -> -62.651625 | R94: =-Q135*IF(Q135>0,Drivers!R83,Drivers!R84) -> -66.316497 | S94: =-R135*IF(R135>0,Drivers!S83,Drivers!S84) -> -69.586427 | V94: Interest on opening net debt (avoids circularity)
B95: Interest on lease liabilities | C95: NOKm | E95: =Hist!E23 -> -63.7 | F95: =Hist!F23 -> -64.5 | G95: =Hist!G23 -> -65.3 | H95: =Hist!H23 -> -69.9 | I95: =Hist!I23 -> -75 | J95: =Hist!J23 -> -79.7 | K95: =Hist!K23 -> -84.8 | L95: =L81*Drivers!L85 -> -89.954521 | M95: =M81*Drivers!M85 -> -95.316096 | N95: =N81*Drivers!N85 -> -100.70512 | O95: =O81*Drivers!O85 -> -106.08393 | P95: =P81*Drivers!P85 -> -111.21756 | Q95: =Q81*Drivers!Q85 -> -116.0791 | R95: =R81*Drivers!R85 -> -120.64017 | S95: =S81*Drivers!S85 -> -125.11382
B96: Profit before tax | C96: NOKm | E96: =E91+E94+E95 -> 496.9 | F96: =F91+F94+F95 -> 242.2 | G96: =G91+G94+G95 -> 399.6 | H96: =H91+H94+H95 -> 524.6 | I96: =I91+I94+I95 -> 608.4 | J96: =J91+J94+J95 -> 745.3 | K96: =K91+K94+K95 -> 870.3 | L96: =L91+L94+L95 -> 945.2231 | ... S96: =S91+S94+S95 -> 1501.719
B97: Income tax | C97: NOKm | E97: =Hist!E25 -> -114.3 | F97: =Hist!F25 -> -61.3 | G97: =Hist!G25 -> -87.9 | H97: =Hist!H25 -> -115.4 | I97: =Hist!I25 -> -133.8 | J97: =Hist!J25 -> -164 | K97: =Hist!K25 -> -191.5 | L97: =-L96*Drivers!L81 -> -207.94908 | M97: =-M96*Drivers!M81 -> -225.80147 | N97: =-N96*Drivers!N81 -> -245.816 | O97: =-O96*Drivers!O81 -> -265.46151 | P97: =-P96*Drivers!P81 -> -284.39914 | Q97: =-Q96*Drivers!Q81 -> -301.57659 | R97: =-R96*Drivers!R81 -> -316.80294 | S97: =-S96*Drivers!S81 -> -330.37818
B98: Net profit | C98: NOKm | E98: =E96+E97 -> 382.6 | F98: =F96+F97 -> 180.9 | G98: =G96+G97 -> 311.7 | H98: =H96+H97 -> 409.2 | I98: =I96+I97 -> 474.6 | J98: =J96+J97 -> 581.3 | K98: =K96+K97 -> 678.8 | L98: =L96+L97 -> 737.27402 | ... S98: =S96+S97 -> 1171.3408
B99: Minority interests | C99: NOKm | E99: =Hist!E27 -> -3.8 | F99: =Hist!F27 -> -1.8 | G99: =Hist!G27 -> -3.1 | H99: =Hist!H27 -> -4.1 | I99: =Hist!I27 -> -4.7 | J99: =Hist!J27 -> -5.8 | K99: =Hist!K27 -> -6.8 | L99: =-L98*Drivers!L86 -> -7.3727402 | M99: =-M98*Drivers!M86 -> -8.0056886 | N99: =-N98*Drivers!N86 -> -8.7152944 | O99: =-O98*Drivers!O86 -> -9.4118173 | P99: =-P98*Drivers!P86 -> -10.083242 | Q99: =-Q98*Drivers!Q86 -> -10.692261 | R99: =-R98*Drivers!R86 -> -11.232104 | S99: =-S98*Drivers!S86 -> -11.713408
B100: Net profit to shareholders | C100: NOKm | E100: =E98+E99 -> 378.8 | F100: =F98+F99 -> 179.1 | G100: =G98+G99 -> 308.6 | H100: =H98+H99 -> 405.1 | I100: =I98+I99 -> 469.9 | J100: =J98+J99 -> 575.5 | K100: =K98+K99 -> 672 | L100: =L98+L99 -> 729.90128 | ... S100: =S98+S99 -> 1159.6274
B101: Net profit margin | C101: % | E101: =E100/E67 -> 0.09994723 | F101: =F100/F67 -> 0.051643599 | G101: =G100/G67 -> 0.084133043 | H101: =H100/H67 -> 0.095049273 | I101: =I100/I67 -> 0.10025603 | J101: =J100/J67 -> 0.11407334 | K101: =K100/K67 -> 0.12368857 | L101: =L100/L67 -> 0.12746144 | ... S101: =S100/S67 -> 0.14066022
B103: Per share
B104: Diluted shares | C104: m | E104: =Hist!E82 -> 85 | F104: =Hist!F82 -> 85 | G104: =Hist!G82 -> 85 | H104: =Hist!H82 -> 85 | I104: =Hist!I82 -> 85 | J104: =Hist!J82 -> 85 | K104: =Hist!K82 -> 85 | L104: =Inputs!$C$31+L134/L133 -> 85.151424 | M104: =L104+M134/M133 -> 83.583314 | N104: =M104+N134/N133 -> 82.123959 | O104: =N104+O134/O133 -> 80.801072 | P104: =O104+P134/P133 -> 79.668734 | Q104: =P104+Q134/Q133 -> 78.781136 | R104: =Q104+R134/R133 -> 78.145256 | S104: =R104+S134/S133 -> 77.607416 | V104: Reduced by buybacks (section 4)
B105: EPS | C105: NOK | E105: =E100/E104 -> 4.4564706 | F105: =F100/F104 -> 2.1070588 | G105: =G100/G104 -> 3.6305882 | H105: =H100/H104 -> 4.7658824 | I105: =I100/I104 -> 5.5282353 | J105: =J100/J104 -> 6.7705882 | K105: =K100/K104 -> 7.9058824 | L105: =L100/L104 -> 8.5718035 | ... S105: =S100/S104 -> 14.942224
B106: EPS growth | C106: % | F106: =IF(E105<=0,"n.m.",F105/E105-1) -> -0.52719113 | G106: =IF(F105<=0,"n.m.",G105/F105-1) -> 0.72305974 | H106: =IF(G105<=0,"n.m.",H105/G105-1) -> 0.31270253 | I106: =IF(H105<=0,"n.m.",I105/H105-1) -> 0.1599605 | J106: =IF(I105<=0,"n.m.",J105/I105-1) -> 0.22472867 | K106: =IF(J105<=0,"n.m.",K105/J105-1) -> 0.16768028 | L106: =IF(K105<=0,"n.m.",L105/K105-1) -> 0.084231102 | M106: =IF(L105<=0,"n.m.",M105/L105-1) -> 0.10622149 | ... S106: =IF(R105<=0,"n.m.",S105/R105-1) -> 0.050077974
B107: DPS | C107: NOK | E107: =Hist!E83 -> 0 | F107: =Hist!F83 -> 0 | G107: =Hist!G83 -> 2.5 | H107: =Hist!H83 -> 3.5 | I107: =Hist!I83 -> 4.2 | J107: =Hist!J83 -> 4.8 | K107: =Hist!K83 -> 5.4 | L107: =MAX(0,L105*Drivers!L82) -> 5.5716723 | M107: =MAX(0,M105*Drivers!M82) -> 6.6376193 | N107: =MAX(0,N105*Drivers!N82) -> 7.8796811 | O107: =MAX(0,O105*Drivers!O82) -> 9.2253222 | P107: =MAX(0,P105*Drivers!P82) -> 10.650412 | Q107: =MAX(0,Q105*Drivers!Q82) -> 12.092748 | R107: =MAX(0,R105*Drivers!R82) -> 12.80667 | S107: =MAX(0,S105*Drivers!S82) -> 13.448002
B108: Payout ratio | C108: % | E108: =IF(E105<=0,0,E107/E105) -> 0 | F108: =IF(F105<=0,0,F107/F105) -> 0 | G108: =IF(G105<=0,0,G107/G105) -> 0.68859365 | H108: =IF(H105<=0,0,H107/H105) -> 0.73438657 | I108: =IF(I105<=0,0,I107/I105) -> 0.75973611 | J108: =IF(J105<=0,0,J107/J105) -> 0.70894874 | K108: =IF(K105<=0,0,K107/K105) -> 0.68303571 | L108: =IF(L105<=0,0,L107/L105) -> 0.65 | ... S108: =IF(S105<=0,0,S107/S105) -> 0.9
B110: 3. Investments, working capital and free cash flow
B112: Net working capital | C112: NOKm | E112: =Hist!E123 -> -227.4 | F112: =Hist!F123 -> -180.3 | G112: =Hist!G123 -> -205.4 | H112: =Hist!H123 -> -260 | I112: =Hist!I123 -> -295.3 | J112: =Hist!J123 -> -322.9 | K112: =Hist!K123 -> -353.1 | L112: =L67*Drivers!L80 -> -372.21912 | M112: =M67*Drivers!M80 -> -395.44978 | N112: =N67*Drivers!N80 -> -421.13683 | O112: =O67*Drivers!O80 -> -446.93253 | P112: =P67*Drivers!P80 -> -471.76604 | Q112: =Q67*Drivers!Q80 -> -494.86511 | R112: =R67*Drivers!R80 -> -516.02347 | S112: =S67*Drivers!S80 -> -535.87134
B113: Change in NWC (increase = cash outflow) | C113: NOKm | F113: =F112-E112 -> 47.1 | G113: =G112-F112 -> -25.1 | H113: =H112-G112 -> -54.6 | I113: =I112-H112 -> -35.3 | J113: =J112-I112 -> -27.6 | K113: =K112-J112 -> -30.2 | L113: =L112-K112 -> -19.119117 | M113: =M112-L112 -> -23.230659 | ... S113: =S112-R112 -> -19.847874
B114: Maintenance capex | C114: NOKm | L114: =-L67*Drivers!L77 -> -286.3224 | M114: =-M67*Drivers!M77 -> -304.19214 | N114: =-N67*Drivers!N77 -> -323.95141 | O114: =-O67*Drivers!O77 -> -343.79425 | P114: =-P67*Drivers!P77 -> -362.89696 | Q114: =-Q67*Drivers!Q77 -> -380.66547 | R114: =-R67*Drivers!R77 -> -396.94113 | S114: =-S67*Drivers!S77 -> -412.20873 | V114: ≈ D&A – keeps the existing asset base intact (Drivers A)
B115: Growth capex | C115: NOKm | L115: =IF(Inputs!$C$72=2,-L53*Drivers!L79,-MAX(0,L67-K67)/Drivers!L78) -> -154 | M115: =IF(Inputs!$C$72=2,-M53*Drivers!M79,-MAX(0,M67-L67)/Drivers!M78) -> -158.2 | N115: =IF(Inputs!$C$72=2,-N53*Drivers!N79,-MAX(0,N67-M67)/Drivers!N78) -> -161.7 | O115: =IF(Inputs!$C$72=2,-O53*Drivers!O79,-MAX(0,O67-N67)/Drivers!O78) -> -142.2 | P115: =IF(Inputs!$C$72=2,-P53*Drivers!P79,-MAX(0,P67-O67)/Drivers!P78) -> -121.5 | Q115: =IF(Inputs!$C$72=2,-Q53*Drivers!Q79,-MAX(0,Q67-P67)/Drivers!Q78) -> -99.6 | R115: =IF(Inputs!$C$72=2,-R53*Drivers!R79,-MAX(0,R67-Q67)/Drivers!R78) -> -76.5 | S115: =IF(Inputs!$C$72=2,-S53*Drivers!S79,-MAX(0,S67-R67)/Drivers!S78) -> -78.3 | V115: Location mode: openings x capex per new location. Segment mode: incremental revenue / sales-to-capital
...

Sheet Output >>>
D8: =Inputs!$C$6 -> Example Company ASA
D9: Financial Model
D12: Output
D14: Link-only presentation of the results – what you would show in a report.
D17: Output | E17: Financial statements | F17: Income statement, balance sheet (capital employed) and cash flow with integrity checks
D18: Analysis | E18: Financial analysis | F18: Growth, margins, ROIC vs. WACC, leverage, per-share data and valuation multiples
D21: ← Back to cover

Sheet Output
B1: Output Financial Statements | T1: =Inputs!$C$6&" | Scenario: "&Inputs!$C$53 -> Example Company ASA | Scenario: Base
B2: Link-only presentation of the income statement, balance sheet and cash flow – no assumptions are entered here.
E3: =Inputs!$C$17+0 -> 2019 | F3: =Inputs!$C$17+1 -> 2020 | G3: =Inputs!$C$17+2 -> 2021 | H3: =Inputs!$C$17+3 -> 2022 | I3: =Inputs!$C$17+4 -> 2023 | J3: =Inputs!$C$17+5 -> 2024 | K3: =Inputs!$C$17+6 -> 2025 | L3: =Inputs!$C$19+0 -> 2026 | M3: =Inputs!$C$19+1 -> 2027 | N3: =Inputs!$C$19+2 -> 2028 | O3: =Inputs!$C$19+3 -> 2029 | P3: =Inputs!$C$19+4 -> 2030 | Q3: =Inputs!$C$19+5 -> 2031 | R3: =Inputs!$C$19+6 -> 2032 | S3: =Inputs!$C$19+7 -> 2033
E4: Historicals | L4: Explicit forecast
B5: ="("&Inputs!$C$11&")" -> (NOKm) | E5: =E3&"A" -> 2019A | F5: =F3&"A" -> 2020A | G5: =G3&"A" -> 2021A | H5: =H3&"A" -> 2022A | I5: =I3&"A" -> 2023A | J5: =J3&"A" -> 2024A | K5: =K3&"A" -> 2025A | L5: =L3&"E" -> 2026E | M5: =M3&"E" -> 2027E | N5: =N3&"E" -> 2028E | O5: =O3&"E" -> 2029E | P5: =P3&"E" -> 2030E | Q5: =Q3&"E" -> 2031E | R5: =R3&"E" -> 2032E | S5: =S3&"E" -> 2033E | V5: Notes
B7: Income statement
B9: Revenue | C9: NOKm | E9: =Model!E67 -> 3790 | F9: =Model!F67 -> 3468 | G9: =Model!G67 -> 3668 | H9: =Model!H67 -> 4262 | I9: =Model!I67 -> 4687 | J9: =Model!J67 -> 5045 | K9: =Model!K67 -> 5433 | L9: =Model!L67 -> 5726.448 | ... S9: =Model!S67 -> 8244.1745
B10: Growth | C10: % | F10: =F9/E9-1 -> -0.084960422 | G10: =G9/F9-1 -> 0.057670127 | H10: =H9/G9-1 -> 0.16194111 | I10: =I9/H9-1 -> 0.099718442 | J10: =J9/I9-1 -> 0.076381481 | K10: =K9/J9-1 -> 0.07690783 | L10: =L9/K9-1 -> 0.05401214 | M10: =M9/L9-1 -> 0.062411248 | ... S10: =S9/R9-1 -> 0.038463123
B12: Cost of goods sold | C12: NOKm | E12: =Model!E68 -> -1383.3 | F12: =Model!F68 -> -1310.9 | G12: =Model!G68 -> -1364.5 | H12: =Model!H68 -> -1623.8 | I12: =Model!I68 -> -1762.3 | J12: =Model!J68 -> -1866.7 | K12: =Model!K68 -> -1988.5 | L12: =Model!L68 -> -2095.88 | ... S12: =Model!S68 -> -3017.3679
B13: Gross profit | C13: NOKm | E13: =Model!E69 -> 2406.7 | F13: =Model!F69 -> 2157.1 | G13: =Model!G69 -> 2303.5 | H13: =Model!H69 -> 2638.2 | I13: =Model!I69 -> 2924.7 | J13: =Model!J69 -> 3178.3 | K13: =Model!K69 -> 3444.5 | L13: =Model!L69 -> 3630.568 | ... S13: =Model!S69 -> 5226.8066
B14: Margin | C14: % | E14: =E13/E9 -> 0.63501319 | F14: =F13/F9 -> 0.62200115 | G14: =G13/G9 -> 0.62799891 | H14: =H13/H9 -> 0.61900516 | I14: =I13/I9 -> 0.62400256 | J14: =J13/J9 -> 0.62999009 | K14: =K13/K9 -> 0.63399595 | L14: =L13/L9 -> 0.634 | ... S14: =S13/S9 -> 0.634
B16: Personnel expenses | C16: NOKm | E16: =Model!E74 -> -871.7 | F16: =Model!F74 -> -853.1 | G16: =Model!G74 -> -873 | H16: =Model!H74 -> -976 | I16: =Model!I74 -> -1049.9 | J16: =Model!J74 -> -1114.9 | K16: =Model!K74 -> -1184.4 | L16: =Model!L74 -> -1247.9798 | ... S16: =Model!S74 -> -1720.8828
B17: Other operating expenses | C17: NOKm | E17: =Model!E77 -> -485.1 | F17: =Model!F77 -> -468.2 | G17: =Model!G77 -> -480.5 | H17: =Model!H77 -> -537 | I17: =Model!I77 -> -576.5 | J17: =Model!J77 -> -610.4 | K17: =Model!K77 -> -646.5 | L17: =Model!L77 -> -681.25582 | ... S17: =Model!S77 -> -946.30562
B18: EBITDA | C18: NOKm | E18: =Model!E78 -> 1049.9 | F18: =Model!F78 -> 835.8 | G18: =Model!G78 -> 950 | H18: =Model!H78 -> 1125.2 | I18: =Model!I78 -> 1298.3 | J18: =Model!J78 -> 1453 | K18: =Model!K78 -> 1613.6 | L18: =Model!L78 -> 1701.3324 | ... S18: =Model!S78 -> 2559.6182
B19: Margin | C19: % | E19: =E18/E9 -> 0.27701847 | F19: =F18/F9 -> 0.24100346 | G19: =G18/G9 -> 0.25899673 | H19: =H18/H9 -> 0.26400751 | I19: =I18/I9 -> 0.27700021 | J19: =J18/J9 -> 0.28800793 | K19: =K18/K9 -> 0.29699982 | L19: =L18/L9 -> 0.29710083 | ... S19: =S18/S9 -> 0.31047598
B21: D&A – owned assets | C21: NOKm | E21: =Model!E84 -> -174.3 | F21: =Model!F84 -> -176.9 | G21: =Model!G84 -> -179.7 | H21: =Model!H84 -> -196.1 | I21: =Model!I84 -> -210.9 | J21: =Model!J84 -> -227 | K21: =Model!K84 -> -239.1 | L21: =Model!L84 -> -251.96371 | ... S21: =Model!S84 -> -362.74368
B22: Depreciation – right-of-use assets | C22: NOKm | E22: =Model!E90 -> -254.7 | F22: =Model!F90 -> -258 | G22: =Model!G90 -> -261.2 | H22: =Model!H90 -> -279.6 | I22: =Model!I90 -> -300 | J22: =Model!J90 -> -318.9 | K22: =Model!K90 -> -339 | L22: =Model!L90 -> -359.81808 | ... S22: =Model!S90 -> -500.45526
B23: Impairments and special items | C23: NOKm | E23: =Model!E89 -> 0 | F23: =Model!F89 -> -45 | G23: =Model!G89 -> 0 | H23: =Model!H89 -> 0 | I23: =Model!I89 -> -20 | J23: =Model!J89 -> 0 | K23: =Model!K89 -> 0 | L23: =Model!L89 -> 0 | ... S23: =Model!S89 -> 0
B24: EBIT | C24: NOKm | E24: =Model!E91 -> 620.9 | F24: =Model!F91 -> 355.9 | G24: =Model!G91 -> 509.1 | H24: =Model!H91 -> 649.5 | I24: =Model!I91 -> 767.4 | J24: =Model!J91 -> 907.1 | K24: =Model!K91 -> 1035.5 | L24: =Model!L91 -> 1089.5506 | ... S24: =Model!S91 -> 1696.4192
B25: Margin | C25: % | E25: =E24/E9 -> 0.16382586 | F25: =F24/F9 -> 0.10262399 | G25: =G24/G9 -> 0.13879498 | H25: =H24/H9 -> 0.15239324 | I25: =I24/I9 -> 0.16372946 | J25: =J24/J9 -> 0.17980178 | K25: =K24/K9 -> 0.19059452 | L25: =L24/L9 -> 0.1902664 | ... S25: =S24/S9 -> 0.20577187
B27: Net financial items excl. leases | C27: NOKm | E27: =Model!E94 -> -60.3 | F27: =Model!F94 -> -49.2 | G27: =Model!G94 -> -44.2 | H27: =Model!H94 -> -55 | I27: =Model!I94 -> -84 | J27: =Model!J94 -> -82.1 | K27: =Model!K94 -> -80.4 | L27: =Model!L94 -> -54.373 | ... S27: =Model!S94 -> -69.586427
B28: Interest on lease liabilities | C28: NOKm | E28: =Model!E95 -> -63.7 | F28: =Model!F95 -> -64.5 | G28: =Model!G95 -> -65.3 | H28: =Model!H95 -> -69.9 | I28: =Model!I95 -> -75 | J28: =Model!J95 -> -79.7 | K28: =Model!K95 -> -84.8 | L28: =Model!L95 -> -89.954521 | ... S28: =Model!S95 -> -125.11382
B29: Profit before tax | C29: NOKm | E29: =Model!E96 -> 496.9 | F29: =Model!F96 -> 242.2 | G29: =Model!G96 -> 399.6 | H29: =Model!H96 -> 524.6 | I29: =Model!I96 -> 608.4 | J29: =Model!J96 -> 745.3 | K29: =Model!K96 -> 870.3 | L29: =Model!L96 -> 945.2231 | ... S29: =Model!S96 -> 1501.719
B31: Income tax | C31: NOKm | E31: =Model!E97 -> -114.3 | F31: =Model!F97 -> -61.3 | G31: =Model!G97 -> -87.9 | H31: =Model!H97 -> -115.4 | I31: =Model!I97 -> -133.8 | J31: =Model!J97 -> -164 | K31: =Model!K97 -> -191.5 | L31: =Model!L97 -> -207.94908 | ... S31: =Model!S97 -> -330.37818
B32: Net profit | C32: NOKm | E32: =Model!E98 -> 382.6 | F32: =Model!F98 -> 180.9 | G32: =Model!G98 -> 311.7 | H32: =Model!H98 -> 409.2 | I32: =Model!I98 -> 474.6 | J32: =Model!J98 -> 581.3 | K32: =Model!K98 -> 678.8 | L32: =Model!L98 -> 737.27402 | ... S32: =Model!S98 -> 1171.3408
B33: Minority interests | C33: NOKm | E33: =Model!E99 -> -3.8 | F33: =Model!F99 -> -1.8 | G33: =Model!G99 -> -3.1 | H33: =Model!H99 -> -4.1 | I33: =Model!I99 -> -4.7 | J33: =Model!J99 -> -5.8 | K33: =Model!K99 -> -6.8 | L33: =Model!L99 -> -7.3727402 | ... S33: =Model!S99 -> -11.713408
B34: Net profit to shareholders | C34: NOKm | E34: =Model!E100 -> 378.8 | F34: =Model!F100 -> 179.1 | G34: =Model!G100 -> 308.6 | H34: =Model!H100 -> 405.1 | I34: =Model!I100 -> 469.9 | J34: =Model!J100 -> 575.5 | K34: =Model!K100 -> 672 | L34: =Model!L100 -> 729.90128 | ... S34: =Model!S100 -> 1159.6274
B35: Margin | C35: % | E35: =E34/E9 -> 0.09994723 | F35: =F34/F9 -> 0.051643599 | G35: =G34/G9 -> 0.084133043 | H35: =H34/H9 -> 0.095049273 | I35: =I34/I9 -> 0.10025603 | J35: =J34/J9 -> 0.11407334 | K35: =K34/K9 -> 0.12368857 | L35: =L34/L9 -> 0.12746144 | ... S35: =S34/S9 -> 0.14066022
B37: Memo: pre-IFRS 16 earnings used in the valuation
B38: EBITDAaL (EBITDA after lease payments) | C38: NOKm | E38: =Model!E82 -> 731.5 | F38: =Model!F82 -> 513.3 | G38: =Model!G82 -> 623.5 | H38: =Model!H82 -> 775.7 | I38: =Model!I82 -> 923.3 | J38: =Model!J82 -> 1054.4 | K38: =Model!K82 -> 1189.8 | L38: =Model!L82 -> 1251.5598 | ... S38: =Model!S82 -> 1934.0491
B39: EBIT adj. (pre-IFRS 16, excl. special items) | C39: NOKm | E39: =Model!E85 -> 557.2 | F39: =Model!F85 -> 336.4 | G39: =Model!G85 -> 443.8 | H39: =Model!H85 -> 579.6 | I39: =Model!I85 -> 712.4 | J39: =Model!J85 -> 827.4 | K39: =Model!K85 -> 950.7 | L39: =Model!L85 -> 999.5961 | ... S39: =Model!S85 -> 1571.3054
B40: Margin | C40: % | E40: =E39/E9 -> 0.14701847 | F40: =F39/F9 -> 0.097001153 | G40: =G39/G9 -> 0.12099237 | H40: =H39/H9 -> 0.13599249 | I40: =I39/I9 -> 0.15199488 | J40: =J39/J9 -> 0.16400396 | K40: =K39/K9 -> 0.1749862 | L40: =L39/L9 -> 0.17455779 | ... S40: =S39/S9 -> 0.19059585
B41: EPS | C41: NOK | E41: =Model!E105 -> 4.4564706 | F41: =Model!F105 -> 2.1070588 | G41: =Model!G105 -> 3.6305882 | H41: =Model!H105 -> 4.7658824 | I41: =Model!I105 -> 5.5282353 | J41: =Model!J105 -> 6.7705882 | K41: =Model!K105 -> 7.9058824 | L41: =Model!L105 -> 8.5718035 | ... S41: =Model!S105 -> 14.942224
B42: DPS | C42: NOK | E42: =Model!E107 -> 0 | F42: =Model!F107 -> 0 | G42: =Model!G107 -> 2.5 | H42: =Model!H107 -> 3.5 | I42: =Model!I107 -> 4.2 | J42: =Model!J107 -> 4.8 | K42: =Model!K107 -> 5.4 | L42: =Model!L107 -> 5.5716723 | ... S42: =Model!S107 -> 13.448002
B44: Balance sheet – capital employed format
B46: Net working capital | C46: NOKm | E46: =Model!E112 -> -227.4 | F46: =Model!F112 -> -180.3 | G46: =Model!G112 -> -205.4 | H46: =Model!H112 -> -260 | I46: =Model!I112 -> -295.3 | J46: =Model!J112 -> -322.9 | K46: =Model!K112 -> -353.1 | L46: =Model!L112 -> -372.21912 | ... S46: =Model!S112 -> -535.87134
B47: PP&E and intangibles excl. goodwill | C47: NOKm | E47: =Model!E117 -> 1072.8 | F47: =Model!F117 -> 1020.7 | G47: =Model!G117 -> 1002.4 | H47: =Model!H117 -> 1245 | I47: =Model!I117 -> 1287.2 | J47: =Model!J117 -> 1437.5 | K47: =Model!K117 -> 1470.1 | L47: =Model!L117 -> 1658.4587 | ... S47: =Model!S117 -> 2799.4167
B48: Goodwill | C48: NOKm | E48: =Model!E118 -> 1800 | F48: =Model!F118 -> 1800 | G48: =Model!G118 -> 1800 | H48: =Model!H118 -> 2400 | I48: =Model!I118 -> 2400 | J48: =Model!J118 -> 2730 | K48: =Model!K118 -> 2730 | L48: =Model!L118 -> 2730 | ... S48: =Model!S118 -> 2730
B49: Invested capital (pre-IFRS 16) | C49: NOKm | E49: =E46+E47+E48 -> 2645.4 | F49: =F46+F47+F48 -> 2640.4 | G49: =G46+G47+G48 -> 2597 | H49: =H46+H47+H48 -> 3385 | I49: =I46+I47+I48 -> 3391.9 | J49: =J46+J47+J48 -> 3844.6 | K49: =K46+K47+K48 -> 3847 | L49: =L46+L47+L48 -> 4016.2396 | ... S49: =S46+S47+S48 -> 4993.5454
B51: Right-of-use assets | C51: NOKm | E51: =Model!E140 -> 1267.3 | F51: =Model!F140 -> 1284.5 | G51: =Model!G140 -> 1301.3 | H51: =Model!H140 -> 1397.9 | I51: =Model!I140 -> 1505 | J51: =Model!J140 -> 1604.1 | K51: =Model!K140 -> 1710 | L51: =Model!L140 -> 1819.0874 | ... S51: =Model!S140 -> 2557.4492
B52: Other non-current assets | C52: NOKm | E52: =Model!E141 -> 55 | F52: =Model!F141 -> 55 | G52: =Model!G141 -> 55 | H52: =Model!H141 -> 55 | I52: =Model!I141 -> 55 | J52: =Model!J141 -> 55 | K52: =Model!K141 -> 55 | L52: =Model!L141 -> 55 | ... S52: =Model!S141 -> 55
B53: Net capital employed | C53: NOKm | E53: =E49+E51+E52 -> 3967.7 | F53: =F49+F51+F52 -> 3979.9 | G53: =G49+G51+G52 -> 3953.3 | H53: =H49+H51+H52 -> 4837.9 | I53: =I49+I51+I52 -> 4951.9 | J53: =J49+J51+J52 -> 5503.7 | K53: =K49+K51+K52 -> 5612 | L53: =L49+L51+L52 -> 5890.327 | ... S53: =S49+S51+S52 -> 7605.9945
B55: Net interest-bearing debt excl. leases | C55: NOKm | E55: =Model!E135 -> 1148.5 | F55: =Model!F135 -> 962.6 | G55: =Model!G135 -> 607.5 | H55: =Model!H135 -> 1198.8 | I55: =Model!I135 -> 1028.6 | J55: =Model!J135 -> 1257 | K55: =Model!K135 -> 988.6 | L55: =Model!L135 -> 938.66986 | ... S55: =Model!S135 -> 1450.5368
B56: Lease liabilities | C56: NOKm | E56: =Model!E136 -> 1337.3 | F56: =Model!F136 -> 1354.5 | G56: =Model!G136 -> 1371.3 | H56: =Model!H136 -> 1467.9 | I56: =Model!I136 -> 1575 | J56: =Model!J136 -> 1674.1 | K56: =Model!K136 -> 1780 | L56: =Model!L136 -> 1889.0874 | ... S56: =Model!S136 -> 2627.4492
B57: Net debt incl. leases | C57: NOKm | E57: =E55+E56 -> 2485.8 | F57: =F55+F56 -> 2317.1 | G57: =G55+G56 -> 1978.8 | H57: =H55+H56 -> 2666.7 | I57: =I55+I56 -> 2603.6 | J57: =J55+J56 -> 2931.1 | K57: =K55+K56 -> 2768.6 | L57: =L55+L56 -> 2827.7572 | ... S57: =S55+S56 -> 4077.986
B59: Deferred tax and other non-current liabilities | C59: NOKm | E59: =Model!E142 -> 180 | F59: =Model!F142 -> 180 | G59: =Model!G142 -> 180 | H59: =Model!H142 -> 180 | I59: =Model!I142 -> 180 | J59: =Model!J142 -> 180 | K59: =Model!K142 -> 180 | L59: =Model!L142 -> 180 | ... S59: =Model!S142 -> 180
B61: Equity to shareholders | C61: NOKm | E61: =Model!E143 -> 1270.1 | F61: =Model!F143 -> 1449.2 | G61: =Model!G143 -> 1757.8 | H61: =Model!H143 -> 1950.4 | I61: =Model!I143 -> 2122.8 | J61: =Model!J143 -> 2341.3 | K61: =Model!K143 -> 2605.3 | L61: =Model!L143 -> 2817.097 | ... S61: =Model!S143 -> 3212.682
B62: Minority interests | C62: NOKm | E62: =Model!E144 -> 31.8 | F62: =Model!F144 -> 33.6 | G62: =Model!G144 -> 36.7 | H62: =Model!H144 -> 40.8 | I62: =Model!I144 -> 45.5 | J62: =Model!J144 -> 51.3 | K62: =Model!K144 -> 58.1 | L62: =Model!L144 -> 65.47274 | ... S62: =Model!S144 -> 135.32656
B63: Total equity | C63: NOKm | E63: =E61+E62 -> 1301.9 | F63: =F61+F62 -> 1482.8 | G63: =G61+G62 -> 1794.5 | H63: =H61+H62 -> 1991.2 | I63: =I61+I62 -> 2168.3 | J63: =J61+J62 -> 2392.6 | K63: =K61+K62 -> 2663.4 | L63: =L61+L62 -> 2882.5697 | ... S63: =S61+S62 -> 3348.0085
B65: Total funds invested | C65: NOKm | E65: =E57+E59+E63 -> 3967.7 | F65: =F57+F59+F63 -> 3979.9 | G65: =G57+G59+G63 -> 3953.3 | H65: =H57+H59+H63 -> 4837.9 | I65: =I57+I59+I63 -> 4951.9 | J65: =J57+J59+J63 -> 5503.7 | K65: =K57+K59+K63 -> 5612 | L65: =L57+L59+L63 -> 5890.327 | ... S65: =S57+S59+S63 -> 7605.9945
B66: Check (capital employed – funds invested) | C66: NOKm | E66: =ROUND(E53-E65,1) -> 0 | F66: =ROUND(F53-F65,1) -> 0 | G66: =ROUND(G53-G65,1) -> 0 | H66: =ROUND(H53-H65,1) -> 0 | I66: =ROUND(I53-I65,1) -> 0 | J66: =ROUND(J53-J65,1) -> 0 | K66: =ROUND(K53-K65,1) -> 0 | L66: =ROUND(L53-L65,1) -> 0 | ... S66: =ROUND(S53-S65,1) -> 0
B68: Cash flow statement
B70: EBITDAaL | C70: NOKm | F70: =F38 -> 513.3 | G70: =G38 -> 623.5 | H70: =H38 -> 775.7 | I70: =I38 -> 923.3 | J70: =J38 -> 1054.4 | K70: =K38 -> 1189.8 | L70: =L38 -> 1251.5598 | M70: =M38 -> 1342.8702 | ... S70: =S38 -> 1934.0491
B71: Income tax | C71: NOKm | F71: =F31 -> -61.3 | G71: =G31 -> -87.9 | H71: =H31 -> -115.4 | I71: =I31 -> -133.8 | J71: =J31 -> -164 | K71: =K31 -> -191.5 | L71: =L31 -> -207.94908 | M71: =M31 -> -225.80147 | ... S71: =S31 -> -330.37818
B72: Net financial items excl. leases | C72: NOKm | F72: =F27 -> -49.2 | G72: =G27 -> -44.2 | H72: =H27 -> -55 | I72: =I27 -> -84 | J72: =J27 -> -82.1 | K72: =K27 -> -80.4 | L72: =L27 -> -54.373 | M72: =M27 -> -48.810833 | ... S72: =S27 -> -69.586427
B73: Special items | C73: NOKm | F73: =F23 -> -45 | G73: =G23 -> 0 | H73: =H23 -> 0 | I73: =I23 -> -20 | J73: =J23 -> 0 | K73: =K23 -> 0 | L73: =L23 -> 0 | M73: =M23 -> 0 | ... S73: =S23 -> 0
B74: Change in net working capital | C74: NOKm | F74: =-Model!F113 -> -47.1 | G74: =-Model!G113 -> 25.1 | H74: =-Model!H113 -> 54.6 | I74: =-Model!I113 -> 35.3 | J74: =-Model!J113 -> 27.6 | K74: =-Model!K113 -> 30.2 | L74: =-Model!L113 -> 19.119117 | M74: =-Model!M113 -> 23.230659 | ... S74: =-Model!S113 -> 19.847874
B75: Other operating items (reported history) | C75: NOKm | F75: =Hist!F63+Hist!F32-SUM(F70:F74) -> 0 | G75: =Hist!G63+Hist!G32-SUM(G70:G74) -> 0 | H75: =Hist!H63+Hist!H32-SUM(H70:H74) -> 0 | I75: =Hist!I63+Hist!I32-SUM(I70:I74) -> 0 | J75: =Hist!J63+Hist!J32-SUM(J70:J74) -> 0 | K75: =Hist!K63+Hist!K32-SUM(K70:K74) -> 0 | L75: =0 -> 0 | M75: =0 -> 0 | N75: =0 -> 0 | O75: =0 -> 0 | P75: =0 -> 0 | Q75: =0 -> 0 | R75: =0 -> 0 | S75: =0 -> 0 | V75: History: difference between reported cash flow from operations and the lines above
B76: Cash flow from operations after leases | C76: NOKm | F76: =SUM(F70:F75) -> 310.7 | G76: =SUM(G70:G75) -> 516.5 | H76: =SUM(H70:H75) -> 659.9 | I76: =SUM(I70:I75) -> 720.8 | J76: =SUM(J70:J75) -> 835.9 | K76: =SUM(K70:K75) -> 948.1 | L76: =SUM(L70:L75) -> 1008.3568 | M76: =SUM(M70:M75) -> 1091.4886 | ... S76: =SUM(S70:S75) -> 1553.9324
B78: Capital expenditure | C78: NOKm | F78: =Model!F116 -> -124.8 | G78: =Model!G116 -> -161.4 | H78: =Model!H116 -> -238.7 | I78: =Model!I116 -> -253.1 | J78: =Model!J116 -> -257.3 | K78: =Model!K116 -> -271.7 | L78: =Model!L116 -> -440.3224 | M78: =Model!M116 -> -462.39214 | ... S78: =Model!S116 -> -490.50873
B79: Free cash flow (after leases, interest and tax) | C79: NOKm | F79: =F76+F78 -> 185.9 | G79: =G76+G78 -> 355.1 | H79: =H76+H78 -> 421.2 | I79: =I76+I78 -> 467.7 | J79: =J76+J78 -> 578.6 | K79: =K76+K78 -> 676.4 | L79: =L76+L78 -> 568.03445 | M79: =M76+M78 -> 629.09646 | ... S79: =S76+S78 -> 1063.4236
B81: Acquisitions and disposals | C81: NOKm | F81: =Hist!F65 -> 0 | G81: =Hist!G65 -> 0 | H81: =Hist!H65 -> -800 | I81: =Hist!I65 -> 0 | J81: =Hist!J65 -> -450 | K81: =Hist!K65 -> 0 | L81: =0 -> 0 | M81: =0 -> 0 | N81: =0 -> 0 | O81: =0 -> 0 | P81: =0 -> 0 | Q81: =0 -> 0 | R81: =0 -> 0 | S81: =0 -> 0
B82: Dividends paid | C82: NOKm | F82: =Model!F131 -> 0 | G82: =Model!G131 -> 0 | H82: =Model!H131 -> -212.5 | I82: =Model!I131 -> -297.5 | J82: =Model!J131 -> -357 | K82: =Model!K131 -> -408 | L82: =Model!L131 -> -459 | M82: =Model!M131 -> -474.43583 | ... S82: =Model!S131 -> -1000.7805
B83: Share buybacks | C83: NOKm | F83: =0 -> 0 | G83: =0 -> 0 | H83: =0 -> 0 | I83: =0 -> 0 | J83: =0 -> 0 | K83: =0 -> 0 | L83: =Model!L134 -> -59.104313 | M83: =Model!M134 -> -223.14344 | N83: =Model!N134 -> -224.28066 | O83: =Model!O134 -> -219.57236 | P83: =Model!P134 -> -202.9806 | Q83: =Model!Q134 -> -171.83791 | R83: =Model!R134 -> -132.95397 | S83: =Model!S134 -> -121.45146 | V83: Forecast: cash above the target leverage on Drivers (section E) when the buyback switch is on
B84: Other items (reported history) | C84: NOKm | F84: =(E55-F55)-(F79+F81+F82+F83) -> 0 | G84: =(F55-G55)-(G79+G81+G82+G83) -> 0 | H84: =(G55-H55)-(H79+H81+H82+H83) -> 0 | I84: =(H55-I55)-(I79+I81+I82+I83) -> 3.4106051e-13 | J84: =(I55-J55)-(J79+J81+J82+J83) -> -2.2737368e-13 | K84: =(J55-K55)-(K79+K81+K82+K83) -> 0 | L84: =0 -> 0 | M84: =0 -> 0 | N84: =0 -> 0 | O84: =0 -> 0 | P84: =0 -> 0 | Q84: =0 -> 0 | R84: =0 -> 0 | S84: =0 -> 0 | V84: History: balancing item so the statement ties to the reported change in net debt
B85: Decrease / (increase) in net interest-bearing debt | C85: NOKm | F85: =F79+F81+F82+F83+F84 -> 185.9 | G85: =G79+G81+G82+G83+G84 -> 355.1 | H85: =H79+H81+H82+H83+H84 -> -591.3 | I85: =I79+I81+I82+I83+I84 -> 170.2 | J85: =J79+J81+J82+J83+J84 -> -228.4 | K85: =K79+K81+K82+K83+K84 -> 268.4 | L85: =L79+L81+L82+L83+L84 -> 49.930139 | M85: =M79+M81+M82+M83+M84 -> -68.482819 | ... S85: =S79+S81+S82+S83+S84 -> -58.808294
B87: Net interest-bearing debt – opening | C87: NOKm | F87: =E55 -> 1148.5 | G87: =F55 -> 962.6 | H87: =G55 -> 607.5 | I87: =H55 -> 1198.8 | J87: =I55 -> 1028.6 | K87: =J55 -> 1257 | L87: =K55 -> 988.6 | M87: =L55 -> 938.66986 | ... S87: =R55 -> 1391.7285
B88: Net interest-bearing debt – closing | C88: NOKm | F88: =F87-F85 -> 962.6 | G88: =G87-G85 -> 607.5 | H88: =H87-H85 -> 1198.8 | I88: =I87-I85 -> 1028.6 | J88: =J87-J85 -> 1257 | K88: =K87-K85 -> 988.6 | L88: =L87-L85 -> 938.66986 | M88: =M87-M85 -> 1007.1527 | ... S88: =S87-S85 -> 1450.5368
B89: Check (closing NIBD – balance sheet) | C89: NOKm | F89: =ROUND(F88-F55,1) -> 0 | G89: =ROUND(G88-G55,1) -> 0 | H89: =ROUND(H88-H55,1) -> 0 | I89: =ROUND(I88-I55,1) -> 0 | J89: =ROUND(J88-J55,1) -> 0 | K89: =ROUND(K88-K55,1) -> 0 | L89: =ROUND(L88-L55,1) -> 0 | M89: =ROUND(M88-M55,1) -> 0 | ... S89: =ROUND(S88-S55,1) -> 0
B91: Memo
B92: Free cash flow to firm (unlevered – used in the DCF) | C92: NOKm | F92: =Model!F125 -> 267.392 | G92: =Model!G125 -> 389.564 | H92: =Model!H125 -> 464.088 | I92: =Model!I125 -> 548.772 | J92: =Model!J125 -> 642.672 | K92: =Model!K125 -> 739.146 | L92: =Model!L125 -> 610.44539 | M92: =Model!M125 -> 667.16891 | ... S92: =Model!S125 -> 1117.7011

Sheet Analysis
B1: Financial Analysis | T1: =Inputs!$C$6&" | Scenario: "&Inputs!$C$53 -> Example Company ASA | Scenario: Base
B2: Growth, profitability, returns, leverage, per-share data and valuation multiples.
E3: =Inputs!$C$17+0 -> 2019 | F3: =Inputs!$C$17+1 -> 2020 | G3: =Inputs!$C$17+2 -> 2021 | H3: =Inputs!$C$17+3 -> 2022 | I3: =Inputs!$C$17+4 -> 2023 | J3: =Inputs!$C$17+5 -> 2024 | K3: =Inputs!$C$17+6 -> 2025 | L3: =Inputs!$C$19+0 -> 2026 | M3: =Inputs!$C$19+1 -> 2027 | N3: =Inputs!$C$19+2 -> 2028 | O3: =Inputs!$C$19+3 -> 2029 | P3: =Inputs!$C$19+4 -> 2030 | Q3: =Inputs!$C$19+5 -> 2031 | R3: =Inputs!$C$19+6 -> 2032 | S3: =Inputs!$C$19+7 -> 2033
E4: Historicals | L4: Explicit forecast
B5: ="("&Inputs!$C$11&")" -> (NOKm) | E5: =E3&"A" -> 2019A | F5: =F3&"A" -> 2020A | G5: =G3&"A" -> 2021A | H5: =H3&"A" -> 2022A | I5: =I3&"A" -> 2023A | J5: =J3&"A" -> 2024A | K5: =K3&"A" -> 2025A | L5: =L3&"E" -> 2026E | M5: =M3&"E" -> 2027E | N5: =N3&"E" -> 2028E | O5: =O3&"E" -> 2029E | P5: =P3&"E" -> 2030E | Q5: =Q3&"E" -> 2031E | R5: =R3&"E" -> 2032E | S5: =S3&"E" -> 2033E | V5: Notes
B7: Growth (year on year)
B9: Revenue | C9: % | F9: =Model!F59 -> -0.084960422 | G9: =Model!G59 -> 0.057670127 | H9: =Model!H59 -> 0.16194111 | I9: =Model!I59 -> 0.099718442 | J9: =Model!J59 -> 0.076381481 | K9: =Model!K59 -> 0.07690783 | L9: =Model!L59 -> 0.05401214 | M9: =Model!M59 -> 0.062411248 | ... S9: =Model!S59 -> 0.038463123
B10: – of which volume | C10: % | F10: =Model!F60 -> -0.066278499 | G10: =Model!G60 -> 0.035508911 | H10: =Model!H60 -> 0.11026525 | I10: =Model!I60 -> 0.050633246 | J10: =Model!J60 -> 0.030697769 | K10: =Model!K60 -> 0.032636412 | L10: =Model!L60 -> 0.020709943 | M10: =Model!M60 -> 0.031836296 | ... S10: =Model!S60 -> 0.016108731
B11: of which new locations (capacity) | C11: % | F11: =Model!F61 -> 0.011085958 | G11: =Model!G61 -> 0.022097561 | H11: =Model!H61 -> 0.066576179 | I11: =Model!I61 -> 0.023084933 | J11: =Model!J61 -> 0.02376248 | K11: =Model!K61 -> 0.028595251 | L11: =Model!L61 -> 0.0106988 | M11: =Model!M61 -> 0.022696934 | ... S11: =Model!S61 -> 0.01265133
B12: of which like-for-like volume | C12: % | F12: =Model!F62 -> -0.077364457 | G12: =Model!G62 -> 0.01341135 | H12: =Model!H62 -> 0.043689067 | I12: =Model!I62 -> 0.027548314 | J12: =Model!J62 -> 0.0069352889 | K12: =Model!K62 -> 0.0040411609 | L12: =Model!L62 -> 0.010011143 | M12: =Model!M62 -> 0.0091393618 | ... S12: =Model!S62 -> 0.0034574003
B13: – of which price/mix | C13: % | F13: =Model!F63 -> -0.018681923 | G13: =Model!G63 -> 0.022161216 | H13: =Model!H63 -> 0.051675866 | I13: =Model!I63 -> 0.049085196 | J13: =Model!J63 -> 0.045683711 | K13: =Model!K63 -> 0.044271418 | L13: =Model!L63 -> 0.033302198 | M13: =Model!M63 -> 0.030574952 | ... S13: =Model!S63 -> 0.022354392
B14: EBITDA | C14: % | F14: =IF(Model!E78<=0,"n.m.",Model!F78/Model!E78-1) -> -0.20392418 | G14: =IF(Model!F78<=0,"n.m.",Model!G78/Model!F78-1) -> 0.13663556 | H14: =IF(Model!G78<=0,"n.m.",Model!H78/Model!G78-1) -> 0.18442105 | I14: =IF(Model!H78<=0,"n.m.",Model!I78/Model!H78-1) -> 0.15383932 | J14: =IF(Model!I78<=0,"n.m.",Model!J78/Model!I78-1) -> 0.11915582 | K14: =IF(Model!J78<=0,"n.m.",Model!K78/Model!J78-1) -> 0.11052994 | L14: =IF(Model!K78<=0,"n.m.",Model!L78/Model!K78-1) -> 0.054370611 | M14: =IF(Model!L78<=0,"n.m.",Model!M78/Model!L78-1) -> 0.069426938 | ... S14: =IF(Model!R78<=0,"n.m.",Model!S78/Model!R78-1) -> 0.040986526
B15: EBIT adj. | C15: % | F15: =IF(Model!E85<=0,"n.m.",Model!F85/Model!E85-1) -> -0.39626705 | G15: =IF(Model!F85<=0,"n.m.",Model!G85/Model!F85-1) -> 0.31926278 | H15: =IF(Model!G85<=0,"n.m.",Model!H85/Model!G85-1) -> 0.30599369 | I15: =IF(Model!H85<=0,"n.m.",Model!I85/Model!H85-1) -> 0.22912353 | J15: =IF(Model!I85<=0,"n.m.",Model!J85/Model!I85-1) -> 0.16142617 | K15: =IF(Model!J85<=0,"n.m.",Model!K85/Model!J85-1) -> 0.14902103 | L15: =IF(Model!K85<=0,"n.m.",Model!L85/Model!K85-1) -> 0.051431687 | M15: =IF(Model!L85<=0,"n.m.",Model!M85/Model!L85-1) -> 0.075615596 | ... S15: =IF(Model!R85<=0,"n.m.",Model!S85/Model!R85-1) -> 0.043135024
B16: EPS | C16: % | F16: =Model!F106 -> -0.52719113 | G16: =Model!G106 -> 0.72305974 | H16: =Model!H106 -> 0.31270253 | I16: =Model!I106 -> 0.1599605 | J16: =Model!J106 -> 0.22472867 | K16: =Model!K106 -> 0.16768028 | L16: =Model!L106 -> 0.084231102 | M16: =Model!M106 -> 0.10622149 | ... S16: =Model!S106 -> 0.050077974
B17: DPS | C17: % | F17: =IF(Model!E107<=0,"n.m.",Model!F107/Model!E107-1) -> n.m. | G17: =IF(Model!F107<=0,"n.m.",Model!G107/Model!F107-1) -> n.m. | H17: =IF(Model!G107<=0,"n.m.",Model!H107/Model!G107-1) -> 0.4 | I17: =IF(Model!H107<=0,"n.m.",Model!I107/Model!H107-1) -> 0.2 | J17: =IF(Model!I107<=0,"n.m.",Model!J107/Model!I107-1) -> 0.14285714 | K17: =IF(Model!J107<=0,"n.m.",Model!K107/Model!J107-1) -> 0.125 | L17: =IF(Model!K107<=0,"n.m.",Model!L107/Model!K107-1) -> 0.031791167 | M17: =IF(Model!L107<=0,"n.m.",Model!M107/Model!L107-1) -> 0.19131546 | ... S17: =IF(Model!R107<=0,"n.m.",Model!S107/Model!R107-1) -> 0.050077974
B18: Free cash flow to firm | C18: % | G18: =IF(Model!F125<=0,"n.m.",Model!G125/Model!F125-1) -> 0.45690223 | H18: =IF(Model!G125<=0,"n.m.",Model!H125/Model!G125-1) -> 0.19130104 | I18: =IF(Model!H125<=0,"n.m.",Model!I125/Model!H125-1) -> 0.18247401 | J18: =IF(Model!I125<=0,"n.m.",Model!J125/Model!I125-1) -> 0.17110931 | K18: =IF(Model!J125<=0,"n.m.",Model!K125/Model!J125-1) -> 0.1501139 | L18: =IF(Model!K125<=0,"n.m.",Model!L125/Model!K125-1) -> -0.17412069 | M18: =IF(Model!L125<=0,"n.m.",Model!M125/Model!L125-1) -> 0.092921525 | N18: =IF(Model!M125<=0,"n.m.",Model!N125/Model!M125-1) -> 0.10305092 | ... S18: =IF(Model!R125<=0,"n.m.",Model!S125/Model!R125-1) -> 0.042667862
B20: Profitability
B22: Gross margin | C22: % | E22: =Model!E70 -> 0.63501319 | F22: =Model!F70 -> 0.62200115 | G22: =Model!G70 -> 0.62799891 | H22: =Model!H70 -> 0.61900516 | I22: =Model!I70 -> 0.62400256 | J22: =Model!J70 -> 0.62999009 | K22: =Model!K70 -> 0.63399595 | L22: =Model!L70 -> 0.634 | ... S22: =Model!S70 -> 0.634
B23: EBITDA margin (reported) | C23: % | E23: =Model!E79 -> 0.27701847 | F23: =Model!F79 -> 0.24100346 | G23: =Model!G79 -> 0.25899673 | H23: =Model!H79 -> 0.26400751 | I23: =Model!I79 -> 0.27700021 | J23: =Model!J79 -> 0.28800793 | K23: =Model!K79 -> 0.29699982 | L23: =Model!L79 -> 0.29710083 | ... S23: =Model!S79 -> 0.31047598
B24: EBITDAaL margin | C24: % | E24: =Model!E83 -> 0.19300792 | F24: =Model!F83 -> 0.14801038 | G24: =Model!G83 -> 0.16998364 | H24: =Model!H83 -> 0.18200375 | I24: =Model!I83 -> 0.19699168 | J24: =Model!J83 -> 0.20899901 | K24: =Model!K83 -> 0.21899503 | L24: =Model!L83 -> 0.21855779 | ... S24: =Model!S83 -> 0.23459585
B25: EBIT adj. margin | C25: % | E25: =Model!E86 -> 0.14701847 | F25: =Model!F86 -> 0.097001153 | G25: =Model!G86 -> 0.12099237 | H25: =Model!H86 -> 0.13599249 | I25: =Model!I86 -> 0.15199488 | J25: =Model!J86 -> 0.16400396 | K25: =Model!K86 -> 0.1749862 | L25: =Model!L86 -> 0.17455779 | ... S25: =Model!S86 -> 0.19059585
B26: Net profit margin | C26: % | E26: =Model!E101 -> 0.09994723 | F26: =Model!F101 -> 0.051643599 | G26: =Model!G101 -> 0.084133043 | H26: =Model!H101 -> 0.095049273 | I26: =Model!I101 -> 0.10025603 | J26: =Model!J101 -> 0.11407334 | K26: =Model!K101 -> 0.12368857 | L26: =Model!L101 -> 0.12746144 | ... S26: =Model!S101 -> 0.14066022
B27: Effective tax rate | C27: % | E27: =IF(Model!E96=0,0,-Model!E97/Model!E96) -> 0.23002616 | F27: =IF(Model!F96=0,0,-Model!F97/Model!F96) -> 0.25309661 | G27: =IF(Model!G96=0,0,-Model!G97/Model!G96) -> 0.21996997 | H27: =IF(Model!H96=0,0,-Model!H97/Model!H96) -> 0.21997713 | I27: =IF(Model!I96=0,0,-Model!I97/Model!I96) -> 0.2199211 | J27: =IF(Model!J96=0,0,-Model!J97/Model!J96) -> 0.22004562 | K27: =IF(Model!K96=0,0,-Model!K97/Model!K96) -> 0.22003907 | L27: =IF(Model!L96=0,0,-Model!L97/Model!L96) -> 0.22 | ... S27: =IF(Model!S96=0,0,-Model!S97/Model!S96) -> 0.22
B29: Returns and capital efficiency (DuPont: ROIC = NOPAT margin x capital turnover)
B31: NOPAT margin | C31: % | E31: =Model!E121/Model!E67 -> 0.11467441 | F31: =Model!F121/Model!F67 -> 0.0756609 | G31: =Model!G121/Model!G67 -> 0.094374046 | H31: =Model!H121/Model!H67 -> 0.10607414 | I31: =Model!I121/Model!I67 -> 0.11855601 | J31: =Model!J121/Model!J67 -> 0.12792309 | K31: =Model!K121/Model!K67 -> 0.13648923 | L31: =Model!L121/Model!L67 -> 0.13615508 | ... S31: =Model!S121/Model!S67 -> 0.14866476
B32: Capital turnover (revenue / average invested capital) | C32: x | F32: =Model!F67/AVERAGE(Model!E119,Model!F119) -> 1.3121949 | G32: =Model!G67/AVERAGE(Model!F119,Model!G119) -> 1.400695 | H32: =Model!H67/AVERAGE(Model!G119,Model!H119) -> 1.4249415 | I32: =Model!I67/AVERAGE(Model!H119,Model!I119) -> 1.3832283 | J32: =Model!J67/AVERAGE(Model!I119,Model!J119) -> 1.3943205 | K32: =Model!K67/AVERAGE(Model!J119,Model!K119) -> 1.41271 | L32: =Model!L67/AVERAGE(Model!K119,Model!L119) -> 1.4565111 | M32: =Model!M67/AVERAGE(Model!L119,Model!M119) -> 1.4831494 | ... S32: =Model!S67/AVERAGE(Model!R119,Model!S119) -> 1.6690009
B33: ROIC | C33: % | F33: =Model!F122 -> 0.099281849 | G33: =Model!G122 -> 0.13218925 | H33: =Model!H122 -> 0.15114945 | I33: =Model!I122 -> 0.16399002 | J33: =Model!J122 -> 0.17836578 | K33: =Model!K122 -> 0.1928197 | L33: =Model!L122 -> 0.19831138 | M33: =Model!M122 -> 0.20444814 | ... S33: =Model!S122 -> 0.24812161
B34: WACC | C34: % | F34: =WACC!$C$34 -> 0.089875829 | G34: =WACC!$C$34 -> 0.089875829 | H34: =WACC!$C$34 -> 0.089875829 | I34: =WACC!$C$34 -> 0.089875829 | J34: =WACC!$C$34 -> 0.089875829 | K34: =WACC!$C$34 -> 0.089875829 | L34: =WACC!$C$34 -> 0.089875829 | M34: =WACC!$C$34 -> 0.089875829 | ... S34: =WACC!$C$34 -> 0.089875829
B35: ROIC – WACC spread | C35: % | F35: =F33-F34 -> 0.0094060203 | G35: =G33-G34 -> 0.042313425 | H35: =H33-H34 -> 0.061273619 | I35: =I33-I34 -> 0.074114196 | J35: =J33-J34 -> 0.088489955 | K35: =K33-K34 -> 0.10294387 | L35: =L33-L34 -> 0.10843556 | M35: =M33-M34 -> 0.11457231 | ... S35: =S33-S34 -> 0.15824578 | V35: Positive spread = value creation
B36: Return on equity | C36: % | F36: =Model!F145 -> 0.13172508 | G36: =Model!G145 -> 0.19245401 | H36: =Model!H145 -> 0.21848875 | I36: =Model!I145 -> 0.23072768 | J36: =Model!J145 -> 0.25783473 | K36: =Model!K145 -> 0.27170177 | L36: =Model!L145 -> 0.26921721 | M36: =Model!M145 -> 0.27667606 | ... S36: =Model!S145 -> 0.3630661
B38: Cash flow quality and investment intensity
B40: Cash conversion (FCFF / EBITDAaL) | C40: % | F40: =Model!F127 -> 0.52092733 | G40: =Model!G127 -> 0.62480192 | H40: =Model!H127 -> 0.59828284 | I40: =Model!I127 -> 0.59435936 | J40: =Model!J127 -> 0.60951442 | K40: =Model!K127 -> 0.6212355 | L40: =Model!L127 -> 0.48774768 | M40: =Model!M127 -> 0.49682306 | ... S40: =Model!S127 -> 0.57790728
B41: FCFF margin | C41: % | F41: =Model!F126 -> 0.077102653 | G41: =Model!G126 -> 0.10620611 | H41: =Model!H126 -> 0.10888972 | I41: =Model!I126 -> 0.11708385 | J41: =Model!J126 -> 0.12738791 | K41: =Model!K126 -> 0.13604749 | L41: =Model!L126 -> 0.10660105 | M41: =Model!M126 -> 0.10966242 | ... S41: =Model!S126 -> 0.13557465
B42: Capex / revenue | C42: % | E42: =-Model!E116/Model!E67 -> 0.052005277 | F42: =-Model!F116/Model!F67 -> 0.035986159 | G42: =-Model!G116/Model!G67 -> 0.044002181 | H42: =-Model!H116/Model!H67 -> 0.05600657 | I42: =-Model!I116/Model!I67 -> 0.054000427 | J42: =-Model!J116/Model!J67 -> 0.051000991 | K42: =-Model!K116/Model!K67 -> 0.050009203 | L42: =-Model!L116/Model!L67 -> 0.076892762 | ... S42: =-Model!S116/Model!S67 -> 0.059497616
B43: Capex / D&A | C43: x | E43: =IF(Model!E84=0,0,Model!E116/Model!E84) -> 1.130809 | F43: =IF(Model!F84=0,0,Model!F116/Model!F84) -> 0.70548332 | G43: =IF(Model!G84=0,0,Model!G116/Model!G84) -> 0.89816361 | H43: =IF(Model!H84=0,0,Model!H116/Model!H84) -> 1.2172361 | I43: =IF(Model!I84=0,0,Model!I116/Model!I84) -> 1.2000948 | J43: =IF(Model!J84=0,0,Model!J116/Model!J84) -> 1.1334802 | K43: =IF(Model!K84=0,0,Model!K116/Model!K84) -> 1.1363446 | L43: =IF(Model!L84=0,0,Model!L116/Model!L84) -> 1.7475628 | ... S43: =IF(Model!S84=0,0,Model!S116/Model!S84) -> 1.3522185
B44: Net reinvestment / revenue (capex – D&A + increase in NWC) | C44: % | F44: =Model!F123/Model!F67 -> -0.0014417532 | G44: =Model!G123/Model!G67 -> -0.011832061 | H44: =Model!H123/Model!H67 -> -0.0028155795 | I44: =Model!I123/Model!I67 -> 0.001472157 | J44: =Model!J123/Model!J67 -> 0.00053518335 | K44: =Model!K123/Model!K67 -> 0.00044174489 | L44: =Model!L123/Model!L67 -> 0.029554022 | M44: =Model!M123/Model!M67 -> 0.028184883 | ... S44: =Model!S123/Model!S67 -> 0.013090113
B45: Net working capital / revenue | C45: % | E45: =Model!E112/Model!E67 -> -0.06 | F45: =Model!F112/Model!F67 -> -0.051989619 | G45: =Model!G112/Model!G67 -> -0.055997819 | H45: =Model!H112/Model!H67 -> -0.061004223 | I45: =Model!I112/Model!I67 -> -0.063004054 | J45: =Model!J112/Model!J67 -> -0.064003964 | K45: =Model!K112/Model!K67 -> -0.064991717 | L45: =Model!L112/Model!L67 -> -0.065 | ... S45: =Model!S112/Model!S67 -> -0.065
B46: Revenue per average location (NOKm) | C46: NOKm | F46: =Model!F56 -> 18.95082 | G46: =Model!G56 -> 19.72043 | H46: =Model!H56 -> 21.912596 | I46: =Model!I56 -> 23.031941 | J46: =Model!J56 -> 24.196643 | K46: =Model!K56 -> 25.38785 | L46: =Model!L56 -> 25.970286 | M46: =Model!M56 -> 26.742166 | ... S46: =Model!S56 -> 32.016212
B48: Leverage and coverage
B50: NIBD / EBITDAaL | C50: x | E50: =Model!E138 -> 1.5700615 | F50: =Model!F138 -> 1.8753166 | G50: =Model!G138 -> 0.97433841 | H50: =Model!H138 -> 1.5454428 | I50: =Model!I138 -> 1.1140474 | J50: =Model!J138 -> 1.1921472 | K50: =Model!K138 -> 0.83089595 | L50: =Model!L138 -> 0.75 | ... S50: =Model!S138 -> 0.75
B51: Net debt incl. leases / EBITDA | C51: x | E51: =IF(Model!E78=0,0,Model!E137/Model!E78) -> 2.3676541 | F51: =IF(Model!F78=0,0,Model!F137/Model!F78) -> 2.772314 | G51: =IF(Model!G78=0,0,Model!G137/Model!G78) -> 2.0829474 | H51: =IF(Model!H78=0,0,Model!H137/Model!H78) -> 2.3699787 | I51: =IF(Model!I78=0,0,Model!I137/Model!I78) -> 2.0053917 | J51: =IF(Model!J78=0,0,Model!J137/Model!J78) -> 2.0172746 | K51: =IF(Model!K78=0,0,Model!K137/Model!K78) -> 1.7157908 | L51: =IF(Model!L78=0,0,Model!L137/Model!L78) -> 1.6620839 | ... S51: =IF(Model!S78=0,0,Model!S137/Model!S78) -> 1.5932009
B52: Interest cover (EBIT adj. / net financial expense) | C52: x | E52: =IF(Model!E94>=0,"n.m.",-Model!E85/Model!E94) -> 9.2404643 | F52: =IF(Model!F94>=0,"n.m.",-Model!F85/Model!F94) -> 6.8373984 | G52: =IF(Model!G94>=0,"n.m.",-Model!G85/Model!G94) -> 10.040724 | H52: =IF(Model!H94>=0,"n.m.",-Model!H85/Model!H94) -> 10.538182 | I52: =IF(Model!I94>=0,"n.m.",-Model!I85/Model!I94) -> 8.4809524 | J52: =IF(Model!J94>=0,"n.m.",-Model!J85/Model!J94) -> 10.077954 | K52: =IF(Model!K94>=0,"n.m.",-Model!K85/Model!K94) -> 11.824627 | L52: =IF(Model!L94>=0,"n.m.",-Model!L85/Model!L94) -> 18.384053 | ... S52: =IF(Model!S94>=0,"n.m.",-Model!S85/Model!S94) -> 22.580631
B53: NIBD / equity | C53: x | E53: =Model!E135/Model!E143 -> 0.90425951 | F53: =Model!F135/Model!F143 -> 0.66422854 | G53: =Model!G135/Model!G143 -> 0.34560246 | H53: =Model!H135/Model!H143 -> 0.61464315 | I53: =Model!I135/Model!I143 -> 0.48454871 | J53: =Model!J135/Model!J143 -> 0.53688122 | K53: =Model!K135/Model!K143 -> 0.37945726 | L53: =Model!L135/Model!L143 -> 0.33320467 | ... S53: =Model!S135/Model!S143 -> 0.4515034
B55: Per share data (NOK)
B57: EPS | C57: NOK | E57: =Model!E105 -> 4.4564706 | F57: =Model!F105 -> 2.1070588 | G57: =Model!G105 -> 3.6305882 | H57: =Model!H105 -> 4.7658824 | I57: =Model!I105 -> 5.5282353 | J57: =Model!J105 -> 6.7705882 | K57: =Model!K105 -> 7.9058824 | L57: =Model!L105 -> 8.5718035 | ... S57: =Model!S105 -> 14.942224
B58: DPS | C58: NOK | E58: =Model!E107 -> 0 | F58: =Model!F107 -> 0 | G58: =Model!G107 -> 2.5 | H58: =Model!H107 -> 3.5 | I58: =Model!I107 -> 4.2 | J58: =Model!J107 -> 4.8 | K58: =Model!K107 -> 5.4 | L58: =Model!L107 -> 5.5716723 | ... S58: =Model!S107 -> 13.448002
B59: Payout ratio | C59: % | E59: =Model!E108 -> 0 | F59: =Model!F108 -> 0 | G59: =Model!G108 -> 0.68859365 | H59: =Model!H108 -> 0.73438657 | I59: =Model!I108 -> 0.75973611 | J59: =Model!J108 -> 0.70894874 | K59: =Model!K108 -> 0.68303571 | L59: =Model!L108 -> 0.65 | ... S59: =Model!S108 -> 0.9
B60: Diluted shares (m) | C60: m | E60: =Model!E104 -> 85 | F60: =Model!F104 -> 85 | G60: =Model!G104 -> 85 | H60: =Model!H104 -> 85 | I60: =Model!I104 -> 85 | J60: =Model!J104 -> 85 | K60: =Model!K104 -> 85 | L60: =Model!L104 -> 85.151424 | ... S60: =Model!S104 -> 77.607416 | V60: Reduced by buybacks in the forecast
B61: Book value per share | C61: NOK | E61: =Model!E143/Model!E104 -> 14.942353 | F61: =Model!F143/Model!F104 -> 17.049412 | G61: =Model!G143/Model!G104 -> 20.68 | H61: =Model!H143/Model!H104 -> 22.945882 | I61: =Model!I143/Model!I104 -> 24.974118 | J61: =Model!J143/Model!J104 -> 27.544706 | K61: =Model!K143/Model!K104 -> 30.650588 | L61: =Model!L143/Model!L104 -> 33.08338 | ... S61: =Model!S143/Model!S104 -> 41.396585
B62: Free cash flow per share | C62: NOK | F62: =Output!F79/Model!F104 -> 2.1870588 | G62: =Output!G79/Model!G104 -> 4.1776471 | H62: =Output!H79/Model!H104 -> 4.9552941 | I62: =Output!I79/Model!I104 -> 5.5023529 | J62: =Output!J79/Model!J104 -> 6.8070588 | K62: =Output!K79/Model!K104 -> 7.9576471 | L62: =Output!L79/Model!L104 -> 6.6708743 | M62: =Output!M79/Model!M104 -> 7.5265796 | ... S62: =Output!S79/Model!S104 -> 13.702603
B64: Valuation multiples at the current share price
B66: Market capitalisation | C66: NOKm | E66: =Inputs!$C$32 -> 10370 | F66: =Inputs!$C$32 -> 10370 | G66: =Inputs!$C$32 -> 10370 | H66: =Inputs!$C$32 -> 10370 | I66: =Inputs!$C$32 -> 10370 | J66: =Inputs!$C$32 -> 10370 | K66: =Inputs!$C$32 -> 10370 | L66: =Inputs!$C$32 -> 10370 | ... S66: =Inputs!$C$32 -> 10370
B67: Enterprise value excl. leases | C67: NOKm | E67: =Inputs!$C$48 -> 11445 | F67: =Inputs!$C$48 -> 11445 | G67: =Inputs!$C$48 -> 11445 | H67: =Inputs!$C$48 -> 11445 | I67: =Inputs!$C$48 -> 11445 | J67: =Inputs!$C$48 -> 11445 | K67: =Inputs!$C$48 -> 11445 | L67: =Inputs!$C$48 -> 11445 | ... S67: =Inputs!$C$48 -> 11445
B68: Enterprise value incl. leases | C68: NOKm | E68: =Inputs!$C$49 -> 13250 | F68: =Inputs!$C$49 -> 13250 | G68: =Inputs!$C$49 -> 13250 | H68: =Inputs!$C$49 -> 13250 | I68: =Inputs!$C$49 -> 13250 | J68: =Inputs!$C$49 -> 13250 | K68: =Inputs!$C$49 -> 13250 | L68: =Inputs!$C$49 -> 13250 | ... S68: =Inputs!$C$49 -> 13250
B69: EV / Sales | C69: x | E69: =IF(Inputs!$C$67=1,E68,E67)/Model!E67 -> 3.4960422 | F69: =IF(Inputs!$C$67=1,F68,F67)/Model!F67 -> 3.8206459 | G69: =IF(Inputs!$C$67=1,G68,G67)/Model!G67 -> 3.6123228 | H69: =IF(Inputs!$C$67=1,H68,H67)/Model!H67 -> 3.1088691 | I69: =IF(Inputs!$C$67=1,I68,I67)/Model!I67 -> 2.8269682 | J69: =IF(Inputs!$C$67=1,J68,J67)/Model!J67 -> 2.6263627 | K69: =IF(Inputs!$C$67=1,K68,K67)/Model!K67 -> 2.4387999 | L69: =IF(Inputs!$C$67=1,L68,L67)/Model!L67 -> 2.3138253 | ... S69: =IF(Inputs!$C$67=1,S68,S67)/Model!S67 -> 1.6071955 | V69: EV basis follows the peer-multiple switch on Inputs
B70: EV / EBITDA | C70: x | E70: =IF(Inputs!$C$67=1,E68/Model!E78,E67/Model!E82) -> 12.62025 | F70: =IF(Inputs!$C$67=1,F68/Model!F78,F67/Model!F82) -> 15.853075 | G70: =IF(Inputs!$C$67=1,G68/Model!G78,G67/Model!G82) -> 13.947368 | H70: =IF(Inputs!$C$67=1,H68/Model!H78,H67/Model!H82) -> 11.775684 | I70: =IF(Inputs!$C$67=1,I68/Model!I78,I67/Model!I82) -> 10.205654 | J70: =IF(Inputs!$C$67=1,J68/Model!J78,J67/Model!J82) -> 9.119064 | K70: =IF(Inputs!$C$67=1,K68/Model!K78,K67/Model!K82) -> 8.2114527 | L70: =IF(Inputs!$C$67=1,L68/Model!L78,L67/Model!L82) -> 7.7880136 | ... S70: =IF(Inputs!$C$67=1,S68/Model!S78,S67/Model!S82) -> 5.1765533 | V70: IFRS 16 basis: EV incl. leases / reported EBITDA; otherwise EV excl. leases / EBITDAaL
B71: EV / EBIT | C71: x | E71: =IF(Inputs!$C$67=1,E68/(Model!E85-Model!E95),E67/Model!E85) -> 21.33999 | F71: =IF(Inputs!$C$67=1,F68/(Model!F85-Model!F95),F67/Model!F85) -> 33.050636 | G71: =IF(Inputs!$C$67=1,G68/(Model!G85-Model!G95),G67/Model!G85) -> 26.026321 | H71: =IF(Inputs!$C$67=1,H68/(Model!H85-Model!H95),H67/Model!H85) -> 20.400308 | I71: =IF(Inputs!$C$67=1,I68/(Model!I85-Model!I95),I67/Model!I85) -> 16.827534 | J71: =IF(Inputs!$C$67=1,J68/(Model!J85-Model!J95),J67/Model!J85) -> 14.606989 | K71: =IF(Inputs!$C$67=1,K68/(Model!K85-Model!K95),K67/Model!K85) -> 12.795751 | L71: =IF(Inputs!$C$67=1,L68/(Model!L85-Model!L95),L67/Model!L85) -> 12.160977 | ... S71: =IF(Inputs!$C$67=1,S68/(Model!S85-Model!S95),S67/Model!S85) -> 7.8105693
B72: P / E | C72: x | E72: =IF(Model!E105<=0,"n.m.",Inputs!$C$27/Model!E105) -> 27.375924 | F72: =IF(Model!F105<=0,"n.m.",Inputs!$C$27/Model!F105) -> 57.900614 | G72: =IF(Model!G105<=0,"n.m.",Inputs!$C$27/Model!G105) -> 33.60337 | H72: =IF(Model!H105<=0,"n.m.",Inputs!$C$27/Model!H105) -> 25.598618 | I72: =IF(Model!I105<=0,"n.m.",Inputs!$C$27/Model!I105) -> 22.068525 | J72: =IF(Model!J105<=0,"n.m.",Inputs!$C$27/Model!J105) -> 18.019114 | K72: =IF(Model!K105<=0,"n.m.",Inputs!$C$27/Model!K105) -> 15.431548 | L72: =IF(Model!L105<=0,"n.m.",Inputs!$C$27/Model!L105) -> 14.232711 | ... S72: =IF(Model!S105<=0,"n.m.",Inputs!$C$27/Model!S105) -> 8.1647818
B73: P / B | C73: x | E73: =Inputs!$C$27/E61 -> 8.1647114 | F73: =Inputs!$C$27/F61 -> 7.1556721 | G73: =Inputs!$C$27/G61 -> 5.8994197 | H73: =Inputs!$C$27/H61 -> 5.3168581 | I73: =Inputs!$C$27/I61 -> 4.8850575 | J73: =Inputs!$C$27/J61 -> 4.4291633 | K73: =Inputs!$C$27/K61 -> 3.9803478 | L73: =Inputs!$C$27/L61 -> 3.6876522 | ... S73: =Inputs!$C$27/S61 -> 2.947103
B74: FCF yield (FCFE / market cap) | C74: % | F74: =(Model!F125+Model!F94*(1-Inputs!$C$77))/F66 -> 0.022084474 | G74: =(Model!G125+Model!G94*(1-Inputs!$C$77))/G66 -> 0.034241851 | H74: =(Model!H125+Model!H94*(1-Inputs!$C$77))/H66 -> 0.040616008 | I74: =(Model!I125+Model!I94*(1-Inputs!$C$77))/I66 -> 0.046600964 | J74: =(Model!J125+Model!J94*(1-Inputs!$C$77))/J66 -> 0.055798843 | K74: =(Model!K125+Model!K94*(1-Inputs!$C$77))/K66 -> 0.065229894 | L74: =(Model!L125+Model!L94*(1-Drivers!L81))/L66 -> 0.054776707 | M74: =(Model!M125+Model!M94*(1-Drivers!M81))/M66 -> 0.060665039 | N74: =(Model!N125+Model!N94*(1-Drivers!N81))/N66 -> 0.067178623 | O74: =(Model!O125+Model!O94*(1-Drivers!O81))/O66 -> 0.075556617 | P74: =(Model!P125+Model!P94*(1-Drivers!P81))/P66 -> 0.083713608 | Q74: =(Model!Q125+Model!Q94*(1-Drivers!Q81))/Q66 -> 0.091325488 | R74: =(Model!R125+Model!R94*(1-Drivers!R81))/R66 -> 0.098383398 | S74: =(Model!S125+Model!S94*(1-Drivers!S81))/S66 -> 0.10254809
B75: Dividend yield | C75: % | E75: =Model!E107/Inputs!$C$27 -> 0 | F75: =Model!F107/Inputs!$C$27 -> 0 | G75: =Model!G107/Inputs!$C$27 -> 0.020491803 | H75: =Model!H107/Inputs!$C$27 -> 0.028688525 | I75: =Model!I107/Inputs!$C$27 -> 0.03442623 | J75: =Model!J107/Inputs!$C$27 -> 0.039344262 | K75: =Model!K107/Inputs!$C$27 -> 0.044262295 | L75: =Model!L107/Inputs!$C$27 -> 0.045669445 | ... S75: =Model!S107/Inputs!$C$27 -> 0.11022952
B77: Company metrics on peer basis (used by Comps – basis follows the Inputs switch)
B79: Revenue | C79: NOKm | E79: =Model!E67 -> 3790 | F79: =Model!F67 -> 3468 | G79: =Model!G67 -> 3668 | H79: =Model!H67 -> 4262 | I79: =Model!I67 -> 4687 | J79: =Model!J67 -> 5045 | K79: =Model!K67 -> 5433 | L79: =Model!L67 -> 5726.448 | ... S79: =Model!S67 -> 8244.1745
B80: EBITDA (peer basis) | C80: NOKm | E80: =IF(Inputs!$C$67=1,Model!E78,Model!E82) -> 1049.9 | F80: =IF(Inputs!$C$67=1,Model!F78,Model!F82) -> 835.8 | G80: =IF(Inputs!$C$67=1,Model!G78,Model!G82) -> 950 | H80: =IF(Inputs!$C$67=1,Model!H78,Model!H82) -> 1125.2 | I80: =IF(Inputs!$C$67=1,Model!I78,Model!I82) -> 1298.3 | J80: =IF(Inputs!$C$67=1,Model!J78,Model!J82) -> 1453 | K80: =IF(Inputs!$C$67=1,Model!K78,Model!K82) -> 1613.6 | L80: =IF(Inputs!$C$67=1,Model!L78,Model!L82) -> 1701.3324 | ... S80: =IF(Inputs!$C$67=1,Model!S78,Model!S82) -> 2559.6182
B81: EBIT (peer basis, excl. special items) | C81: NOKm | E81: =IF(Inputs!$C$67=1,Model!E85-Model!E95,Model!E85) -> 620.9 | F81: =IF(Inputs!$C$67=1,Model!F85-Model!F95,Model!F85) -> 400.9 | G81: =IF(Inputs!$C$67=1,Model!G85-Model!G95,Model!G85) -> 509.1 | H81: =IF(Inputs!$C$67=1,Model!H85-Model!H95,Model!H85) -> 649.5 | I81: =IF(Inputs!$C$67=1,Model!I85-Model!I95,Model!I85) -> 787.4 | J81: =IF(Inputs!$C$67=1,Model!J85-Model!J95,Model!J85) -> 907.1 | K81: =IF(Inputs!$C$67=1,Model!K85-Model!K95,Model!K85) -> 1035.5 | L81: =IF(Inputs!$C$67=1,Model!L85-Model!L95,Model!L85) -> 1089.5506 | ... S81: =IF(Inputs!$C$67=1,Model!S85-Model!S95,Model!S85) -> 1696.4192
B82: Net profit to shareholders | C82: NOKm | E82: =Model!E100 -> 378.8 | F82: =Model!F100 -> 179.1 | G82: =Model!G100 -> 308.6 | H82: =Model!H100 -> 405.1 | I82: =Model!I100 -> 469.9 | J82: =Model!J100 -> 575.5 | K82: =Model!K100 -> 672 | L82: =Model!L100 -> 729.90128 | ... S82: =Model!S100 -> 1159.6274
B83: EPS | C83: NOK | E83: =Model!E105 -> 4.4564706 | F83: =Model!F105 -> 2.1070588 | G83: =Model!G105 -> 3.6305882 | H83: =Model!H105 -> 4.7658824 | I83: =Model!I105 -> 5.5282353 | J83: =Model!J105 -> 6.7705882 | K83: =Model!K105 -> 7.9058824 | L83: =Model!L105 -> 8.5718035 | ... S83: =Model!S105 -> 14.942224
B84: EBIT margin (peer basis) | C84: % | E84: =E81/E79 -> 0.16382586 | F84: =F81/F79 -> 0.11559977 | G84: =G81/G79 -> 0.13879498 | H84: =H81/H79 -> 0.15239324 | I84: =I81/I79 -> 0.16799659 | J84: =J81/J79 -> 0.17980178 | K84: =K81/K79 -> 0.19059452 | L84: =L81/L79 -> 0.1902664 | ... S84: =S81/S79 -> 0.20577187

Sheet Valuation >>>
D8: =Inputs!$C$6 -> Example Company ASA
D9: Financial Model
D12: Valuation
D14: From cost of capital to target price, cross-checked with peers.
D17: WACC | E17: Cost of capital | F17: CAPM with peer-based beta, cost of debt and target capital structure
D18: DCF | E18: DCF valuation | F18: FCFF, stub period and mid-year discounting, terminal value, equity bridge and target price
D19: Sensitivity | E19: Sensitivity & scenarios | F19: WACC vs. growth, WACC vs. exit multiple, growth vs. margin and Bear/Base/Bull
D20: Comps | E20: Trading multiples | F20: Peer group statistics and implied value per share
D21: Football | E21: Football field | F21: Valuation summary across all methods, with chart
D24: ← Back to cover

Sheet WACC
B1: Cost of capital (WACC) | M1: =Inputs!$C$6&" | Scenario: "&Inputs!$C$53 -> Example Company ASA | Scenario: Base
B2: CAPM with peer-based beta. Only blue cells are inputs.
B4: Cost of equity (CAPM) | G4: Peer beta analysis
G5: Peer | H5: Country | I5: Raw beta | J5: Adj. beta | K5: D/E (mkt) | L5: Tax rate | M5: Unlev. beta
B6: Risk-free rate (10-year Norwegian government bond) | C6: 0.04 | E6: Example value – update to the current 10y yield (Norges Bank) | G6: =Comps!B6 -> Peer A ASA | H6: =Comps!C6 -> NO | I6: 1.05 | J6: =0.67*I6+0.33 -> 1.0335 | K6: 0.28 | L6: 0.22 | M6: =IF($M$17=1,J6,I6)/(1+(1-L6)*K6) -> 0.8482436
B7: Equity risk premium | C7: 0.05 | E7: NFF/PwC Norwegian risk premium survey: typically about 5% | G7: =Comps!B7 -> Peer B AB | H7: =Comps!C7 -> SE | I7: 0.98 | J7: =0.67*I7+0.33 -> 0.9866 | K7: 0.35 | L7: 0.206 | M7: =IF($M$17=1,J7,I7)/(1+(1-L7)*K7) -> 0.77204789
B8: Unlevered beta – peer median | C8: =MEDIAN($M$6:$M$13) -> 0.8220006 | E8: From the peer beta table to the right | G8: =Comps!B8 -> Peer C A/S | H8: =Comps!C8 -> DK | I8: 1.12 | J8: =0.67*I8+0.33 -> 1.0804 | K8: 0.42 | L8: 0.22 | M8: =IF($M$17=1,J8,I8)/(1+(1-L8)*K8) -> 0.81379934
B9: Unlevered beta – override (optional) | E9: Leave blank to use the peer median | G9: =Comps!B9 -> Peer D Oyj | H9: =Comps!C9 -> FI | I9: 1.21 | J9: =0.67*I9+0.33 -> 1.1407 | K9: 0.55 | L9: 0.2 | M9: =IF($M$17=1,J9,I9)/(1+(1-L9)*K9) -> 0.79215278
B10: Unlevered beta used | C10: =IF($C$9="",$C$8,$C$9) -> 0.8220006 | G10: =Comps!B10 -> Peer E AB | H10: =Comps!C10 -> SE | I10: 0.92 | J10: =0.67*I10+0.33 -> 0.9464 | K10: 0.18 | L10: 0.206 | M10: =IF($M$17=1,J10,I10)/(1+(1-L10)*K10) -> 0.82805446
B11: Target debt / equity (D/E) | C11: =$C$29/$C$30 -> 0.11111111 | G11: =Comps!B11 -> Peer F plc | H11: =Comps!C11 -> UK | I11: 1.01 | J11: =0.67*I11+0.33 -> 1.0067 | K11: 0.26 | L11: 0.25 | M11: =IF($M$17=1,J11,I11)/(1+(1-L11)*K11) -> 0.84242678
B12: Tax rate | C12: =Drivers!$H$94 -> 0.22 | G12: =Comps!B12 -> Peer G SE | H12: =Comps!C12 -> DE | I12: 1.08 | J12: =0.67*I12+0.33 -> 1.0536 | K12: 0.38 | L12: 0.3 | M12: =IF($M$17=1,J12,I12)/(1+(1-L12)*K12) -> 0.83222749
B13: Relevered beta = βu x (1 + (1 – t) x D/E) | C13: =$C$10*(1+(1-$C$12)*$C$11) -> 0.89324065 | E13: Hamada formula | G13: =Comps!B13 -> Peer H NV | H13: =Comps!C13 -> NL | I13: 1.15 | J13: =0.67*I13+0.33 -> 1.1005 | K13: 0.47 | L13: 0.258 | M13: =IF($M$17=1,J13,I13)/(1+(1-L13)*K13) -> 0.81594674
B14: Size premium | C14: 0.01 | E14: Optional small/mid-cap premium | G14: Median | I14: =MEDIAN(I6:I13) -> 1.065 | J14: =MEDIAN(J6:J13) -> 1.04355 | K14: =MEDIAN(K6:K13) -> 0.365 | L14: =MEDIAN(L6:L13) -> 0.22 | M14: =MEDIAN(M6:M13) -> 0.8220006
B15: Company-specific risk premium | C15: 0 | E15: Use sparingly – prefer scenarios | G15: Mean | I15: =AVERAGE(I6:I13) -> 1.065 | J15: =AVERAGE(J6:J13) -> 1.04355 | K15: =AVERAGE(K6:K13) -> 0.36125 | L15: =AVERAGE(L6:L13) -> 0.2325 | M15: =AVERAGE(M6:M13) -> 0.81811238
B16: Cost of equity (Ke) | C16: =$C$6+$C$13*$C$7+$C$14+$C$15 -> 0.094662032
G17: Apply Blume adjustment (1 = yes) | M17: 1
B18: Cost of debt | G18: Adjusted beta = 0.67 x raw + 0.33 x 1.0 (Bloomberg convention). Source: example data – replace with 2y weekly betas.
G19: Unlevered beta = beta / (1 + (1 – tax) x D/E)
B20: Credit spread over the risk-free rate | C20: 0.02 | E20: From loan/bond terms, or a synthetic rating based on interest cover
B21: Pre-tax cost of debt (Kd) | C21: =$C$6+$C$20 -> 0.06
B22: After-tax cost of debt | C22: =$C$21*(1-$C$12) -> 0.0468
B24: Capital structure and WACC
B26: Capital structure basis (1 = target, 2 = modelled from the forecast balance sheet) | C26: 1 | E26: 2 = average forecast D/(D+E) with NIBD from the Model and equity at the current market cap
B27: Target D / (D + E) | C27: 0.1 | E27: Long-term target, excl. leases (FCFF is pre-IFRS 16)
B28: Modelled average D / (D + E) over the forecast | C28: =SUMPRODUCT((Model!$L$135:$S$135>0)*Model!$L$135:$S$135/((Model!$L$135:$S$135>0)*Model!$L$135:$S$135+Inputs!$C$32))/8 -> 0.1038066 | E28: Net cash counts as zero debt. Buybacks (Drivers E) keep this close to the target – a gap above 10pp is flagged on Checks
B29: D / (D + E) used | C29: =IF($C$26=2,$C$28,$C$27) -> 0.1
B30: E / (D + E) used | C30: =1-$C$29 -> 0.9
B31: Current market D / (D + E), excl. leases – reference | C31: =Inputs!$C$42/(Inputs!$C$42+Inputs!$C$32) -> 0.089951733
B32: WACC (calculated) | C32: =$C$30*$C$16+$C$29*$C$22 -> 0.089875829
B33: WACC override (optional) | E33: Leave blank to use the calculated WACC
B34: WACC used in the valuation | C34: =IF($C$33="",$C$32,$C$33) -> 0.089875829

Sheet DCF
B1: DCF Valuation | T1: =Inputs!$C$6&" | Scenario: "&Inputs!$C$53 -> Example Company ASA | Scenario: Base
B2: FCFF discounted at WACC with stub period and mid-year convention; terminal value by value-driver Gordon growth.
E3: =Inputs!$C$17+0 -> 2019 | F3: =Inputs!$C$17+1 -> 2020 | G3: =Inputs!$C$17+2 -> 2021 | H3: =Inputs!$C$17+3 -> 2022 | I3: =Inputs!$C$17+4 -> 2023 | J3: =Inputs!$C$17+5 -> 2024 | K3: =Inputs!$C$17+6 -> 2025 | L3: =Inputs!$C$19+0 -> 2026 | M3: =Inputs!$C$19+1 -> 2027 | N3: =Inputs!$C$19+2 -> 2028 | O3: =Inputs!$C$19+3 -> 2029 | P3: =Inputs!$C$19+4 -> 2030 | Q3: =Inputs!$C$19+5 -> 2031 | R3: =Inputs!$C$19+6 -> 2032 | S3: =Inputs!$C$19+7 -> 2033
E4: Historicals | L4: Explicit forecast | T4: Terminal
B5: ="("&Inputs!$C$11&")" -> (NOKm) | E5: =E3&"A" -> 2019A | F5: =F3&"A" -> 2020A | G5: =G3&"A" -> 2021A | H5: =H3&"A" -> 2022A | I5: =I3&"A" -> 2023A | J5: =J3&"A" -> 2024A | K5: =K3&"A" -> 2025A | L5: =L3&"E" -> 2026E | M5: =M3&"E" -> 2027E | N5: =N3&"E" -> 2028E | O5: =O3&"E" -> 2029E | P5: =P3&"E" -> 2030E | Q5: =Q3&"E" -> 2031E | R5: =R3&"E" -> 2032E | S5: =S3&"E" -> 2033E | T5: TV year | V5: Notes
B7: Key assumptions (linked – change them on Inputs, Drivers and WACC)
B9: WACC | E9: =WACC!$C$34 -> 0.089875829
B10: Terminal growth rate | E10: =Drivers!$H$91 -> 0.02
B11: Return on new invested capital (RONIC) | E11: =Drivers!$H$93 -> 0.12
B12: Long-term tax rate | E12: =Drivers!$H$94 -> 0.22
B13: Valuation date | E13: =Inputs!$C$21 -> 46281
B14: Share of first forecast year included (stub) | E14: =Inputs!$C$23 -> 0.29041096
B15: Mid-year discounting | E15: =IF(Inputs!$C$55=1,"On","Off") -> On
B16: Active scenario | E16: =Inputs!$C$53 -> Base
B17: Revenue build | E17: =IF(Inputs!$C$72=2,"Locations: like-for-like + new","Segments: volume x price") -> Locations: like-for-like + new
B18: Growth capex (first forecast year) | E18: =IF(Inputs!$C$72=2,"NOK "&FIXED(Drivers!L79,1)&"m per new location","Sales-to-capital "&FIXED(Drivers!L78,1)&"x") -> NOK 22,0m per new location
B19: Capital structure in the WACC | E19: =IF(WACC!$C$26=1,"Target","Modelled")&" D/(D+E) "&FIXED(WACC!$C$29*100,0)&"%" -> Target D/(D+E) 10%
B21: Free cash flow to firm (FCFF, pre-IFRS 16 – lease payments treated as operating costs)
B23: Total revenue | C23: NOKm | E23: =Model!E67 -> 3790 | F23: =Model!F67 -> 3468 | G23: =Model!G67 -> 3668 | H23: =Model!H67 -> 4262 | I23: =Model!I67 -> 4687 | J23: =Model!J67 -> 5045 | K23: =Model!K67 -> 5433 | L23: =Model!L67 -> 5726.448 | ... S23: =Model!S67 -> 8244.1745 | T23: =S23*(1+$E$52) -> 8409.058
B24: Revenue growth | C24: % | F24: =F23/E23-1 -> -0.084960422 | G24: =G23/F23-1 -> 0.057670127 | H24: =H23/G23-1 -> 0.16194111 | I24: =I23/H23-1 -> 0.099718442 | J24: =J23/I23-1 -> 0.076381481 | K24: =K23/J23-1 -> 0.07690783 | L24: =L23/K23-1 -> 0.05401214 | M24: =M23/L23-1 -> 0.062411248 | ... T24: =T23/S23-1 -> 0.02
B25: EBITDAaL | C25: NOKm | E25: =Model!E82 -> 731.5 | F25: =Model!F82 -> 513.3 | G25: =Model!G82 -> 623.5 | H25: =Model!H82 -> 775.7 | I25: =Model!I82 -> 923.3 | J25: =Model!J82 -> 1054.4 | K25: =Model!K82 -> 1189.8 | L25: =Model!L82 -> 1251.5598 | ... S25: =Model!S82 -> 1934.0491
B26: EBITDAaL margin | C26: % | E26: =E25/E23 -> 0.19300792 | F26: =F25/F23 -> 0.14801038 | G26: =G25/G23 -> 0.16998364 | H26: =H25/H23 -> 0.18200375 | I26: =I25/I23 -> 0.19699168 | J26: =J25/J23 -> 0.20899901 | K26: =K25/K23 -> 0.21899503 | L26: =L25/L23 -> 0.21855779 | ... S26: =S25/S23 -> 0.23459585
B27: D&A – owned assets | C27: NOKm | E27: =Model!E84 -> -174.3 | F27: =Model!F84 -> -176.9 | G27: =Model!G84 -> -179.7 | H27: =Model!H84 -> -196.1 | I27: =Model!I84 -> -210.9 | J27: =Model!J84 -> -227 | K27: =Model!K84 -> -239.1 | L27: =Model!L84 -> -251.96371 | ... S27: =Model!S84 -> -362.74368
B28: EBIT adj. (pre-IFRS 16) | C28: NOKm | E28: =Model!E85 -> 557.2 | F28: =Model!F85 -> 336.4 | G28: =Model!G85 -> 443.8 | H28: =Model!H85 -> 579.6 | I28: =Model!I85 -> 712.4 | J28: =Model!J85 -> 827.4 | K28: =Model!K85 -> 950.7 | L28: =Model!L85 -> 999.5961 | ... S28: =Model!S85 -> 1571.3054 | T28: =T23*T29 -> 1602.7315
B29: EBIT adj. margin | C29: % | E29: =E28/E23 -> 0.14701847 | F29: =F28/F23 -> 0.097001153 | G29: =G28/G23 -> 0.12099237 | H29: =H28/H23 -> 0.13599249 | I29: =I28/I23 -> 0.15199488 | J29: =J28/J23 -> 0.16400396 | K29: =K28/K23 -> 0.1749862 | L29: =L28/L23 -> 0.17455779 | ... S29: =S28/S23 -> 0.19059585 | T29: =Drivers!$H$92 -> 0.19059585
B30: Taxes on EBIT | C30: NOKm | E30: =-E28*Inputs!$C$77 -> -122.584 | F30: =-F28*Inputs!$C$77 -> -74.008 | G30: =-G28*Inputs!$C$77 -> -97.636 | H30: =-H28*Inputs!$C$77 -> -127.512 | I30: =-I28*Inputs!$C$77 -> -156.728 | J30: =-J28*Inputs!$C$77 -> -182.028 | K30: =-K28*Inputs!$C$77 -> -209.154 | L30: =-L28*Drivers!L81 -> -219.91114 | M30: =-M28*Drivers!M81 -> -236.53986 | N30: =-N28*Drivers!N81 -> -256.89468 | O30: =-O28*Drivers!O81 -> -277.44695 | P30: =-P28*Drivers!P81 -> -297.29935 | Q30: =-Q28*Drivers!Q81 -> -315.35995 | R30: =-R28*Drivers!R81 -> -331.39257 | S30: =-S28*Drivers!S81 -> -345.68719 | T30: =-T28*Drivers!$H$94 -> -352.60094
B31: NOPAT | C31: NOKm | E31: =E28+E30 -> 434.616 | F31: =F28+F30 -> 262.392 | G31: =G28+G30 -> 346.164 | H31: =H28+H30 -> 452.088 | I31: =I28+I30 -> 555.672 | J31: =J28+J30 -> 645.372 | K31: =K28+K30 -> 741.546 | L31: =L28+L30 -> 779.68496 | ... T31: =T28+T30 -> 1250.1306
B32: Add back: D&A | C32: NOKm | E32: =-E27 -> 174.3 | F32: =-F27 -> 176.9 | G32: =-G27 -> 179.7 | H32: =-H27 -> 196.1 | I32: =-I27 -> 210.9 | J32: =-J27 -> 227 | K32: =-K27 -> 239.1 | L32: =-L27 -> 251.96371 | ... S32: =-S27 -> 362.74368
B33: Less: capital expenditure | C33: NOKm | E33: =Model!E116 -> -197.1 | F33: =Model!F116 -> -124.8 | G33: =Model!G116 -> -161.4 | H33: =Model!H116 -> -238.7 | I33: =Model!I116 -> -253.1 | J33: =Model!J116 -> -257.3 | K33: =Model!K116 -> -271.7 | L33: =Model!L116 -> -440.3224 | ... S33: =Model!S116 -> -490.50873
B34: Less: increase in net working capital | C34: NOKm | F34: =-Model!F113 -> -47.1 | G34: =-Model!G113 -> 25.1 | H34: =-Model!H113 -> 54.6 | I34: =-Model!I113 -> 35.3 | J34: =-Model!J113 -> 27.6 | K34: =-Model!K113 -> 30.2 | L34: =-Model!L113 -> 19.119117 | M34: =-Model!M113 -> 23.230659 | ... S34: =-Model!S113 -> 19.847874
B35: Unlevered free cash flow (FCFF) | C35: NOKm | F35: =F31+F32+F33+F34 -> 267.392 | G35: =G31+G32+G33+G34 -> 389.564 | H35: =H31+H32+H33+H34 -> 464.088 | I35: =I31+I32+I33+I34 -> 548.772 | J35: =J31+J32+J33+J34 -> 642.672 | K35: =K31+K32+K33+K34 -> 739.146 | L35: =L31+L32+L33+L34 -> 610.44539 | M35: =M31+M32+M33+M34 -> 667.16891 | ... S35: =S31+S32+S33+S34 -> 1117.7011 | T35: =$E$59 -> 1041.7755 | V35: TY column: normalised terminal-year FCFF (see terminal value)
B36: FCFF growth | C36: % | G36: =IF(F35<=0,"n.m.",G35/F35-1) -> 0.45690223 | H36: =IF(G35<=0,"n.m.",H35/G35-1) -> 0.19130104 | I36: =IF(H35<=0,"n.m.",I35/H35-1) -> 0.18247401 | J36: =IF(I35<=0,"n.m.",J35/I35-1) -> 0.17110931 | K36: =IF(J35<=0,"n.m.",K35/J35-1) -> 0.1501139 | L36: =IF(K35<=0,"n.m.",L35/K35-1) -> -0.17412069 | M36: =IF(L35<=0,"n.m.",M35/L35-1) -> 0.092921525 | N36: =IF(M35<=0,"n.m.",N35/M35-1) -> 0.10305092 | ... S36: =IF(R35<=0,"n.m.",S35/R35-1) -> 0.042667862
B37: Cash conversion (FCFF / EBITDAaL) | C37: % | F37: =IF(F25=0,0,F35/F25) -> 0.52092733 | G37: =IF(G25=0,0,G35/G25) -> 0.62480192 | H37: =IF(H25=0,0,H35/H25) -> 0.59828284 | I37: =IF(I25=0,0,I35/I25) -> 0.59435936 | J37: =IF(J25=0,0,J35/J25) -> 0.60951442 | K37: =IF(K25=0,0,K35/K25) -> 0.6212355 | L37: =IF(L25=0,0,L35/L25) -> 0.48774768 | M37: =IF(M25=0,0,M35/M25) -> 0.49682306 | ... S37: =IF(S25=0,0,S35/S25) -> 0.57790728
B38: Reinvestment rate (1 – FCFF / NOPAT) | C38: % | F38: =IF(F31=0,0,1-F35/F31) -> -0.019055459 | G38: =IF(G31=0,0,1-G35/G31) -> -0.1253741 | H38: =IF(H31=0,0,1-H35/H31) -> -0.026543505 | I38: =IF(I31=0,0,1-I35/I31) -> 0.012417397 | J38: =IF(J31=0,0,1-J35/J31) -> 0.0041836336 | K38: =IF(K31=0,0,1-K35/K31) -> 0.0032364816 | L38: =IF(L31=0,0,1-L35/L31) -> 0.21706148 | M38: =IF(M31=0,0,1-M35/M31) -> 0.20446453 | ... S38: =IF(S31=0,0,1-S35/S31) -> 0.088051214 | T38: =1-T35/T31 -> 0.16666667
B39: ROIC | C39: % | F39: =Model!F122 -> 0.099281849 | G39: =Model!G122 -> 0.13218925 | H39: =Model!H122 -> 0.15114945 | I39: =Model!I122 -> 0.16399002 | J39: =Model!J122 -> 0.17836578 | K39: =Model!K122 -> 0.1928197 | L39: =Model!L122 -> 0.19831138 | M39: =Model!M122 -> 0.20444814 | ... S39: =Model!S122 -> 0.24812161
B41: Discounting (valuation date and stub period from Inputs)
B43: Forecast year number | C43: # | L43: =COLUMN()-COLUMN($L$1)+1 -> 1 | M43: =COLUMN()-COLUMN($L$1)+1 -> 2 | N43: =COLUMN()-COLUMN($L$1)+1 -> 3 | O43: =COLUMN()-COLUMN($L$1)+1 -> 4 | P43: =COLUMN()-COLUMN($L$1)+1 -> 5 | Q43: =COLUMN()-COLUMN($L$1)+1 -> 6 | R43: =COLUMN()-COLUMN($L$1)+1 -> 7 | S43: =COLUMN()-COLUMN($L$1)+1 -> 8
B44: Share of year included (stub) | C44: % | L44: =IF(L43=1,Inputs!$C$23,1) -> 0.29041096 | M44: =IF(M43=1,Inputs!$C$23,1) -> 1 | N44: =IF(N43=1,Inputs!$C$23,1) -> 1 | O44: =IF(O43=1,Inputs!$C$23,1) -> 1 | P44: =IF(P43=1,Inputs!$C$23,1) -> 1 | Q44: =IF(Q43=1,Inputs!$C$23,1) -> 1 | R44: =IF(R43=1,Inputs!$C$23,1) -> 1 | S44: =IF(S43=1,Inputs!$C$23,1) -> 1
B45: FCFF included in valuation | C45: NOKm | L45: =L35*L44 -> 177.28003 | M45: =M35*M44 -> 667.16891 | N45: =N35*N44 -> 735.92128 | O45: =O35*O44 -> 826.01594 | P45: =P35*P44 -> 913.84721 | Q45: =Q35*Q44 -> 995.91358 | R45: =R35*R44 -> 1071.9627 | S45: =S35*S44 -> 1117.7011
B46: Discount period (years) | C46: yrs | L46: =IF(Inputs!$C$55=1,IF(L43=1,Inputs!$C$23/2,Inputs!$C$23+L43-1.5),Inputs!$C$23+L43-1) -> 0.14520548 | M46: =IF(Inputs!$C$55=1,IF(M43=1,Inputs!$C$23/2,Inputs!$C$23+M43-1.5),Inputs!$C$23+M43-1) -> 0.79041096 | N46: =IF(Inputs!$C$55=1,IF(N43=1,Inputs!$C$23/2,Inputs!$C$23+N43-1.5),Inputs!$C$23+N43-1) -> 1.790411 | O46: =IF(Inputs!$C$55=1,IF(O43=1,Inputs!$C$23/2,Inputs!$C$23+O43-1.5),Inputs!$C$23+O43-1) -> 2.790411 | P46: =IF(Inputs!$C$55=1,IF(P43=1,Inputs!$C$23/2,Inputs!$C$23+P43-1.5),Inputs!$C$23+P43-1) -> 3.790411 | Q46: =IF(Inputs!$C$55=1,IF(Q43=1,Inputs!$C$23/2,Inputs!$C$23+Q43-1.5),Inputs!$C$23+Q43-1) -> 4.790411 | R46: =IF(Inputs!$C$55=1,IF(R43=1,Inputs!$C$23/2,Inputs!$C$23+R43-1.5),Inputs!$C$23+R43-1) -> 5.790411 | S46: =IF(Inputs!$C$55=1,IF(S43=1,Inputs!$C$23/2,Inputs!$C$23+S43-1.5),Inputs!$C$23+S43-1) -> 6.790411
B47: Discount factor | L47: =1/(1+WACC!$C$34)^L46 -> 0.98758083 | M47: =1/(1+WACC!$C$34)^M46 -> 0.93423642 | N47: =1/(1+WACC!$C$34)^N46 -> 0.85719528 | O47: =1/(1+WACC!$C$34)^O46 -> 0.78650729 | P47: =1/(1+WACC!$C$34)^P46 -> 0.72164853 | Q47: =1/(1+WACC!$C$34)^Q46 -> 0.6621383 | R47: =1/(1+WACC!$C$34)^R46 -> 0.60753554 | S47: =1/(1+WACC!$C$34)^S46 -> 0.55743556
B48: Present value of FCFF | C48: NOKm | L48: =L45*L47 -> 175.07836 | M48: =M45*M47 -> 623.29349 | N48: =N45*N47 -> 630.82825 | O48: =O45*O47 -> 649.66756 | P48: =P45*P47 -> 659.47649 | Q48: =Q45*Q47 -> 659.43252 | R48: =R45*R47 -> 651.25544 | S48: =S45*S47 -> 623.04631
B50: Terminal value
B52: Terminal growth rate (g) | E52: =Drivers!$H$91 -> 0.02
B53: WACC | E53: =WACC!$C$34 -> 0.089875829
B54: Terminal-year NOPAT (final-year revenue x (1+g) x terminal margin x (1-t)) | E54: =$T$31 -> 1250.1306
B55: Return on new invested capital (RONIC) | E55: =Drivers!$H$93 -> 0.12
B56: Net reinvestment (NOPAT x g / RONIC) | E56: =-$E$54*$E$52/$E$55 -> -208.3551
B57: Terminal FCFF – value driver method | E57: =$E$54+$E$56 -> 1041.7755
B58: Terminal FCFF – final-year FCFF x (1+g) | E58: =$S$35*(1+$E$52) -> 1140.0551
B59: Terminal FCFF used | E59: =IF(Inputs!$C$58=1,$E$57,$E$58) -> 1041.7755
B60: Terminal value – Gordon growth (end of final year) | E60: =$E$59/($E$53-$E$52) -> 14908.954 | G60: TV = FCFF(TY) / (WACC – g)
B61: Exit multiple (EV / EBITDAaL) | E61: =Drivers!$H$95 -> 8.5
B62: Terminal value – exit multiple (end of final year) | E62: =$S$25*$E$61 -> 16439.417
B63: Discount factor – Gordon TV (same timing as final-year FCFF) | E63: =$S$47 -> 0.55743556 | G63: With mid-year convention the Gordon TV is discounted half a year less
B64: Discount factor – exit-multiple TV (end of final year) | E64: =1/(1+$E$53)^(Inputs!$C$23+$S$43-1) -> 0.53395684
B65: PV of terminal value – Gordon growth | E65: =$E$60*$E$63 -> 8310.7808
B66: PV of terminal value – exit multiple | E66: =$E$62*$E$64 -> 8777.9394
B67: PV of terminal value – weighted (weights on Inputs) | E67: =Inputs!$C$56*$E$65+Inputs!$C$57*$E$66 -> 8310.7808
B69: Enterprise value to equity value
B71: Sum of PV of FCFF (explicit forecast) | E71: =SUM($L$48:$S$48) -> 4672.0784
B72: PV of terminal value | E72: =$E$67 -> 8310.7808
B73: Enterprise value (DCF) | E73: =$E$71+$E$72 -> 12982.859
B74: Terminal value in % of EV | E74: =$E$72/$E$73 -> 0.64013486
B75: Less: net interest-bearing debt excl. leases | E75: =-Inputs!$C$42 -> -1025
B76: Less: minority interests | E76: =-Inputs!$C$44 -> -70
B77: Add: associates and financial investments | E77: =Inputs!$C$45 -> 40
B78: Less: pension deficit and other debt-like items | E78: =-Inputs!$C$46 -> -20
B79: Add: other adjustments | E79: =Inputs!$C$47 -> 0
B80: Equity value | E80: =$E$73+SUM($E$75:$E$79) -> 11907.859
B81: Memo: lease liabilities – not deducted, FCFF is already after lease payments | E81: =Inputs!$C$43 -> 1805
B82: Diluted shares (m) | E82: =Inputs!$C$31 -> 85.6
B83: DCF value per share (NOK) | E83: =$E$80/$E$82 -> 139.11051
B84: Current share price (NOK) | E84: =Inputs!$C$27 -> 122
B85: Upside / (downside) to DCF value | E85: =$E$83/$E$84-1 -> 0.14025004
B87: Sanity checks
B89: Implied EV / EBITDAaL – first forecast year | E89: =$E$73/$L$25 -> 10.373343
B90: Implied EV / EBITDAaL – second forecast year | E90: =$E$73/$M$25 -> 9.6679924
B91: Implied exit multiple from Gordon TV (EV / EBITDAaL) | E91: =$E$60/$S$25 -> 7.7086738 | G91: Compare with peer EV/EBITDA and the company's own trading history
B92: Implied perpetual growth from exit-multiple TV | E92: =($E$62*$E$53-$S$35)/($E$62+$S$35) -> 0.020493409
B93: Terminal-year ROIC (NOPAT / final-year invested capital) | E93: =$E$54/Model!$S$119 -> 0.2503493
B94: Return on new capital, explicit period (ΔNOPAT / cumulative net reinvestment) | E94: =IF(SUM(Model!$L$123:$R$123)<=0,9.99,($S$31-$L$31)/SUM(Model!$L$123:$R$123)) -> 0.42934832 | G94: Shown as 999% if revenue grows without net investment
B95: Benchmark: the higher of ROIC in the last actual year and the terminal RONIC | E95: =MAX($E$55,Model!$K$122) -> 0.1928197 | G95: Explicit-period returns are judged against what the company earns today, not only the long-run fade
B96: … relative to the benchmark (x) – tolerance on Inputs | E96: =$E$94/$E$95 -> 2.2266829 | G96: Price increases on existing locations need no capital; far above the tolerance means growth is almost free
B97: RONIC minus WACC | E97: =$E$55-$E$53 -> 0.030124171 | G97: Positive = growth creates value in the terminal period
B98: WACC minus terminal growth | E98: =$E$53-$E$52 -> 0.069875829
B100: Target price and recommendation
B102: DCF value per share (NOK) | E102: =$E$83 -> 139.11051 | F102: =Inputs!$C$59 -> 0.7 | G102: weight
B103: Peer multiples value per share (NOK) | E103: =Comps!$H$33 -> 135.89853 | F103: =Inputs!$C$60 -> 0.3 | G103: weight
B104: Blended fair value per share (NOK) | E104: =$E$102*Inputs!$C$59+$E$103*Inputs!$C$60 -> 138.14691
B105: Cost of equity | E105: =WACC!$C$16 -> 0.094662032
B106: Roll-forward factor (12 months) | E106: =IF(Inputs!$C$61=1,1+$E$105,1) -> 1.094662
B107: Less: expected dividend next 12 months (NOK) | E107: =IF(Inputs!$C$61=1,Model!$L$107,0) -> 5.5716723
B108: 12-month target price, unrounded (NOK) | E108: =$E$104*$E$106-$E$107 -> 145.65251
B109: Target price (NOK) | E109: =ROUND($E$108/Inputs!$C$62,0)*Inputs!$C$62 -> 146
B110: Upside / (downside) to target price | E110: =$E$109/$E$84-1 -> 0.19672131
B111: Expected dividend yield (next 12 months) | E111: =Model!$L$107/$E$84 -> 0.045669445
B112: Expected total return | E112: =$E$110+$E$111 -> 0.24239076
B113: Excess return: expected total return minus cost of equity | E113: =$E$112-$E$105 -> 0.14772872 | G113: A fairly priced share returns its cost of equity – only the excess justifies a rating
B114: Recommendation | E114: =IF($E$113>=Inputs!$C$63,"BUY",IF($E$113<=Inputs!$C$64,"SELL","HOLD")) -> BUY

Sheet Sensitivity
B1: Sensitivity & scenario analysis | N1: =Inputs!$C$6&" | Scenario: "&Inputs!$C$53 -> Example Company ASA | Scenario: Base
B2: Tables 1-2 are live formulas. Tables 3-4 are Excel data tables (Data > What-If Analysis).
B3: Data-table input cells – must stay BLANK (Excel substitutes values here when tables recalculate)
B4: Scenario override (1-3) | F4: Do not type in the grey cells – they feed the data tables in sections 3 and 4.
B5: Revenue growth adjustment (pp p.a.)
B6: EBITDA margin adjustment (pp)
B8: 1. DCF value per share (NOK) – WACC vs. terminal growth
B9: WACC step | C9: 0.005
B10: Terminal growth step | C10: 0.0025
C12: g \ WACC | D12: =WACC!$C$34+(0-3)*$C$9 -> 0.074875829 | E12: =WACC!$C$34+(1-3)*$C$9 -> 0.079875829 | F12: =WACC!$C$34+(2-3)*$C$9 -> 0.084875829 | G12: =WACC!$C$34+(3-3)*$C$9 -> 0.089875829 | H12: =WACC!$C$34+(4-3)*$C$9 -> 0.094875829 | I12: =WACC!$C$34+(5-3)*$C$9 -> 0.099875829 | J12: =WACC!$C$34+(6-3)*$C$9 -> 0.10487583 | L12: Centre cell = model value (checked on the Checks sheet)
C13: =Drivers!$H$91+(0-2)*$C$10 -> 0.015 | D13: =(SUMPRODUCT(DCF!$L$45:$S$45,(1+D$12)^(-DCF!$L$46:$S$46))+Inputs!$C$56*IF(Inputs!$C$58=1,DCF!$S$23*(1+$C13)*DCF!$T$29*(1-Drivers!$H$94)*(1-$C13/Drivers!$H$93),DCF!$S$35*(1+$C13))/(D$12-$C13)*(1+D$12)^(-DCF!$S$46)+Inputs!$C$57*DCF!$S$25*Drivers!$H$95*(1+D$12)^(-(Inputs!$C$23+DCF!$S$43-1))+SUM(DCF!$E$75:$E$79))/Inputs!$C$31 -> 174.95623 | E13: =(SUMPRODUCT(DCF!$L$45:$S$45,(1+E$12)^(-DCF!$L$46:$S$46))+Inputs!$C$56*IF(Inputs!$C$58=1,DCF!$S$23*(1+$C13)*DCF!$T$29*(1-Drivers!$H$94)*(1-$C13/Drivers!$H$93),DCF!$S$35*(1+$C13))/(E$12-$C13)*(1+E$12)^(-DCF!$S$46)+Inputs!$C$57*DCF!$S$25*Drivers!$H$95*(1+E$12)^(-(Inputs!$C$23+DCF!$S$43-1))+SUM(DCF!$E$75:$E$79))/Inputs!$C$31 -> 160.22628 | F13: =(SUMPRODUCT(DCF!$L$45:$S$45,(1+F$12)^(-DCF!$L$46:$S$46))+Inputs!$C$56*IF(Inputs!$C$58=1,DCF!$S$23*(1+$C13)*DCF!$T$29*(1-Drivers!$H$94)*(1-$C13/Drivers!$H$93),DCF!$S$35*(1+$C13))/(F$12-$C13)*(1+F$12)^(-DCF!$S$46)+Inputs!$C$57*DCF!$S$25*Drivers!$H$95*(1+F$12)^(-(Inputs!$C$23+DCF!$S$43-1))+SUM(DCF!$E$75:$E$79))/Inputs!$C$31 -> 147.61262 | G13: =(SUMPRODUCT(DCF!$L$45:$S$45,(1+G$12)^(-DCF!$L$46:$S$46))+Inputs!$C$56*IF(Inputs!$C$58=1,DCF!$S$23*(1+$C13)*DCF!$T$29*(1-Drivers!$H$94)*(1-$C13/Drivers!$H$93),DCF!$S$35*(1+$C13))/(G$12-$C13)*(1+G$12)^(-DCF!$S$46)+Inputs!$C$57*DCF!$S$25*Drivers!$H$95*(1+G$12)^(-(Inputs!$C$23+DCF!$S$43-1))+SUM(DCF!$E$75:$E$79))/Inputs!$C$31 -> 136.69111 | H13: =(SUMPRODUCT(DCF!$L$45:$S$45,(1+H$12)^(-DCF!$L$46:$S$46))+Inputs!$C$56*IF(Inputs!$C$58=1,DCF!$S$23*(1+$C13)*DCF!$T$29*(1-Drivers!$H$94)*(1-$C13/Drivers!$H$93),DCF!$S$35*(1+$C13))/(H$12-$C13)*(1+H$12)^(-DCF!$S$46)+Inputs!$C$57*DCF!$S$25*Drivers!$H$95*(1+H$12)^(-(Inputs!$C$23+DCF!$S$43-1))+SUM(DCF!$E$75:$E$79))/Inputs!$C$31 -> 127.14384 | I13: =(SUMPRODUCT(DCF!$L$45:$S$45,(1+I$12)^(-DCF!$L$46:$S$46))+Inputs!$C$56*IF(Inputs!$C$58=1,DCF!$S$23*(1+$C13)*DCF!$T$29*(1-Drivers!$H$94)*(1-$C13/Drivers!$H$93),DCF!$S$35*(1+$C13))/(I$12-$C13)*(1+I$12)^(-DCF!$S$46)+Inputs!$C$57*DCF!$S$25*Drivers!$H$95*(1+I$12)^(-(Inputs!$C$23+DCF!$S$43-1))+SUM(DCF!$E$75:$E$79))/Inputs!$C$31 -> 118.7278 | J13: =(SUMPRODUCT(DCF!$L$45:$S$45,(1+J$12)^(-DCF!$L$46:$S$46))+Inputs!$C$56*IF(Inputs!$C$58=1,DCF!$S$23*(1+$C13)*DCF!$T$29*(1-Drivers!$H$94)*(1-$C13/Drivers!$H$93),DCF!$S$35*(1+$C13))/(J$12-$C13)*(1+J$12)^(-DCF!$S$46)+Inputs!$C$57*DCF!$S$25*Drivers!$H$95*(1+J$12)^(-(Inputs!$C$23+DCF!$S$43-1))+SUM(DCF!$E$75:$E$79))/Inputs!$C$31 -> 111.25406
C14: =Drivers!$H$91+(1-2)*$C$10 -> 0.0175 | D14: =(SUMPRODUCT(DCF!$L$45:$S$45,(1+D$12)^(-DCF!$L$46:$S$46))+Inputs!$C$56*IF(Inputs!$C$58=1,DCF!$S$23*(1+$C14)*DCF!$T$29*(1-Drivers!$H$94)*(1-$C14/Drivers!$H$93),DCF!$S$35*(1+$C14))/(D$12-$C14)*(1+D$12)^(-DCF!$S$46)+Inputs!$C$57*DCF!$S$25*Drivers!$H$95*(1+D$12)^(-(Inputs!$C$23+DCF!$S$43-1))+SUM(DCF!$E$75:$E$79))/Inputs!$C$31 -> 177.71815 | E14: =(SUMPRODUCT(DCF!$L$45:$S$45,(1+E$12)^(-DCF!$L$46:$S$46))+Inputs!$C$56*IF(Inputs!$C$58=1,DCF!$S$23*(1+$C14)*DCF!$T$29*(1-Drivers!$H$94)*(1-$C14/Drivers!$H$93),DCF!$S$35*(1+$C14))/(E$12-$C14)*(1+E$12)^(-DCF!$S$46)+Inputs!$C$57*DCF!$S$25*Drivers!$H$95*(1+E$12)^(-(Inputs!$C$23+DCF!$S$43-1))+SUM(DCF!$E$75:$E$79))/Inputs!$C$31 -> 162.29869 | F14: =(SUMPRODUCT(DCF!$L$45:$S$45,(1+F$12)^(-DCF!$L$46:$S$46))+Inputs!$C$56*IF(Inputs!$C$58=1,DCF!$S$23*(1+$C14)*DCF!$T$29*(1-Drivers!$H$94)*(1-$C14/Drivers!$H$93),DCF!$S$35*(1+$C14))/(F$12-$C14)*(1+F$12)^(-DCF!$S$46)+Inputs!$C$57*DCF!$S$25*Drivers!$H$95*(1+F$12)^(-(Inputs!$C$23+DCF!$S$43-1))+SUM(DCF!$E$75:$E$79))/Inputs!$C$31 -> 149.17268 | G14: =(SUMPRODUCT(DCF!$L$45:$S$45,(1+G$12)^(-DCF!$L$46:$S$46))+Inputs!$C$56*IF(Inputs!$C$58=1,DCF!$S$23*(1+$C14)*DCF!$T$29*(1-Drivers!$H$94)*(1-$C14/Drivers!$H$93),DCF!$S$35*(1+$C14))/(G$12-$C14)*(1+G$12)^(-DCF!$S$46)+Inputs!$C$57*DCF!$S$25*Drivers!$H$95*(1+G$12)^(-(Inputs!$C$23+DCF!$S$43-1))+SUM(DCF!$E$75:$E$79))/Inputs!$C$31 -> 137.86477 | H14: =(SUMPRODUCT(DCF!$L$45:$S$45,(1+H$12)^(-DCF!$L$46:$S$46))+Inputs!$C$56*IF(Inputs!$C$58=1,DCF!$S$23*(1+$C14)*DCF!$T$29*(1-Drivers!$H$94)*(1-$C14/Drivers!$H$93),DCF!$S$35*(1+$C14))/(H$12-$C14)*(1+H$12)^(-DCF!$S$46)+Inputs!$C$57*DCF!$S$25*Drivers!$H$95*(1+H$12)^(-(Inputs!$C$23+DCF!$S$43-1))+SUM(DCF!$E$75:$E$79))/Inputs!$C$31 -> 128.02245 | I14: =(SUMPRODUCT(DCF!$L$45:$S$45,(1+I$12)^(-DCF!$L$46:$S$46))+Inputs!$C$56*IF(Inputs!$C$58=1,DCF!$S$23*(1+$C14)*DCF!$T$29*(1-Drivers!$H$94)*(1-$C14/Drivers!$H$93),DCF!$S$35*(1+$C14))/(I$12-$C14)*(1+I$12)^(-DCF!$S$46)+Inputs!$C$57*DCF!$S$25*Drivers!$H$95*(1+I$12)^(-(Inputs!$C$23+DCF!$S$43-1))+SUM(DCF!$E$75:$E$79))/Inputs!$C$31 -> 119.37882 | J14: =(SUMPRODUCT(DCF!$L$45:$S$45,(1+J$12)^(-DCF!$L$46:$S$46))+Inputs!$C$56*IF(Inputs!$C$58=1,DCF!$S$23*(1+$C14)*DCF!$T$29*(1-Drivers!$H$94)*(1-$C14/Drivers!$H$93),DCF!$S$35*(1+$C14))/(J$12-$C14)*(1+J$12)^(-DCF!$S$46)+Inputs!$C$57*DCF!$S$25*Drivers!$H$95*(1+J$12)^(-(Inputs!$C$23+DCF!$S$43-1))+SUM(DCF!$E$75:$E$79))/Inputs!$C$31 -> 111.72806
C15: =Drivers!$H$91+(2-2)*$C$10 -> 0.02 | D15: =(SUMPRODUCT(DCF!$L$45:$S$45,(1+D$12)^(-DCF!$L$46:$S$46))+Inputs!$C$56*IF(Inputs!$C$58=1,DCF!$S$23*(1+$C15)*DCF!$T$29*(1-Drivers!$H$94)*(1-$C15/Drivers!$H$93),DCF!$S$35*(1+$C15))/(D$12-$C15)*(1+D$12)^(-DCF!$S$46)+Inputs!$C$57*DCF!$S$25*Drivers!$H$95*(1+D$12)^(-(Inputs!$C$23+DCF!$S$43-1))+SUM(DCF!$E$75:$E$79))/Inputs!$C$31 -> 180.71508 | E15: =(SUMPRODUCT(DCF!$L$45:$S$45,(1+E$12)^(-DCF!$L$46:$S$46))+Inputs!$C$56*IF(Inputs!$C$58=1,DCF!$S$23*(1+$C15)*DCF!$T$29*(1-Drivers!$H$94)*(1-$C15/Drivers!$H$93),DCF!$S$35*(1+$C15))/(E$12-$C15)*(1+E$12)^(-DCF!$S$46)+Inputs!$C$57*DCF!$S$25*Drivers!$H$95*(1+E$12)^(-(Inputs!$C$23+DCF!$S$43-1))+SUM(DCF!$E$75:$E$79))/Inputs!$C$31 -> 164.52938 | F15: =(SUMPRODUCT(DCF!$L$45:$S$45,(1+F$12)^(-DCF!$L$46:$S$46))+Inputs!$C$56*IF(Inputs!$C$58=1,DCF!$S$23*(1+$C15)*DCF!$T$29*(1-Drivers!$H$94)*(1-$C15/Drivers!$H$93),DCF!$S$35*(1+$C15))/(F$12-$C15)*(1+F$12)^(-DCF!$S$46)+Inputs!$C$57*DCF!$S$25*Drivers!$H$95*(1+F$12)^(-(Inputs!$C$23+DCF!$S$43-1))+SUM(DCF!$E$75:$E$79))/Inputs!$C$31 -> 150.83976 | G15: =(SUMPRODUCT(DCF!$L$45:$S$45,(1+G$12)^(-DCF!$L$46:$S$46))+Inputs!$C$56*IF(Inputs!$C$58=1,DCF!$S$23*(1+$C15)*DCF!$T$29*(1-Drivers!$H$94)*(1-$C15/Drivers!$H$93),DCF!$S$35*(1+$C15))/(G$12-$C15)*(1+G$12)^(-DCF!$S$46)+Inputs!$C$57*DCF!$S$25*Drivers!$H$95*(1+G$12)^(-(Inputs!$C$23+DCF!$S$43-1))+SUM(DCF!$E$75:$E$79))/Inputs!$C$31 -> 139.11051 | H15: =(SUMPRODUCT(DCF!$L$45:$S$45,(1+H$12)^(-DCF!$L$46:$S$46))+Inputs!$C$56*IF(Inputs!$C$58=1,DCF!$S$23*(1+$C15)*DCF!$T$29*(1-Drivers!$H$94)*(1-$C15/Drivers!$H$93),DCF!$S$35*(1+$C15))/(H$12-$C15)*(1+H$12)^(-DCF!$S$46)+Inputs!$C$57*DCF!$S$25*Drivers!$H$95*(1+H$12)^(-(Inputs!$C$23+DCF!$S$43-1))+SUM(DCF!$E$75:$E$79))/Inputs!$C$31 -> 128.94897 | I15: =(SUMPRODUCT(DCF!$L$45:$S$45,(1+I$12)^(-DCF!$L$46:$S$46))+Inputs!$C$56*IF(Inputs!$C$58=1,DCF!$S$23*(1+$C15)*DCF!$T$29*(1-Drivers!$H$94)*(1-$C15/Drivers!$H$93),DCF!$S$35*(1+$C15))/(I$12-$C15)*(1+I$12)^(-DCF!$S$46)+Inputs!$C$57*DCF!$S$25*Drivers!$H$95*(1+I$12)^(-(Inputs!$C$23+DCF!$S$43-1))+SUM(DCF!$E$75:$E$79))/Inputs!$C$31 -> 120.06081 | J15: =(SUMPRODUCT(DCF!$L$45:$S$45,(1+J$12)^(-DCF!$L$46:$S$46))+Inputs!$C$56*IF(Inputs!$C$58=1,DCF!$S$23*(1+$C15)*DCF!$T$29*(1-Drivers!$H$94)*(1-$C15/Drivers!$H$93),DCF!$S$35*(1+$C15))/(J$12-$C15)*(1+J$12)^(-DCF!$S$46)+Inputs!$C$57*DCF!$S$25*Drivers!$H$95*(1+J$12)^(-(Inputs!$C$23+DCF!$S$43-1))+SUM(DCF!$E$75:$E$79))/Inputs!$C$31 -> 112.22105
C16: =Drivers!$H$91+(3-2)*$C$10 -> 0.0225 | D16: =(SUMPRODUCT(DCF!$L$45:$S$45,(1+D$12)^(-DCF!$L$46:$S$46))+Inputs!$C$56*IF(Inputs!$C$58=1,DCF!$S$23*(1+$C16)*DCF!$T$29*(1-Drivers!$H$94)*(1-$C16/Drivers!$H$93),DCF!$S$35*(1+$C16))/(D$12-$C16)*(1+D$12)^(-DCF!$S$46)+Inputs!$C$57*DCF!$S$25*Drivers!$H$95*(1+D$12)^(-(Inputs!$C$23+DCF!$S$43-1))+SUM(DCF!$E$75:$E$79))/Inputs!$C$31 -> 183.98067 | E16: =(SUMPRODUCT(DCF!$L$45:$S$45,(1+E$12)^(-DCF!$L$46:$S$46))+Inputs!$C$56*IF(Inputs!$C$58=1,DCF!$S$23*(1+$C16)*DCF!$T$29*(1-Drivers!$H$94)*(1-$C16/Drivers!$H$93),DCF!$S$35*(1+$C16))/(E$12-$C16)*(1+E$12)^(-DCF!$S$46)+Inputs!$C$57*DCF!$S$25*Drivers!$H$95*(1+E$12)^(-(Inputs!$C$23+DCF!$S$43-1))+SUM(DCF!$E$75:$E$79))/Inputs!$C$31 -> 166.93903 | F16: =(SUMPRODUCT(DCF!$L$45:$S$45,(1+F$12)^(-DCF!$L$46:$S$46))+Inputs!$C$56*IF(Inputs!$C$58=1,DCF!$S$23*(1+$C16)*DCF!$T$29*(1-Drivers!$H$94)*(1-$C16/Drivers!$H$93),DCF!$S$35*(1+$C16))/(F$12-$C16)*(1+F$12)^(-DCF!$S$46)+Inputs!$C$57*DCF!$S$25*Drivers!$H$95*(1+F$12)^(-(Inputs!$C$23+DCF!$S$43-1))+SUM(DCF!$E$75:$E$79))/Inputs!$C$31 -> 152.62672 | G16: =(SUMPRODUCT(DCF!$L$45:$S$45,(1+G$12)^(-DCF!$L$46:$S$46))+Inputs!$C$56*IF(Inputs!$C$58=1,DCF!$S$23*(1+$C16)*DCF!$T$29*(1-Drivers!$H$94)*(1-$C16/Drivers!$H$93),DCF!$S$35*(1+$C16))/(G$12-$C16)*(1+G$12)^(-DCF!$S$46)+Inputs!$C$57*DCF!$S$25*Drivers!$H$95*(1+G$12)^(-(Inputs!$C$23+DCF!$S$43-1))+SUM(DCF!$E$75:$E$79))/Inputs!$C$31 -> 140.43635 | H16: =(SUMPRODUCT(DCF!$L$45:$S$45,(1+H$12)^(-DCF!$L$46:$S$46))+Inputs!$C$56*IF(Inputs!$C$58=1,DCF!$S$23*(1+$C16)*DCF!$T$29*(1-Drivers!$H$94)*(1-$C16/Drivers!$H$93),DCF!$S$35*(1+$C16))/(H$12-$C16)*(1+H$12)^(-DCF!$S$46)+Inputs!$C$57*DCF!$S$25*Drivers!$H$95*(1+H$12)^(-(Inputs!$C$23+DCF!$S$43-1))+SUM(DCF!$E$75:$E$79))/Inputs!$C$31 -> 129.92835 | I16: =(SUMPRODUCT(DCF!$L$45:$S$45,(1+I$12)^(-DCF!$L$46:$S$46))+Inputs!$C$56*IF(Inputs!$C$58=1,DCF!$S$23*(1+$C16)*DCF!$T$29*(1-Drivers!$H$94)*(1-$C16/Drivers!$H$93),DCF!$S$35*(1+$C16))/(I$12-$C16)*(1+I$12)^(-DCF!$S$46)+Inputs!$C$57*DCF!$S$25*Drivers!$H$95*(1+I$12)^(-(Inputs!$C$23+DCF!$S$43-1))+SUM(DCF!$E$75:$E$79))/Inputs!$C$31 -> 120.77677 | J16: =(SUMPRODUCT(DCF!$L$45:$S$45,(1+J$12)^(-DCF!$L$46:$S$46))+Inputs!$C$56*IF(Inputs!$C$58=1,DCF!$S$23*(1+$C16)*DCF!$T$29*(1-Drivers!$H$94)*(1-$C16/Drivers!$H$93),DCF!$S$35*(1+$C16))/(J$12-$C16)*(1+J$12)^(-DCF!$S$46)+Inputs!$C$57*DCF!$S$25*Drivers!$H$95*(1+J$12)^(-(Inputs!$C$23+DCF!$S$43-1))+SUM(DCF!$E$75:$E$79))/Inputs!$C$31 -> 112.73477
C17: =Drivers!$H$91+(4-2)*$C$10 -> 0.025 | D17: =(SUMPRODUCT(DCF!$L$45:$S$45,(1+D$12)^(-DCF!$L$46:$S$46))+Inputs!$C$56*IF(Inputs!$C$58=1,DCF!$S$23*(1+$C17)*DCF!$T$29*(1-Drivers!$H$94)*(1-$C17/Drivers!$H$93),DCF!$S$35*(1+$C17))/(D$12-$C17)*(1+D$12)^(-DCF!$S$46)+Inputs!$C$57*DCF!$S$25*Drivers!$H$95*(1+D$12)^(-(Inputs!$C$23+DCF!$S$43-1))+SUM(DCF!$E$75:$E$79))/Inputs!$C$31 -> 187.55532 | E17: =(SUMPRODUCT(DCF!$L$45:$S$45,(1+E$12)^(-DCF!$L$46:$S$46))+Inputs!$C$56*IF(Inputs!$C$58=1,DCF!$S$23*(1+$C17)*DCF!$T$29*(1-Drivers!$H$94)*(1-$C17/Drivers!$H$93),DCF!$S$35*(1+$C17))/(E$12-$C17)*(1+E$12)^(-DCF!$S$46)+Inputs!$C$57*DCF!$S$25*Drivers!$H$95*(1+E$12)^(-(Inputs!$C$23+DCF!$S$43-1))+SUM(DCF!$E$75:$E$79))/Inputs!$C$31 -> 169.55211 | F17: =(SUMPRODUCT(DCF!$L$45:$S$45,(1+F$12)^(-DCF!$L$46:$S$46))+Inputs!$C$56*IF(Inputs!$C$58=1,DCF!$S$23*(1+$C17)*DCF!$T$29*(1-Drivers!$H$94)*(1-$C17/Drivers!$H$93),DCF!$S$35*(1+$C17))/(F$12-$C17)*(1+F$12)^(-DCF!$S$46)+Inputs!$C$57*DCF!$S$25*Drivers!$H$95*(1+F$12)^(-(Inputs!$C$23+DCF!$S$43-1))+SUM(DCF!$E$75:$E$79))/Inputs!$C$31 -> 154.54858 | G17: =(SUMPRODUCT(DCF!$L$45:$S$45,(1+G$12)^(-DCF!$L$46:$S$46))+Inputs!$C$56*IF(Inputs!$C$58=1,DCF!$S$23*(1+$C17)*DCF!$T$29*(1-Drivers!$H$94)*(1-$C17/Drivers!$H$93),DCF!$S$35*(1+$C17))/(G$12-$C17)*(1+G$12)^(-DCF!$S$46)+Inputs!$C$57*DCF!$S$25*Drivers!$H$95*(1+G$12)^(-(Inputs!$C$23+DCF!$S$43-1))+SUM(DCF!$E$75:$E$79))/Inputs!$C$31 -> 141.85156 | H17: =(SUMPRODUCT(DCF!$L$45:$S$45,(1+H$12)^(-DCF!$L$46:$S$46))+Inputs!$C$56*IF(Inputs!$C$58=1,DCF!$S$23*(1+$C17)*DCF!$T$29*(1-Drivers!$H$94)*(1-$C17/Drivers!$H$93),DCF!$S$35*(1+$C17))/(H$12-$C17)*(1+H$12)^(-DCF!$S$46)+Inputs!$C$57*DCF!$S$25*Drivers!$H$95*(1+H$12)^(-(Inputs!$C$23+DCF!$S$43-1))+SUM(DCF!$E$75:$E$79))/Inputs!$C$31 -> 130.96629 | I17: =(SUMPRODUCT(DCF!$L$45:$S$45,(1+I$12)^(-DCF!$L$46:$S$46))+Inputs!$C$56*IF(Inputs!$C$58=1,DCF!$S$23*(1+$C17)*DCF!$T$29*(1-Drivers!$H$94)*(1-$C17/Drivers!$H$93),DCF!$S$35*(1+$C17))/(I$12-$C17)*(1+I$12)^(-DCF!$S$46)+Inputs!$C$57*DCF!$S$25*Drivers!$H$95*(1+I$12)^(-(Inputs!$C$23+DCF!$S$43-1))+SUM(DCF!$E$75:$E$79))/Inputs!$C$31 -> 121.5301 | J17: =(SUMPRODUCT(DCF!$L$45:$S$45,(1+J$12)^(-DCF!$L$46:$S$46))+Inputs!$C$56*IF(Inputs!$C$58=1,DCF!$S$23*(1+$C17)*DCF!$T$29*(1-Drivers!$H$94)*(1-$C17/Drivers!$H$93),DCF!$S$35*(1+$C17))/(J$12-$C17)*(1+J$12)^(-DCF!$S$46)+Inputs!$C$57*DCF!$S$25*Drivers!$H$95*(1+J$12)^(-(Inputs!$C$23+DCF!$S$43-1))+SUM(DCF!$E$75:$E$79))/Inputs!$C$31 -> 113.27116
B19: 2. DCF value per share (NOK) – WACC vs. exit multiple (exit-multiple method only)
B20: Exit multiple step | C20: 1
C22: Multiple \ WACC | D22: =WACC!$C$34+(0-3)*$C$9 -> 0.074875829 | E22: =WACC!$C$34+(1-3)*$C$9 -> 0.079875829 | F22: =WACC!$C$34+(2-3)*$C$9 -> 0.084875829 | G22: =WACC!$C$34+(3-3)*$C$9 -> 0.089875829 | H22: =WACC!$C$34+(4-3)*$C$9 -> 0.094875829 | I22: =WACC!$C$34+(5-3)*$C$9 -> 0.099875829 | J22: =WACC!$C$34+(6-3)*$C$9 -> 0.10487583
C23: =Drivers!$H$95+(0-2)*$C$20 -> 6.5 | D23: =(SUMPRODUCT(DCF!$L$45:$S$45,(1+D$22)^(-DCF!$L$46:$S$46))+DCF!$S$25*$C23*(1+D$22)^(-(Inputs!$C$23+DCF!$S$43-1))+SUM(DCF!$E$75:$E$79))/Inputs!$C$31 -> 131.64342 | E23: =(SUMPRODUCT(DCF!$L$45:$S$45,(1+E$22)^(-DCF!$L$46:$S$46))+DCF!$S$25*$C23*(1+E$22)^(-(Inputs!$C$23+DCF!$S$43-1))+SUM(DCF!$E$75:$E$79))/Inputs!$C$31 -> 127.77565 | F23: =(SUMPRODUCT(DCF!$L$45:$S$45,(1+F$22)^(-DCF!$L$46:$S$46))+DCF!$S$25*$C23*(1+F$22)^(-(Inputs!$C$23+DCF!$S$43-1))+SUM(DCF!$E$75:$E$79))/Inputs!$C$31 -> 124.04282 | G23: =(SUMPRODUCT(DCF!$L$45:$S$45,(1+G$22)^(-DCF!$L$46:$S$46))+DCF!$S$25*$C23*(1+G$22)^(-(Inputs!$C$23+DCF!$S$43-1))+SUM(DCF!$E$75:$E$79))/Inputs!$C$31 -> 120.43949 | H23: =(SUMPRODUCT(DCF!$L$45:$S$45,(1+H$22)^(-DCF!$L$46:$S$46))+DCF!$S$25*$C23*(1+H$22)^(-(Inputs!$C$23+DCF!$S$43-1))+SUM(DCF!$E$75:$E$79))/Inputs!$C$31 -> 116.96046 | I23: =(SUMPRODUCT(DCF!$L$45:$S$45,(1+I$22)^(-DCF!$L$46:$S$46))+DCF!$S$25*$C23*(1+I$22)^(-(Inputs!$C$23+DCF!$S$43-1))+SUM(DCF!$E$75:$E$79))/Inputs!$C$31 -> 113.60077 | J23: =(SUMPRODUCT(DCF!$L$45:$S$45,(1+J$22)^(-DCF!$L$46:$S$46))+DCF!$S$25*$C23*(1+J$22)^(-(Inputs!$C$23+DCF!$S$43-1))+SUM(DCF!$E$75:$E$79))/Inputs!$C$31 -> 110.35568
C24: =Drivers!$H$95+(1-2)*$C$20 -> 7.5 | D24: =(SUMPRODUCT(DCF!$L$45:$S$45,(1+D$22)^(-DCF!$L$46:$S$46))+DCF!$S$25*$C24*(1+D$22)^(-(Inputs!$C$23+DCF!$S$43-1))+SUM(DCF!$E$75:$E$79))/Inputs!$C$31 -> 144.99027 | E24: =(SUMPRODUCT(DCF!$L$45:$S$45,(1+E$22)^(-DCF!$L$46:$S$46))+DCF!$S$25*$C24*(1+E$22)^(-(Inputs!$C$23+DCF!$S$43-1))+SUM(DCF!$E$75:$E$79))/Inputs!$C$31 -> 140.67848 | F24: =(SUMPRODUCT(DCF!$L$45:$S$45,(1+F$22)^(-DCF!$L$46:$S$46))+DCF!$S$25*$C24*(1+F$22)^(-(Inputs!$C$23+DCF!$S$43-1))+SUM(DCF!$E$75:$E$79))/Inputs!$C$31 -> 136.51834 | G24: =(SUMPRODUCT(DCF!$L$45:$S$45,(1+G$22)^(-DCF!$L$46:$S$46))+DCF!$S$25*$C24*(1+G$22)^(-(Inputs!$C$23+DCF!$S$43-1))+SUM(DCF!$E$75:$E$79))/Inputs!$C$31 -> 132.50373 | H24: =(SUMPRODUCT(DCF!$L$45:$S$45,(1+H$22)^(-DCF!$L$46:$S$46))+DCF!$S$25*$C24*(1+H$22)^(-(Inputs!$C$23+DCF!$S$43-1))+SUM(DCF!$E$75:$E$79))/Inputs!$C$31 -> 128.62876 | I24: =(SUMPRODUCT(DCF!$L$45:$S$45,(1+I$22)^(-DCF!$L$46:$S$46))+DCF!$S$25*$C24*(1+I$22)^(-(Inputs!$C$23+DCF!$S$43-1))+SUM(DCF!$E$75:$E$79))/Inputs!$C$31 -> 124.88785 | J24: =(SUMPRODUCT(DCF!$L$45:$S$45,(1+J$22)^(-DCF!$L$46:$S$46))+DCF!$S$25*$C24*(1+J$22)^(-(Inputs!$C$23+DCF!$S$43-1))+SUM(DCF!$E$75:$E$79))/Inputs!$C$31 -> 121.27563
C25: =Drivers!$H$95+(2-2)*$C$20 -> 8.5 | D25: =(SUMPRODUCT(DCF!$L$45:$S$45,(1+D$22)^(-DCF!$L$46:$S$46))+DCF!$S$25*$C25*(1+D$22)^(-(Inputs!$C$23+DCF!$S$43-1))+SUM(DCF!$E$75:$E$79))/Inputs!$C$31 -> 158.33713 | E25: =(SUMPRODUCT(DCF!$L$45:$S$45,(1+E$22)^(-DCF!$L$46:$S$46))+DCF!$S$25*$C25*(1+E$22)^(-(Inputs!$C$23+DCF!$S$43-1))+SUM(DCF!$E$75:$E$79))/Inputs!$C$31 -> 153.58131 | F25: =(SUMPRODUCT(DCF!$L$45:$S$45,(1+F$22)^(-DCF!$L$46:$S$46))+DCF!$S$25*$C25*(1+F$22)^(-(Inputs!$C$23+DCF!$S$43-1))+SUM(DCF!$E$75:$E$79))/Inputs!$C$31 -> 148.99387 | G25: =(SUMPRODUCT(DCF!$L$45:$S$45,(1+G$22)^(-DCF!$L$46:$S$46))+DCF!$S$25*$C25*(1+G$22)^(-(Inputs!$C$23+DCF!$S$43-1))+SUM(DCF!$E$75:$E$79))/Inputs!$C$31 -> 144.56796 | H25: =(SUMPRODUCT(DCF!$L$45:$S$45,(1+H$22)^(-DCF!$L$46:$S$46))+DCF!$S$25*$C25*(1+H$22)^(-(Inputs!$C$23+DCF!$S$43-1))+SUM(DCF!$E$75:$E$79))/Inputs!$C$31 -> 140.29706 | I25: =(SUMPRODUCT(DCF!$L$45:$S$45,(1+I$22)^(-DCF!$L$46:$S$46))+DCF!$S$25*$C25*(1+I$22)^(-(Inputs!$C$23+DCF!$S$43-1))+SUM(DCF!$E$75:$E$79))/Inputs!$C$31 -> 136.17492 | J25: =(SUMPRODUCT(DCF!$L$45:$S$45,(1+J$22)^(-DCF!$L$46:$S$46))+DCF!$S$25*$C25*(1+J$22)^(-(Inputs!$C$23+DCF!$S$43-1))+SUM(DCF!$E$75:$E$79))/Inputs!$C$31 -> 132.19559
C26: =Drivers!$H$95+(3-2)*$C$20 -> 9.5 | D26: =(SUMPRODUCT(DCF!$L$45:$S$45,(1+D$22)^(-DCF!$L$46:$S$46))+DCF!$S$25*$C26*(1+D$22)^(-(Inputs!$C$23+DCF!$S$43-1))+SUM(DCF!$E$75:$E$79))/Inputs!$C$31 -> 171.68398 | E26: =(SUMPRODUCT(DCF!$L$45:$S$45,(1+E$22)^(-DCF!$L$46:$S$46))+DCF!$S$25*$C26*(1+E$22)^(-(Inputs!$C$23+DCF!$S$43-1))+SUM(DCF!$E$75:$E$79))/Inputs!$C$31 -> 166.48413 | F26: =(SUMPRODUCT(DCF!$L$45:$S$45,(1+F$22)^(-DCF!$L$46:$S$46))+DCF!$S$25*$C26*(1+F$22)^(-(Inputs!$C$23+DCF!$S$43-1))+SUM(DCF!$E$75:$E$79))/Inputs!$C$31 -> 161.46939 | G26: =(SUMPRODUCT(DCF!$L$45:$S$45,(1+G$22)^(-DCF!$L$46:$S$46))+DCF!$S$25*$C26*(1+G$22)^(-(Inputs!$C$23+DCF!$S$43-1))+SUM(DCF!$E$75:$E$79))/Inputs!$C$31 -> 156.6322 | H26: =(SUMPRODUCT(DCF!$L$45:$S$45,(1+H$22)^(-DCF!$L$46:$S$46))+DCF!$S$25*$C26*(1+H$22)^(-(Inputs!$C$23+DCF!$S$43-1))+SUM(DCF!$E$75:$E$79))/Inputs!$C$31 -> 151.96537 | I26: =(SUMPRODUCT(DCF!$L$45:$S$45,(1+I$22)^(-DCF!$L$46:$S$46))+DCF!$S$25*$C26*(1+I$22)^(-(Inputs!$C$23+DCF!$S$43-1))+SUM(DCF!$E$75:$E$79))/Inputs!$C$31 -> 147.462 | J26: =(SUMPRODUCT(DCF!$L$45:$S$45,(1+J$22)^(-DCF!$L$46:$S$46))+DCF!$S$25*$C26*(1+J$22)^(-(Inputs!$C$23+DCF!$S$43-1))+SUM(DCF!$E$75:$E$79))/Inputs!$C$31 -> 143.11554
C27: =Drivers!$H$95+(4-2)*$C$20 -> 10.5 | D27: =(SUMPRODUCT(DCF!$L$45:$S$45,(1+D$22)^(-DCF!$L$46:$S$46))+DCF!$S$25*$C27*(1+D$22)^(-(Inputs!$C$23+DCF!$S$43-1))+SUM(DCF!$E$75:$E$79))/Inputs!$C$31 -> 185.03083 | E27: =(SUMPRODUCT(DCF!$L$45:$S$45,(1+E$22)^(-DCF!$L$46:$S$46))+DCF!$S$25*$C27*(1+E$22)^(-(Inputs!$C$23+DCF!$S$43-1))+SUM(DCF!$E$75:$E$79))/Inputs!$C$31 -> 179.38696 | F27: =(SUMPRODUCT(DCF!$L$45:$S$45,(1+F$22)^(-DCF!$L$46:$S$46))+DCF!$S$25*$C27*(1+F$22)^(-(Inputs!$C$23+DCF!$S$43-1))+SUM(DCF!$E$75:$E$79))/Inputs!$C$31 -> 173.94491 | G27: =(SUMPRODUCT(DCF!$L$45:$S$45,(1+G$22)^(-DCF!$L$46:$S$46))+DCF!$S$25*$C27*(1+G$22)^(-(Inputs!$C$23+DCF!$S$43-1))+SUM(DCF!$E$75:$E$79))/Inputs!$C$31 -> 168.69644 | H27: =(SUMPRODUCT(DCF!$L$45:$S$45,(1+H$22)^(-DCF!$L$46:$S$46))+DCF!$S$25*$C27*(1+H$22)^(-(Inputs!$C$23+DCF!$S$43-1))+SUM(DCF!$E$75:$E$79))/Inputs!$C$31 -> 163.63367 | I27: =(SUMPRODUCT(DCF!$L$45:$S$45,(1+I$22)^(-DCF!$L$46:$S$46))+DCF!$S$25*$C27*(1+I$22)^(-(Inputs!$C$23+DCF!$S$43-1))+SUM(DCF!$E$75:$E$79))/Inputs!$C$31 -> 158.74908 | J27: =(SUMPRODUCT(DCF!$L$45:$S$45,(1+J$22)^(-DCF!$L$46:$S$46))+DCF!$S$25*$C27*(1+J$22)^(-(Inputs!$C$23+DCF!$S$43-1))+SUM(DCF!$E$75:$E$79))/Inputs!$C$31 -> 154.03549
B29: 3. DCF value per share (NOK) – change in revenue growth vs. change in EBITDA margin (data table)
B30: Rows: change in annual volume growth (segment mode) or like-for-like growth (location mode) for all segments. Columns: change in EBITDA margin (via other opex).
C32: =DCF!$E$83 -> 139.11051 | D32: -0.02 | E32: -0.01 | F32: 0 | G32: 0.01 | H32: 0.02
C33: -0.02 | D33: 76.580857 | E33: 84.072364 | F33: 91.563871 | G33: 99.055378 | H33: 106.54689
C34: -0.01 | D34: 98.570629 | E34: 106.57718 | F34: 114.58373 | G34: 122.59029 | H34: 130.59684
C35: 0 | D35: 122.00005 | E35: 130.55528 | F35: 139.11051 | G35: 147.66573 | H35: 156.22096
C36: 0.01 | D36: 146.95295 | E36: 156.09244 | F36: 165.23193 | G36: 174.37142 | H36: 183.51091
C37: 0.02 | D37: 173.51729 | E37: 183.27868 | F37: 193.04007 | G37: 202.80146 | H37: 212.56285
B39: 4. Scenario analysis – Bear / Base / Bull (data table on the scenario switch)
C40: Scenario | D40: Revenue CAGR (last actual → final year) | E40: Revenue, final forecast year (NOKm) | F40: EBIT adj. margin, final year | G40: FCFF, final forecast year (NOKm) | H40: Enterprise value (NOKm) | I40: DCF value per share (NOK) | J40: Upside to DCF value | K40: Blended fair value (NOK) | L40: Target price (NOK) | M40: Upside to target price | N40: Recommendation | O40: ="Revenue "&Model!L$5 -> Revenue 2026E | P40: ="Revenue "&Model!M$5 -> Revenue 2027E | Q40: ="Revenue "&Model!N$5 -> Revenue 2028E | R40: ="Revenue "&Model!O$5 -> Revenue 2029E | S40: ="Revenue "&Model!P$5 -> Revenue 2030E | T40: ="Revenue "&Model!Q$5 -> Revenue 2031E | U40: ="Revenue "&Model!R$5 -> Revenue 2032E | V40: ="Revenue "&Model!S$5 -> Revenue 2033E | W40: ="EBIT adj. "&Model!L$5 -> EBIT adj. 2026E | X40: ="EBIT adj. "&Model!M$5 -> EBIT adj. 2027E | Y40: ="EBIT adj. "&Model!N$5 -> EBIT adj. 2028E | Z40: ="EBIT adj. "&Model!O$5 -> EBIT adj. 2029E | AA40: ="EBIT adj. "&Model!P$5 -> EBIT adj. 2030E | AB40: ="EBIT adj. "&Model!Q$5 -> EBIT adj. 2031E | AC40: ="EBIT adj. "&Model!R$5 -> EBIT adj. 2032E | AD40: ="EBIT adj. "&Model!S$5 -> EBIT adj. 2033E
